Workbook
Name AMAZONAS: DatosPruebaEmp!$AE$3:$AE$13
Name ANTIOQUIA: DatosPruebaEmp!$AF$3:$AF$127
Name ARAUCA: DatosPruebaEmp!$AG$3:$AG$9
Name ATLANTICO: DatosPruebaEmp!$AH$3:$AH$25
Name BOGOTA_D.E.: DatosPruebaEmp!$AI$3
Name BOLIVAR: DatosPruebaEmp!$AJ$3:$AJ$48
Name BOYACA: DatosPruebaEmp!$AK$3:$AK$125
Name CALDAS: DatosPruebaEmp!$AL$3:$AL$29
Name CAQUETA: DatosPruebaEmp!$AM$3:$AM$18
Name CASANARE: DatosPruebaEmp!$AN$3:$AN$21
Name CAUCA: DatosPruebaEmp!$AO$3:$AO$44
Name CESAR: DatosPruebaEmp!$AP$3:$AP$27
Name CHOCO: DatosPruebaEmp!$AQ$3:$AQ$32
Name CORDOBA: DatosPruebaEmp!$AR$3:$AR$32
Name CUNDINAMARCA: DatosPruebaEmp!$AS$3:$AS$118
Name Encabezados: #REF!
Name GUAINIA: DatosPruebaEmp!$AT$3:$AT$11
Name GUAVIARE: DatosPruebaEmp!$AU$3:$AU$6
Name HUILA: DatosPruebaEmp!$AV$3:$AV$39
Name LA_GUAJIRA: DatosPruebaEmp!$AW$3:$AW$17
Name MAGDALENA: DatosPruebaEmp!$AX$3:$AX$32
Name META: DatosPruebaEmp!$AY$3:$AY$31
Name NARIÑO: DatosPruebaEmp!$AZ$3:$AZ$66
Name NORTE_DE_SANTANDER: DatosPruebaEmp!$BA$3:$BA$42
Name PUTUMAYO: DatosPruebaEmp!$BB$3:$BB$15
Name QUINDIO: DatosPruebaEmp!$BC$3:$BC$14
Name RGAFP: DatosPruebaEmp!$G$3:$G$12
Name RGALTORIESGO: DatosPruebaEmp!$P$3:$P$9
Name RGARP: DatosPruebaEmp!$K$3:$K$14
Name RGCCF: DatosPruebaEmp!$J$3:$J$46
Name RGCENTRABAJO: DatosPruebaEmp!$B$3:$B$27
Name RGCLASERIESGO: DatosPruebaEmp!$L$3
Name RGDIVIDEPTO: DatosPruebaEmp!$AD$3:$AD$35
Name RGEPS: DatosPruebaEmp!$I$3:$I$47
Name RGETIQUETAS: DatosPruebaEmp!$BR$3
Name RGGRUPOPOB: DatosPruebaEmp!$AC$3:$AC$16
Name RGINDALTORIESGO: DatosPruebaEmp!$H$3:$H$7
Name RGNOVEDADES: DatosPruebaEmp!$BO$3:$BO$15
Name RGNOVEDADSLN: DatosPruebaEmp!$W$3:$W$5
Name RGNOVEDADSLN2: DatosPruebaEmp!$X$3:$X$4
Name RGNOVEDADVAC: DatosPruebaEmp!$BN$3:$BN$5
Name RGSINO: DatosPruebaEmp!$M$3:$M$4
Name RGSINOVACIO: DatosPruebaEmp!$N$3:$N$5
Name RGSUBTIPOSCOT: DatosPruebaEmp!$F$3:$F$13
Name RGSUCURSALES: DatosPruebaEmp!$A$3:$A$9
Name RGTARIFAARL: DatosPruebaEmp!$Q$3:$Q$8
Name RGTARIFAARL2: DatosPruebaEmp!$R$3:$R$8
Name RGTARIFAPENSION: DatosPruebaEmp!$Y$3:$Y$4
Name RGTARIFASCCF: DatosPruebaEmp!$O$3:$O$6
Name RGTIPOCORRECCIONES: DatosPruebaEmp!$V$3:$V$5
Name RGTIPOING: DatosPruebaEmp!$AA$3:$AA$4
Name RGTIPOINGLIQ: DatosPruebaEmp!$BL$3:$BL$6
Name RGTIPOPRESENTACION: DatosPruebaEmp!$BP$3:$BP$6
Name RGTIPORET: DatosPruebaEmp!$AB$3:$AB$6
Name RGTIPORETLIQ: DatosPruebaEmp!$BM$3:$BM$7
Name RGTIPOSAPORTANTES: DatosPruebaEmp!$D$3:$D$10
Name RGTIPOSCOT: DatosPruebaEmp!$E$3:$E$38
Name RGTIPOSDOCS: DatosPruebaEmp!$S$3:$S$11
Name RGTIPOSDOCSNIT: DatosPruebaEmp!$T$3:$T$11
Name RGTIPOSNOVINGRET: DatosPruebaEmp!$U$3:$U$4

Sheet DatosPruebaEmp
A1: 0-CENTRO TRABAJO 0 | B1: 1-CENTRO TRABAJO 1 | C1: 10-CENTRO TRABAJO 10 | D1: 15-CENTRO TRABAJO 15 | E1: 24-CENTRO TRABAJO 24 | F1: 3-CENTRO TRABAJO 3 | G1: 30-CENTRO TRABAJO 30 | H1: 33-CENTRO TRABAJO 33 | I1: 4-CENTRO TRABAJO 4 | J1: 40-CENTRO TRABAJO 40 | K1: 50-CENTRO TRABAJO 50 | L1: 57-CENTRO TRABAJO 57 | M1: 6-CENTRO TRABAJO 6 | N1: 67-CENTRO TRABAJO 67 | O1: 696-CENTRO TRABAJO 696 | P1: 8-CENTRO TRABAJO 8 | Q1: 01-PRINCIPAL | R1: 2-ROSAL | S1: 33-CAJAMAG | T1: 31-GUA | U1: 1-RIESGO 01 | V1: 696-RIESGO 5 | W1: 04-SANTANDER | X1: 50-CENTRO 05 | Y1: 05-OBRA
A3: NINGUNA | B3: CENTRO TRABAJO 0 | C3: E - Planilla Empleados Empresas | D3: EMPLEADOR | E3: 1. DEPENDIENTE | F3: NINGUNO | G3: NINGUNA | H3: Sin Riesgo | I3: NINGUNA | J3: NINGUNA | K3: NINGUNA | L3: NINGUNA | M3: NO | N3: NO | O3: NINGUNA | P3: SIN RIESGO | Q3: NINGUNA | R3: 0 | S3: CC | T3: CC | U3: INGRESO (ING) | V3: ACTUAL | W3: NO | X3: LICENCIA NO REMUNERADA | Y3: TARIFA DEL EMPLEADOR | Z3: VARIACIÓN PERMANENTE DE SALARIO (VSP) | AA3: Todos los sistemas (ARL, AFP, CCF, EPS) | AB3: Todos los sistemas (ARL, AFP, CCF, EPS) | AC3: NINGUNO | AD3: AMAZONAS | AE3: EL ENCANTO | AF3: ABEJORRAL | AG3: ARAUCA | AH3: BARANOA | AI3: BOGOTA | AJ3: ACHI | AK3: ALMEIDA | AL3: AGUADAS | AM3: ALBANIA | AN3: AGUAZUL | AO3: ALMAGUER | AP3: AGUACHICA | AQ3: ACANDI | AR3: AYAPEL | AS3: AGUA DE DIOS | AT3: BARRANCO MINAS | AU3: CALAMAR | AV3: ACEVEDO | AW3: ALBANIA | AX3: ALGARROBO | AY3: ACACIAS | AZ3: ALBAN | BA3: ABREGO | BB3: COLON | BC3: ARMENIA | BD3: APIA | BE3: PROVIDENCIA | BF3: AGUADA | BG3: BUENAVISTA | BH3: ALPUJARRA | BI3: ALCALA | BJ3: CARURU | BK3: CUMARIBO | BL3: Todos los sistemas (ARL, AFP, CCF, EPS) | BM3: Todos los sistemas (ARL, AFP, CCF, EPS) | BN3: VACACIONES | BO3: INCAPACIDAD GENERAL (IGE) | BP3: SUCURSAL | BQ3: VACACIONES | BR3: NINGUNA
A4: PRINCIPAL | B4: CENTRO TRABAJO 1 | C4: A - Planilla Empleados Adicionales | D4: INDEPENDIENTE | E4: 12. APRENDICES EN ETAPA LECTIVA | F4: 1. DEPENDIENTE PENSIONADO ACTIVO | G4: CAXDAC | H4: 1. Actividades de alto riesgo | I4: A.I.C. | J4: CAFABA | K4: ALFA | M4: SI | N4: SI | O4: 0.006 | P4: ALTO RIESGO | Q4: 0.00522 | R4: 0.00522 | S4: CE | T4: CE | U4: RETIRO DE LA EMPRESA (RET) | V4: CORRECCIÓN | W4: LICENCIA NO REMUNERADA | X4: COMISIÓN DE SERVICIO | Y4: TARIFA TOTAL | Z4: VARIACIÓN TRANSITORIA DE SALARIO (VST) | AA4: Administradora de Riesgos Laborales (ARL) | AB4: Administradora de Fondo de Pensiones (AFP) | AC4: CONCEJALES I | AD4: ANTIOQUIA | AE4: LA CHORRERA | AF4: ABRIAQUI | AG4: ARAUQUITA | AH4: BARRANQUILLA | AJ4: ALTOS DEL ROSARIO | AK4: AQUITANIA | AL4: ANSERMA | AM4: BELEN DE LOS ANDAQUIES | AN4: CHAMEZA | AO4: ARGELIA | AP4: AGUSTIN CODAZZI | AQ4: ALTO BAUDO | AR4: BUENAVISTA | AS4: ALBAN | AT4: CACAHUAL | AU4: EL RETORNO | AV4: AGRADO | AW4: BARRANCAS | AX4: ARACATACA | AY4: BARRANCA DE UPIA | AZ4: ALDANA | BA4: ARBOLEDAS | BB4: LEGUIZAMO | BC4: BUENAVISTA | BD4: BALBOA | BE4: SAN ANDRES | BF4: ALBANIA | BG4: CAIMITO | BH4: ALVARADO | BI4: ANDALUCIA | BJ4: MITU | BK4: LA PRIMAVERA | BL4: Administradora de Riesgos Laborales (ARL) | BM4: Administradora de Fondo de Pensiones (AFP) | BN4: LICENCIA REMUNERADA | BO4: INCAPACIDAD LABORAL (IRL) | BP4: ÚNICA | BQ4: LICENCIA REMUNERADA
A5: CAJAMAG | B5: CENTRO TRABAJO 10 | C5: I - Planilla Independientes | D5: ENTIDADES O UNIVERSIDADES PÚBLICAS CON RÉGIMEN ESPECIAL EN SALUD | E5: 15. DESEMPLEADO CON SUBSIDIO DE CAJA DE COMPENSACIÓN FAMILIAR | F5: 2. INDEPENDIENTE PENSIONADO ACTIVO | G5: COLFONDOS | H5: 2. Senadores | I5: ADRES - CONTRIBUCIÓN SOLIDARIA | J5: CAFAM | K5: ARL SURA | O5: 0.02 | P5: CTI | Q5: 0.01044 | R5: 0.01044 | S5: TI | T5: NIT | V5: NO | W5: COMISIÓN DE SERVICIO | AB5: Administradora de Riesgos Laborales (ARL) | AC5: CONCEJALES II | AD5: ARAUCA | AE5: LA PEDRERA | AF5: ALEJANDRIA | AG5: CRAVO NORTE | AH5: CAMPO DE LA CRUZ | AJ5: ARENAL | AK5: ARCABUCO | AL5: ARANZAZU | AM5: CARTAGENA DEL CHAIRA | AN5: HATO COROZAL | AO5: BALBOA | AP5: ASTREA | AQ5: ATRATO | AR5: CANALETE | AS5: ANAPOIMA | AT5: INIRIDA | AU5: MIRAFLORES | AV5: AIPE | AW5: DIBULLA | AX5: ARIGUANI | AY5: CABUYARO | AZ5: ANCUYA | BA5: BOCHALEMA | BB5: MOCOA | BC5: CALARCA | BD5: BELEN DE UMBRIA | BF5: ARATOCA | BG5: CHALAN | BH5: AMBALEMA | BI5: ANSERMANUEVO | BJ5: PACOA | BK5: PUERTO CARREÑO | BL5: Caja de Compensación Familiar (CCF) | BM5: Administradora de Riesgos Laborales (ARL) | BN5: NO | BO5: INGRESO (ING) | BP5: CONSOLIDADO
A6: GUAJIRA | B6: CENTRO TRABAJO 15 | C6: Y - Planilla Independientes Empresas | D6: COOPERATIVA Y PRE COOPERATIVA DE TRABAJO ASOCIADO | E6: 16. INDEPENDIENTE AGREMIADO O ASOCIADO | F6: 3. COTIZANTE NO OBLIGADO A COTIZACIÓN A PENSIONES POR EDAD | G6: COLPENSIONES | H6: 3. CTI | I6: ALIANSALUD EPS (ANTES COLMEDICA) | J6: CAFAMAZ | K6: COLMENA | O6: 0.04 | P6: ALTO RIESGO (6%) | Q6: 0.02436 | R6: 0.02436 | S6: RC | T6: TI | AB6: Caja de Compensación Familiar (CCF) | AC6: DESEMPLEADOS | AD6: ATLANTICO | AE6: LA VICTORIA | AF6: AMAGA | AG6: FORTUL | AH6: CANDELARIA | AJ6: ARJONA | AK6: BELEN | AL6: BELALCAZAR | AM6: CURILLO | AN6: LA SALINA | AO6: BOLIVAR | AP6: BECERRIL | AQ6: BAGADO | AR6: CERETE | AS6: ANOLAIMA | AT6: LA GUADALUPE | AU6: SAN JOSE DEL GUAVIARE | AV6: ALGECIRAS | AW6: DISTRACCION | AX6: CERRO SAN ANTONIO | AY6: CASTILLA LA NUEVA | AZ6: ARBOLEDA | BA6: BUCARASICA | BB6: ORITO | BC6: CIRCASIA | BD6: DOSQUEBRADAS | BF6: BARBOSA | BG6: COLOSO | BH6: ANZOATEGUI | BI6: ARGELIA | BJ6: PAPUNAUA | BK6: SANTA ROSALIA | BL6: NO | BM6: Caja de Compensación Familiar (CCF) | BO6: INICIO RESIDENCIA EN EL EXTERIOR (IRE) | BP6: DEPENDENCIA
A7: MEDELLIN | B7: CENTRO TRABAJO 24 | C7: S - Planilla Empleados de Independientes | D7: MISIÓN DIPLOMÁTICA | E7: 18. FUNCIONARIOS PÚBLICOS SIN TOPE MÁXIMO EN EL IBC | F7: 4. COTIZANTE CON REQUISITOS CUMPLIDOS PARA PENSIÓN | G7: FONPRECON | H7: 4. Aviadores | I7: ANAS WAYUU | J7: CAFASUR | K7: COLPATRIA ARP | P7: ALTO RIESGO (8.5%) | Q7: 0.0435 | R7: 0.0435 | S7: PA | T7: RC | AC7: DESOCUPADOS | AD7: BOGOTA_D.E. | AE7: LETICIA | AF7: AMALFI | AG7: PUERTO RONDON | AH7: GALAPA | AJ7: ARROYOHONDO | AK7: BERBEO | AL7: CHINCHINA | AM7: EL DONCELLO | AN7: MANI | AO7: BUENOS AIRES | AP7: BOSCONIA | AQ7: BAHIA SOLANO | AR7: CHIMA | AS7: APULO | AT7: MAPIRIPANA | AV7: ALTAMIRA | AW7: EL MOLINO | AX7: CHIBOLO | AY7: CUBARRAL | AZ7: BARBACOAS | BA7: CACHIRA | BB7: PUERTO ASIS | BC7: CORDOBA | BD7: GUATICA | BF7: BARICHARA | BG7: COROZAL | BH7: ARMERO | BI7: BOLIVAR | BJ7: TARAIRA | BM7: NO | BO7: LICENCIA DE MATERNIDAD (LMA)
A8: SANTANDER | B8: CENTRO TRABAJO 3 | C8: N - Planilla Correcciones | D8: ORGANIZACIÓN ADMINISTRADORA DEL PROGRAMA DE HOGARES DE BIENESTAR | E8: 19. APRENDICES EN ETAPA PRODUCTIVA | F8: 5. COTIZANTE CON INDEMNIZACIÓN SUSTITUTIVA O DEVOLUCIÓN DE SALDOS | G8: PENSIONES DE ANTIOQUIA | I8: ASMET SALUD EPS SAS | J8: CAJACOPI ATLANTICO | K8: COLSANITAS ARL | P8: AVIADORES | Q8: 0.0696 | R8: 0.0696 | S8: CD | T8: PA | AC8: DISCAPACITADOS | AD8: BOLIVAR | AE8: MIRITI - PARANA | AF8: ANDES | AG8: SARAVENA | AH8: JUAN DE ACOSTA | AJ8: BARRANCO DE LOBA | AK8: BETEITIVA | AL8: FILADELFIA | AM8: EL PAUJIL | AN8: MONTERREY | AO8: CAJIBIO | AP8: CHIMICHAGUA | AQ8: BAJO BAUDO | AR8: CHINU | AS8: ARBELAEZ | AT8: MORICHAL | AV8: BARAYA | AW8: FONSECA | AX8: CIENAGA | AY8: CUMARAL | AZ8: BELEN | BA8: CACOTA | BB8: PUERTO CAICEDO | BC8: FILANDIA | BD8: LA CELIA | BF8: BARRANCABERMEJA | BG8: COVEÑAS | BH8: ATACO | BI8: BUENAVENTURA | BJ8: YAVARATE | BO8: RETIRO DE LA EMPRESA (RET)
A9: TOLIMA | B9: CENTRO TRABAJO 30 | C9: M - Planilla Mora | D9: AGREMIACIÓN O ASOCIACIÓN | E9: 20. ESTUDIANTES | F9: 6. COTIZANTE PERTENECIENTE A UN RÉGIMEN EXCEPTUADO DE PENSIONES | G9: PORVENIR | I9: CAJACOPI ATLANTICO | J9: CAJAMAG | K9: FONDO DE RIESGOS LABORALES | P9: SENADORES | S9: SC | T9: CD | AC9: INDEPENDIENTES RURALES I | AD9: BOYACA | AE9: PUERTO ALEGRIA | AF9: ANGELOPOLIS | AG9: TAME | AH9: LURUACO | AJ9: CALAMAR | AK9: BOAVITA | AL9: LA DORADA | AM9: FLORENCIA | AN9: NUNCHIA | AO9: CALDONO | AP9: CHIRIGUANA | AQ9: BOJAYA | AR9: CIENAGA DE ORO | AS9: BELTRAN | AT9: PANA PANA | AV9: CAMPOALEGRE | AW9: HATONUEVO | AX9: CONCORDIA | AY9: EL CALVARIO | AZ9: BUESACO | BA9: CHINACOTA | BB9: PUERTO GUZMAN | BC9: GENOVA | BD9: LA VIRGINIA | BF9: BETULIA | BG9: EL ROBLE | BH9: CAJAMARCA | BI9: BUGALAGRANDE | BO9: SUSPENSIÓN TEMPORAL DEL CONTRATO DE TRABAJO (SLN)
B10: CENTRO TRABAJO 33 | C10: H - Plantilla Madres Comunitarias | D10: PAGADOR DE APORTES DE LOS CONCEJALES O EDILES | E10: 21. ESTUDIANTE Y RESIDENTE | F10: 9. PENSIONADO CON MESADA IGUAL A 25 SMLMV | G10: PROTECCION | I10: CAPITAL SALUD | J10: CAJASAI | K10: LA EQUIDAD SEGUROS | S10: PE | T10: PE | AC10: INDEPENDIENTES RURALES II | AD10: CALDAS | AE10: PUERTO ARICA | AF10: ANGOSTURA | AH10: MALAMBO | AJ10: CANTAGALLO | AK10: BOYACA | AL10: LA MERCED | AM10: LA MONTAÑITA | AN10: OROCUE | AO10: CALOTO | AP10: CURUMANI | AQ10: CARMEN DEL DARIEN | AR10: COTORRA | AS10: BITUIMA | AT10: PUERTO COLOMBIA | AV10: COLOMBIA | AW10: LA JAGUA DEL PILAR | AX10: EL BANCO | AY10: EL CASTILLO | AZ10: CHACHAGI | BA10: CHITAGA | BB10: SAN FRANCISCO | BC10: LA TEBAIDA | BD10: MARSELLA | BF10: BOLIVAR | BG10: GALERAS | BH10: CARMEN DE APICALA | BI10: CAICEDONIA | BO10: TIEMPO PARCIAL (TPR)
B11: CENTRO TRABAJO 4 | C11: T - Planilla Sistema General de Participación | E11: 22. PROFESOR DE ESTABLECIMIENTO PARTICULAR | F11: 10. COLOMBIANO RESIDENTE EN EL EXTERIOR | G11: SKANDIA | I11: CAPRESOCA | J11: CAJASAN | K11: MAPFRE COLOMBIA VIDA SEGUROS S.A. | S11: PT | T11: PT | AC11: INDEPENDIENTES RURALES III | AD11: CAQUETA | AE11: PUERTO NARIÑO | AF11: ANORI | AH11: MANATI | AJ11: CARTAGENA | AK11: BRICEÑO | AL11: MANIZALES | AM11: MILAN | AN11: PAZ DE ARIPORO | AO11: CORINTO | AP11: EL COPEY | AQ11: CERTEGUI | AR11: LA APARTADA | AS11: BOJACA | AT11: SAN FELIPE | AV11: ELIAS | AW11: MAICAO | AX11: EL PIÑON | AY11: EL DORADO | AZ11: COLON | BA11: CONVENCION | BB11: SAN MIGUEL | BC11: MONTENEGRO | BD11: MISTRATO | BF11: BUCARAMANGA | BG11: GUARANDA | BH11: CASABIANCA | BI11: CALI | BO11: VACACIONES (VAC)
B12: CENTRO TRABAJO 40 | C12: F - Planilla Faltante SGP | E12: 23. ESTUDIANTES DECRETO 055 | F12: 11. TAXISTA | G12: SKANDIA ALTERNATIVO | I12: COMFACHOCÓ | J12: COFREM | K12: POSITIVA COMPAÑIA DE SEGUROS | AC12: INDEPENDIENTES URBANOS I | AD12: CASANARE | AE12: PUERTO SANTANDER | AF12: ANZA | AH12: PALMAR DE VARELA | AJ12: CICUCO | AK12: BUENAVISTA | AL12: MANZANARES | AM12: MORELIA | AN12: PORE | AO12: EL TAMBO | AP12: EL PASO | AQ12: CONDOTO | AR12: LORICA | AS12: CABRERA | AV12: GARZON | AW12: MANAURE | AX12: EL RETEN | AY12: FUENTE DE ORO | AZ12: CONSACA | BA12: CUCUTA | BB12: SANTIAGO | BC12: PIJAO | BD12: PEREIRA | BF12: CABRERA | BG12: LA UNION | BH12: CHAPARRAL | BI12: CALIMA | BO12: VARIACIÓN HORAS LABORADAS (VHL)
B13: CENTRO TRABAJO 50 | C13: J - Planilla Aportes en Sentencia Judicial | E13: 3. INDEPENDIENTE | F13: 12. TAXISTA NO OBLIGADOS A COTIZAR PENSIÓN | I13: COMFAMILIAR GUAJIRA | J13: COLSUBSIDIO | K13: SEGUROS BOLIVAR | AC13: INDEPENDIENTES URBANOS II | AD13: CAUCA | AE13: TARAPACA | AF13: APARTADO | AH13: PIOJO | AJ13: CLEMENCIA | AK13: BUSBANZA | AL13: MARMATO | AM13: PUERTO RICO | AN13: RECETOR | AO13: FLORENCIA | AP13: GAMARRA | AQ13: EL CANTON DEL SAN PABLO | AR13: LOS CORDOBAS | AS13: CACHIPAY | AV13: GIGANTE | AW13: RIOHACHA | AX13: FUNDACION | AY13: GRANADA | AZ13: CONTADERO | BA13: CUCUTILLA | BB13: SIBUNDOY | BC13: QUIMBAYA | BD13: PUEBLO RICO | BF13: CALIFORNIA | BG13: LOS PALMITOS | BH13: COELLO | BI13: CANDELARIA | BO13: VARIACIÓN IBC PARAFISCALES (VIP)
B14: CENTRO TRABAJO 57 | C14: X – Planilla para el pago de empresa liquidada | E14: 30. DEPENDIENTE ENTIDADES O UNIVERSIDADES PÚBLICAS CON RÉGIMEN ESPECIAL EN SALUD | I14: COMFAMILIAR HUILA | J14: COMBARRANQUILLA | K14: SEGUROS DE VIDA AURORA | AC14: INDEPENDIENTES URBANOS III | AD14: CESAR | AF14: ARBOLETES | AH14: POLONUEVO | AJ14: CORDOBA | AK14: CALDAS | AL14: MARQUETALIA | AM14: SAN JOSE DEL FRAGUA | AN14: SABANALARGA | AO14: GUACHENÉ | AP14: GONZALEZ | AQ14: EL CARMEN DE ATRATO | AR14: MOMIL | AS14: CAJICA | AV14: GUADALUPE | AW14: SAN JUAN DEL CESAR | AX14: GUAMAL | AY14: GUAMAL | AZ14: CORDOBA | BA14: DURANIA | BB14: VALLE DEL GUAMUEZ | BC14: SALENTO | BD14: QUINCHIA | BF14: CAPITANEJO | BG14: MAJAGUAL | BH14: COYAIMA | BI14: CARTAGO | BO14: VARIACIÓN PERMANENTE DE SALARIO (VSP)
B15: CENTRO TRABAJO 6 | C15: K - Planilla Estudiantes | E15: 31. COOPERADO | I15: COMFAMILIAR NARIÑO | J15: COMCAJA | AC15: MADRE COMUNITARIA | AD15: CHOCO | AF15: ARGELIA | AH15: PONEDERA | AJ15: EL CARMEN DE BOLIVAR | AK15: CAMPOHERMOSO | AL15: MARULANDA | AM15: SAN VICENTE DEL CAGUAN | AN15: SACAMA | AO15: GUAPI | AP15: LA GLORIA | AQ15: EL LITORAL DEL SAN JUAN | AR15: MOÑITOS | AS15: CAPARRAPI | AV15: HOBO | AW15: URIBIA | AX15: NUEVA GRANADA | AY15: LA MACARENA | AZ15: CUASPUD | BA15: EL CARMEN | BB15: VILLAGARZON | BD15: SANTA ROSA DE CABAL | BF15: CARCASI | BG15: MORROA | BH15: CUNDAY | BI15: DAGUA | BO15: VARIACIÓN TRANSITORIA DE SALARIO (VST)
B16: CENTRO TRABAJO 67 | C16: O - Obligaciones Determinadas Por La UGPP | E16: 32. DIPLOMÁTICO, CONSULAR O FUNCIONARIO NO SOMETIDO A LEGISLACIÓN COLOMBIANA | I16: COMFAORIENTE | J16: COMFABOY | AC16: CONCEJALES III | AD16: CORDOBA | AF16: ARMENIA | AH16: PUERTO COLOMBIA | AJ16: EL GUAMO | AK16: CERINZA | AL16: NEIRA | AM16: SOLANO | AN16: SAN LUIS DE PALENQUE | AO16: INZA | AP16: LA JAGUA DE IBIRICO | AQ16: ISTMINA | AR16: MONTELIBANO | AS16: CAQUEZA | AV16: IQUIRA | AW16: URUMITA | AX16: PEDRAZA | AY16: LEJANIAS | AZ16: CUMBAL | BA16: EL TARRA | BD16: SANTUARIO | BF16: CEPITA | BG16: OVEJAS | BH16: DOLORES | BI16: EL AGUILA
B17: CENTRO TRABAJO 696 | C17: B - Piso Protección Total | E17: 34. CONCEJAL O EDIL DE BOGOTÁ D.C. | I17: COMFENALCO VALLE | J17: COMFACA | AD17: CUNDINAMARCA | AF17: BARBOSA | AH17: REPELON | AJ17: EL PEÑON | AK17: CHINAVITA | AL17: NORCASIA | AM17: SOLITA | AN17: TAMARA | AO17: JAMBALO | AP17: LA PAZ | AQ17: JURADO | AR17: MONTERIA | AS17: CARMEN DE CARUPA | AV17: ISNOS | AW17: VILLANUEVA | AX17: PIJIÑO DEL CARMEN | AY17: MAPIRIPAN | AZ17: CUMBITARA | BA17: EL ZULIA | BF17: CERRITO | BG17: PALMITO | BH17: ESPINAL | BI17: EL CAIRO
B18: CENTRO TRABAJO 8 | E18: 35. CONCEJAL NO AMPARADO CON PÓLIZA DE SALUD | I18: COMPARTA | J18: COMFACASANARE | AD18: GUAINIA | AF18: BELLO | AH18: SABANAGRANDE | AJ18: HATILLO DE LOBA | AK18: CHIQUINQUIRA | AL18: PACORA | AM18: VALPARAISO | AN18: TAURAMENA | AO18: LA SIERRA | AP18: MANAURE | AQ18: LLORO | AR18: PLANETA RICA | AS18: CHAGUANI | AV18: LA ARGENTINA | AX18: PIVIJAY | AY18: MESETAS | AZ18: EL CHARCO | BA18: GRAMALOTE | BF18: CHARALA | BG18: SAMPUES | BH18: FALAN | BI18: EL CERRITO
B19: PRINCIPAL | E19: 36. EDIL SIN PÓLIZA DE SALUD BENEFICIARIO DEL FSP | I19: COMPENSAR | J19: COMFACAUCA | AD19: GUAVIARE | AF19: BELMIRA | AH19: SABANALARGA | AJ19: MAGANGUE | AK19: CHIQUIZA | AL19: PALESTINA | AN19: TRINIDAD | AO19: LA VEGA | AP19: PAILITAS | AQ19: MEDIO ATRATO | AR19: PUEBLO NUEVO | AS19: CHIA | AV19: LA PLATA | AX19: PLATO | AY19: PUERTO CONCORDIA | AZ19: EL PEÑOL | BA19: HACARI | BF19: CHARTA | BG19: SAN BENITO ABAD | BH19: FLANDES | BI19: EL DOVIO
B20: ROSAL | E20: 4. MADRE SUSTITUTA | I20: CONVIDA | J20: COMFACESAR | AD20: HUILA | AF20: BETANIA | AH20: SANTA LUCIA | AJ20: MAHATES | AK20: CHISCAS | AL20: PENSILVANIA | AN20: VILLANUEVA | AO20: LOPEZ | AP20: PELAYA | AQ20: MEDIO BAUDO | AR20: PUERTO ESCONDIDO | AS20: CHIPAQUE | AV20: NATAGA | AX20: PUEBLOVIEJO | AY20: PUERTO GAITAN | AZ20: EL ROSARIO | BA20: HERRAN | BF20: CHIMA | BG20: SAN JUAN DE BETULIA | BH20: FRESNO | BI20: FLORIDA
B21: CAJAMAG | E21: 40. BENEFICIARIO DE UPC ADICIONAL | I21: COOMEVA | J21: COMFACHOCÓ | AD21: LA_GUAJIRA | AF21: BETULIA | AH21: SANTO TOMAS | AJ21: MARGARITA | AK21: CHITA | AL21: RIOSUCIO | AN21: YOPAL | AO21: MERCADERES | AP21: PUEBLO BELLO | AQ21: MEDIO SAN JUAN | AR21: PUERTO LIBERTADOR | AS21: CHOACHI | AV21: NEIVA | AX21: REMOLINO | AY21: PUERTO LLERAS | AZ21: EL TABLON DE GOMEZ | BA21: LA ESPERANZA | BF21: CHIPATA | BG21: SAN MARCOS | BH21: GUAMO | BI21: GINEBRA
B22: GUA | E22: 43. COTIZANTE VOLUNTARIO A PENSIONES CON PAGO POR TERCERO | I22: COOSALUD EPS | J22: COMFACOR | AD22: MAGDALENA | AF22: BRICEÑO | AH22: SOLEDAD | AJ22: MARIA LA BAJA | AK22: CHITARAQUE | AL22: RISARALDA | AO22: MIRANDA | AP22: RIO DE ORO | AQ22: NOVITA | AR22: PURISIMA | AS22: CHOCONTA | AV22: OPORAPA | AX22: SABANAS DE SAN ANGEL | AY22: PUERTO LOPEZ | AZ22: EL TAMBO | BA22: LA PLAYA | BF22: CIMITARRA | BG22: SAN ONOFRE | BH22: HERVEO | BI22: GUACARI
B23: RIESGO 01 | E23: 44. EMPLEO DE EMERGENCIA MAYOR A UN MES | I23: COOSALUD MOVILIDAD | J23: COMFACUNDI | AD23: META | AF23: BURITICA | AH23: SUAN | AJ23: MOMPOS | AK23: CHIVATA | AL23: SALAMINA | AO23: MORALES | AP23: SAN ALBERTO | AQ23: NUQUI | AR23: SAHAGUN | AS23: COGUA | AV23: PAICOL | AX23: SALAMINA | AY23: PUERTO RICO | AZ23: FRANCISCO PIZARRO | BA23: LABATECA | BF23: CONCEPCION | BG23: SAN PEDRO | BH23: HONDA | BI23: GUADALAJARA DE BUGA
B24: RIESGO 5 | E24: 45. EMPLEO DE EMERGENCIA MENOR A UN MES | I24: DUSAKAWI | J24: COMFAMA | AD24: NARIÑO | AF24: CACERES | AH24: TUBARA | AJ24: MONTECRISTO | AK24: CHIVOR | AL24: SAMANA | AO24: PADILLA | AP24: SAN DIEGO | AQ24: QUIBDO | AR24: SAN ANDRES SOTAVENTO | AS24: COTA | AV24: PALERMO | AX24: SAN SEBASTIAN DE BUENAVISTA | AY24: RESTREPO | AZ24: FUNES | BA24: LOS PATIOS | BF24: CONFINES | BG24: SANTIAGO DE TOLU | BH24: IBAGUE | BI24: JAMUNDI
B25: SANTANDER | E25: 47. DEPENDIENTE BENEFICIARIO DEL SISTEMA GENERAL DE PARTICIPACIONES | I25: EMPRESAS PUBLICAS DE MEDELLIN DEPARTAMENTO MEDICO | J25: COMFAMILIAR ATLANTICO | AD25: NORTE_DE_SANTANDER | AF25: CAICEDO | AH25: USIACURI | AJ25: MORALES | AK25: CIENEGA | AL25: SAN JOSE | AO25: PAEZ | AP25: SAN MARTIN | AQ25: RIO IRO | AR25: SAN ANTERO | AS25: CUCUNUBA | AV25: PALESTINA | AX25: SAN ZENON | AY25: SAN CARLOS DE GUAROA | AZ25: GUACHUCAL | BA25: LOURDES | BF25: CONTRATACION | BG25: SINCE | BH25: ICONONZO | BI25: LA CUMBRE
B26: CENTRO 05 | E26: 51. TRABAJADOR DE TIEMPO PARCIAL | I26: EMSSANAR | J26: COMFAMILIAR CAMACOL | AD26: PUTUMAYO | AF26: CALDAS | AJ26: NOROSI | AK26: COMBITA | AL26: SUPIA | AO26: PATIA | AP26: TAMALAMEQUE | AQ26: RIO QUITO | AR26: SAN BERNARDO DEL VIENTO | AS26: EL COLEGIO | AV26: PITAL | AX26: SANTA ANA | AY26: SAN JUAN DE ARAMA | AZ26: GUAITARILLA | BA26: MUTISCUA | BF26: COROMORO | BG26: SINCELEJO | BH26: LERIDA | BI26: LA UNION
B27: OBRA | E27: 52. BENEFICIARIO DEL MECANISMO DE PROTECCIÓN AL CESANTE | I27: EPS ECOOPSOS S.A.S | J27: COMFAMILIAR CARTAGENA | AD27: QUINDIO | AF27: CAMPAMENTO | AJ27: PINILLOS | AK27: COPER | AL27: VICTORIA | AO27: PIAMONTE | AP27: VALLEDUPAR | AQ27: RIOSUCIO | AR27: SAN CARLOS | AS27: EL PEÑON | AV27: PITALITO | AX27: SANTA BARBARA DE PINTO | AY27: SAN JUANITO | AZ27: GUALMATAN | BA27: OCAÑA | BF27: CURITI | BG27: SUCRE | BH27: LIBANO | BI27: LA VICTORIA
E28: 53. AFILIADO PARTICIPE | I28: EPS FAMILIAR DE COLOMBIA SAS | J28: COMFAMILIAR GUAJIRA | AD28: RISARALDA | AF28: CAÑASGORDAS | AJ28: REGIDOR | AK28: CORRALES | AL28: VILLAMARIA | AO28: PIENDAMO | AQ28: SAN JOSE DEL PALMAR | AR28: SAN JOSE DE URE | AS28: EL ROSAL | AV28: RIVERA | AX28: SANTA MARTA | AY28: SAN MARTIN | AZ28: ILES | BA28: PAMPLONA | BF28: EL CARMEN DE CHUCURI | BG28: TOLU VIEJO | BH28: MARIQUITA | BI28: OBANDO
E29: 54. PREPENSIONADO DE ENTIDAD EN LIQUIDACIÓN | I29: EPS MUTUAL SER | J29: COMFAMILIAR HUILA | AD29: SAN_ANDRES | AF29: CARACOLI | AJ29: RIO VIEJO | AK29: COVARACHIA | AL29: VITERBO | AO29: POPAYAN | AQ29: SIPI | AR29: SAN PELAYO | AS29: FACATATIVA | AV29: SALADOBLANCO | AX29: SITIONUEVO | AY29: URIBE | AZ29: IMUES | BA29: PAMPLONITA | BF29: EL GUACAMAYO | BH29: MELGAR | BI29: PALMIRA
E30: 55. AFILIADO PARTICIPE – DEPENDIENTE | I30: EPS SURA (ANTES SUSALUD) | J30: COMFAMILIAR NARIÑO | AD30: SANTANDER | AF30: CARAMANTA | AJ30: SAN CRISTOBAL | AK30: CUBARA | AO30: PUERTO TEJADA | AQ30: TADO | AR30: TIERRALTA | AS30: FOMEQUE | AV30: SAN AGUSTIN | AX30: TENERIFE | AY30: VILLAVICENCIO | AZ30: IPIALES | BA30: PUERTO SANTANDER | BF30: EL PEÑON | BH30: MURILLO | BI30: PRADERA
E31: 57. INDEPENDIENTE VOLUNTARIO AL SISTEMA DE RIESGOS LABORALES | I31: FAMISANAR | J31: COMFAMILIAR PUTUMAYO | AD31: SUCRE | AF31: CAREPA | AJ31: SAN ESTANISLAO | AK31: CUCAITA | AO31: PURACE | AQ31: UNGUIA | AR31: TUCHIN | AS31: FOSCA | AV31: SANTA MARIA | AX31: ZAPAYAN | AY31: VISTAHERMOSA | AZ31: LA CRUZ | BA31: RAGONVALIA | BF31: EL PLAYON | BH31: NATAGAIMA | BI31: RESTREPO
E32: 59. INDEPENDIENTE CON CONTRATO DE PRESTACIÓN DE SERVICIOS SUPERIOR A 1 MES | I32: FONDO DE FERROCARRILES NACIONALES DE COLOMBIA | J32: COMFAMILIAR RISARALDA | AD32: TOLIMA | AF32: CAROLINA | AJ32: SAN FERNANDO | AK32: CUITIVA | AO32: ROSAS | AQ32: UNION PANAMERICANA | AR32: VALENCIA | AS32: FUNZA | AV32: SUAZA | AX32: ZONA BANANERA | AZ32: LA FLORIDA | BA32: SALAZAR | BF32: ENCINO | BH32: ORTEGA | BI32: RIOFRIO
E33: 60. EDIL NO BENEFICIARIO DEL FSP | I33: FOSYGA | J33: COMFANDI | AD33: VALLE | AF33: CAUCASIA | AJ33: SAN JACINTO | AK33: DUITAMA | AO33: SAN SEBASTIAN | AS33: FUQUENE | AV33: TARQUI | AZ33: LA LLANADA | BA33: SAN CALIXTO | BF33: ENCISO | BH33: PALOCABILDO | BI33: ROLDANILLO
E34: 62. PERSONAL DEL MAGISTERIO | I34: FOSYGA RÉGIMEN DE EXCEPCIÓN | J34: COMFANORTE | AD34: VAUPES | AF34: CHIGORODO | AJ34: SAN JACINTO DEL CAUCA | AK34: EL COCUY | AO34: SANTA ROSA | AS34: FUSAGASUGA | AV34: TELLO | AZ34: LA TOLA | BA34: SAN CAYETANO | BF34: FLORIAN | BH34: PIEDRAS | BI34: SAN PEDRO
E35: 65. DEPENDIENTE VINCULADO AL PISO DE PROTECCIÓN SOCIAL | I35: FOSYGA RESIDENTE EXTERIOR O RÉGIMEN SUBSIDIADO | J35: COMFAORIENTE | AD35: VICHADA | AF35: CISNEROS | AJ35: SAN JUAN NEPOMUCENO | AK35: EL ESPINO | AO35: SANTANDER DE QUILICHAO | AS35: GACHALA | AV35: TERUEL | AZ35: LA UNION | BA35: SANTIAGO | BF35: FLORIDABLANCA | BH35: PLANADAS | BI35: SEVILLA
E36: 66. INDEPENDIENTE VINCULADO AL PISO DE PROTECCIÓN SOCIAL | I36: MALLAMAS | J36: COMFASUCRE | AF36: CIUDAD BOLIVAR | AJ36: SAN MARTIN DE LOBA | AK36: FIRAVITOBA | AO36: SILVIA | AS36: GACHANCIPA | AV36: TESALIA | AZ36: LEIVA | BA36: SARDINATA | BF36: GALAN | BH36: PRADO | BI36: TORO
E37: 67. VOLUNTARIO EN PRIMERA RESPUESTA | I37: MEDIMAS EPS | J37: COMFATOLIMA | AF37: COCORNA | AJ37: SAN PABLO | AK37: FLORESTA | AO37: SOTARA | AS37: GACHETA | AV37: TIMANA | AZ37: LINARES | BA37: SILOS | BF37: GAMBITA | BH37: PURIFICACION | BI37: TRUJILLO
E38: 68. DEPENDIENTE VETERANO DE LA FUERZA PÚBLICA | I38: MEDIMAS MOVILIDAD | J38: COMFENALCO ANTIOQUIA | AF38: CONCEPCION | AJ38: SANTA CATALINA | AK38: GACHANTIVA | AO38: SUAREZ | AS38: GAMA | AV38: VILLAVIEJA | AZ38: LOS ANDES | BA38: TEORAMA | BF38: GEPSA | BH38: RIOBLANCO | BI38: TULUA
I39: MUTUAL SER | J39: COMFENALCO CARTAGENA | AF39: CONCORDIA | AJ39: SANTA ROSA | AK39: GAMEZA | AO39: SUCRE | AS39: GIRARDOT | AV39: YAGUARA | AZ39: MAGI | BA39: TIBU | BF39: GIRON | BH39: RONCESVALLES | BI39: ULLOA
I40: NUEVA E.P.S. | J40: COMFENALCO QUINDIO | AF40: COPACABANA | AJ40: SANTA ROSA DEL SUR | AK40: GARAGOA | AO40: TIMBIO | AS40: GRANADA | AZ40: MALLAMA | BA40: TOLEDO | BF40: GUACA | BH40: ROVIRA | BI40: VERSALLES
I41: NUEVA EPS MOVILIDAD | J41: COMFENALCO SANTANDER | AF41: DABEIBA | AJ41: SIMITI | AK41: GICAN | AO41: TIMBIQUI | AS41: GUACHETA | AZ41: MOSQUERA | BA41: VILLA CARO | BF41: GUADALUPE | BH41: SALDAÑA | BI41: VIJES
I42: PIJAOSALUD | J42: COMFENALCO TOLIMA | AF42: DON MATIAS | AJ42: SOPLAVIENTO | AK42: GUACAMAYAS | AO42: TORIBIO | AS42: GUADUAS | AZ42: NARIÑO | BA42: VILLA DEL ROSARIO | BF42: GUAPOTA | BH42: SAN ANTONIO | BI42: YOTOCO
I43: S.O.S. SERVICIO OCCIDENTAL DE SALUD S.A. | J43: COMFENALCO VALLE | AF43: EBEJICO | AJ43: TALAIGUA NUEVO | AK43: GUATEQUE | AO43: TOTORO | AS43: GUASCA | AZ43: OLAYA HERRERA | BF43: GUAVATA | BH43: SAN LUIS | BI43: YUMBO
I44: SALUD MIA EPS | J44: COMFIAR | AF44: EL BAGRE | AJ44: TIQUISIO | AK44: GUAYATA | AO44: VILLA RICA | AS44: GUATAQUI | AZ44: OSPINA | BF44: HATO | BH44: SANTA ISABEL | BI44: ZARZAL
I45: SALUD TOTAL | J45: COMPENSAR | AF45: EL CARMEN DE VIBORAL | AJ45: TURBACO | AK45: IZA | AS45: GUATAVITA | AZ45: PASTO | BF45: JESUS MARIA | BH45: SUAREZ
I46: SANITAS | J46: CONFAMILIARES | AF46: EL SANTUARIO | AJ46: TURBANA | AK46: JENESANO | AS46: GUAYABAL DE SIQUIMA | AZ46: POLICARPA | BF46: JORDAN | BH46: VALLE DE SAN JUAN
I47: SAVIA SALUD | AF47: ENTRERRIOS | AJ47: VILLANUEVA | AK47: JERICO | AS47: GUAYABETAL | AZ47: POTOSI | BF47: LA BELLEZA | BH47: VENADILLO
AF48: ENVIGADO | AJ48: ZAMBRANO | AK48: LA CAPILLA | AS48: GUTIERREZ | AZ48: PROVIDENCIA | BF48: LA PAZ | BH48: VILLAHERMOSA
AF49: FREDONIA | AK49: LA UVITA | AS49: JERUSALEN | AZ49: PUERRES | BF49: LANDAZURI | BH49: VILLARRICA
AF50: FRONTINO | AK50: LA VICTORIA | AS50: JUNIN | AZ50: PUPIALES | BF50: LEBRIJA
AF51: GIRALDO | AK51: LABRANZAGRANDE | AS51: LA CALERA | AZ51: RICAURTE | BF51: LOS SANTOS
AF52: GIRARDOTA | AK52: MACANAL | AS52: LA MESA | AZ52: ROBERTO PAYAN | BF52: MACARAVITA
AF53: GOMEZ PLATA | AK53: MARIPI | AS53: LA PALMA | AZ53: SAMANIEGO | BF53: MALAGA
AF54: GRANADA | AK54: MIRAFLORES | AS54: LA PEÑA | AZ54: SAN BERNARDO | BF54: MATANZA
AF55: GUADALUPE | AK55: MONGUA | AS55: LA VEGA | AZ55: SAN LORENZO | BF55: MOGOTES
AF56: GUARNE | AK56: MONGUI | AS56: LENGUAZAQUE | AZ56: SAN PABLO | BF56: MOLAGAVITA
AF57: GUATAPE | AK57: MONIQUIRA | AS57: MACHETA | AZ57: SAN PEDRO DE CARTAGO | BF57: OCAMONTE
AF58: HELICONIA | AK58: MOTAVITA | AS58: MADRID | AZ58: SANDONA | BF58: OIBA
AF59: HISPANIA | AK59: MUZO | AS59: MANTA | AZ59: SANTA BARBARA | BF59: ONZAGA
AF60: ITAGUI | AK60: NOBSA | AS60: MEDINA | AZ60: SANTACRUZ | BF60: PALMAR
AF61: ITUANGO | AK61: NUEVO COLON | AS61: MOSQUERA | AZ61: SAPUYES | BF61: PALMAS DEL SOCORRO
... AF66: LA PINTADA | AK66: PAIPA | AS66: NOCAIMA | AZ66: YACUANQUER | BF66: PUERTO PARRA
AF67: LA UNION | AK67: PAJARITO | AS67: PACHO | BF67: PUERTO WILCHES
AF68: LIBORINA | AK68: PANQUEBA | AS68: PAIME | BF68: RIONEGRO
AF69: MACEO | AK69: PAUNA | AS69: PANDI | BF69: SABANA DE TORRES
AF70: MARINILLA | AK70: PAYA | AS70: PARATEBUENO | BF70: SAN ANDRES
AF71: MEDELLIN | AK71: PAZ DE RIO | AS71: PASCA | BF71: SAN BENITO
AF72: MONTEBELLO | AK72: PESCA | AS72: PUERTO SALGAR | BF72: SAN GIL
AF73: MURINDO | AK73: PISBA | AS73: PULI | BF73: SAN JOAQUIN
AF74: MUTATA | AK74: PUERTO BOYACA | AS74: QUEBRADANEGRA | BF74: SAN JOSE DE MIRANDA
AF75: NARIÑO | AK75: QUIPAMA | AS75: QUETAME | BF75: SAN MIGUEL
AF76: NECHI | AK76: RAMIRIQUI | AS76: QUIPILE | BF76: SAN VICENTE DE CHUCURI
AF77: NECOCLI | AK77: RAQUIRA | AS77: RICAURTE | BF77: SANTA BARBARA
AF78: OLAYA | AK78: RONDON | AS78: SAN ANTONIO DEL TEQUENDAMA | BF78: SANTA HELENA DEL OPON
... AF89: SABANETA | AK89: SANTA ROSA DE VITERBO | AS89: SOPO | BF89: ZAPATOCA
AF90: SALGAR | AK90: SANTA SOFIA | AS90: SUBACHOQUE
AF91: SAN ANDRES | AK91: SANTANA | AS91: SUESCA
AF92: SAN CARLOS | AK92: SATIVANORTE | AS92: SUPATA
AF93: SAN FRANCISCO | AK93: SATIVASUR | AS93: SUSA
AF94: SAN JERONIMO | AK94: SIACHOQUE | AS94: SUTATAUSA
AF95: SAN JOSE DE LA MONTAÑA | AK95: SOATA | AS95: TABIO
AF96: SAN JUAN DE URABA | AK96: SOCHA | AS96: TAUSA
AF97: SAN LUIS | AK97: SOCOTA | AS97: TENA
AF98: SAN PEDRO | AK98: SOGAMOSO | AS98: TENJO
AF99: SAN PEDRO DE URABA | AK99: SOMONDOCO | AS99: TIBACUY
AF100: SAN RAFAEL | AK100: SORA | AS100: TIBIRITA
AF101: SAN ROQUE | AK101: SORACA | AS101: TOCAIMA
... AF118: VALDIVIA | AK118: TURMEQUE | AS118: ZIPAQUIRA
AF119: VALPARAISO | AK119: TUTA
AF120: VEGACHI | AK120: TUTAZA
AF121: VENECIA | AK121: UMBITA
AF122: VIGIA DEL FUERTE | AK122: VENTAQUEMADA
AF123: YALI | AK123: VILLA DE LEYVA
AF124: YARUMAL | AK124: VIRACACHA
AF125: YOLOMBO | AK125: ZETAQUIRA
AF126: YONDO
AF127: ZARAGOZA

Sheet CauPag
A1: No. | B1: Tipo ID | C1: No ID | D1: APELLIDOS Y NOMBRES | E1: Primer Apellido | F1: Segundo Apellido | G1: Primer Nombre | H1: Segundo Nombre | I1: Departamento | J1: Ciudad | K1: Tipo de Cotizante | L1: Subtipo de Cotizante | M1: Horas Laboradas | N1: Extranjero | O1: Colombiano Temporalmente en el Exterior | P1: Fecha Radicación en el Exterior | Q1: ING | R1: Fecha ING | S1: RET | T1: Fecha RET | U1: TDE | V1: TAE | W1: TDP | X1: TAP | Y1: VSP | Z1: Fecha VSP | AA1: VST | AB1: SLN | AC1: Inicio SLN | AD1: Fin SLN | AE1: IGE | AF1: Inicio IGE | AG1: Fin IGE | AH1: LMA | AI1: Inicio LMA | AJ1: Fin LMA | AK1: VAC-LR | AL1: Inicio VAC-LR | AM1: Fin VAC-LR | AN1: AVP | AO1: VCT | AP1: Inicio VCT | AQ1: Fin VCT | AR1: IRL | AS1: Inicio IRL | AT1: Fin IRL | AU1: Correcciones | AV1: Salario Mensual($) | AW1: Salario Integral | AX1: Salario Variable | AY1: Administradora | AZ1: Días | BA1: IBC | BB1: Tarifa | BC1: Valor Cotización | BD1: Indicador Alto Riesgo | BE1: Cotización Voluntaria Afiliado | BF1: Cotización Voluntaria Empleador | BG1: Fondo Solidaridad Pensional | BH1: Fondo Subsistencia | BI1: Valor no Retenido | BJ1: Total | BK1: AFP Destino | BL1: Administradora | BM1: Días | BN1: IBC | BO1: Tarifa | BP1: Valor Cotización | BQ1: Valor UPC | BR1: N° Autorización Incapacidad EG | BS1: Valor Incapacidad EG | BT1: N° Autorización LMA | BU1: Valor Licencia Maternidad | BV1: EPS Destino | BW1: Administradora | BX1: Días | BY1: IBC | BZ1: Tarifa | CA1: Clase | CB1: Centro de Trabajo | CC1: Actividad Económica | CD1: Valor Cotización | CE1: Días | CF1: Administradora CCF | CG1: IBC CCF | CH1: Tarifa CCF | CI1: Valor Cotización CCF | CJ1: IBC Otros Parafiscales | CK1: Tarifa SENA | CL1: Valor Cotización SENA | CM1: Tarifa ICBF | CN1: Valor Cotización ICBF | CO1: Tarifa ESAP | CP1: Valor Cotización ESAP | CQ1: Tarifa MEN | CR1: Valor Cotización MEN | CS1: Exonerado parafiscales y salud | CT1: Tipo ID | CU1: N° ID
A2: CAUSADO | B2: CC | C2: 1000621869 | D2: MENDEZ ROJAS CARLOS ALBERTO | E2: MENDEZ | F2: ROJAS | G2: CARLOS | H2: ALBERTO | I2: BOGOTA_D.E. | J2: BOGOTA | K2: 1. DEPENDIENTE | L2: NINGUNO | M2: 188 | N2: NO | O2: NO | Q2: NO | S2: NO | U2: NO | V2: NO | W2: NO | X2: NO | Y2: NO | AA2: SI | AB2: NO | AE2: NO | AH2: NO | AK2: NO | AN2: NO | AO2: NO | AR2: 0 | AU2: NO | AV2: 1750905 | AW2: NO | AX2: NO | AY2: PORVENIR | AZ2: 30 | BA2: 2032509 | BB2: 0.16 | BC2: 325300 | BE2: 0 | BF2: 0 | BG2: 0 | BH2: 0 | BI2: 0 | BJ2: 325300 | BK2: NINGUNA | BL2: NUEVA E.P.S. | BM2: 30 | BN2: 2032509 | BO2: 0.04 | BP2: 81400 | BQ2: 0 | BS2: 0 | BU2: 0 | BV2: NINGUNA | BW2: COLMENA | BX2: 30 | BY2: 2032509 | BZ2: 0.0696 | CA2: 5 | CB2: CENTRO TRABAJO 24 | CC2: 5711001 | CD2: 141500 | CE2: 30 | CF2: COMPENSAR | CG2: 2032509 | CH2: 0.04 | CI2: 81400 | CJ2: 2032509 | CK2: 0 | CL2: 0 | CM2: 0 | CN2: 0 | CO2: 0 | CP2: 0 | CQ2: 0 | CR2: 0 | CS2: SI
A3: CAUSADO | B3: CC | C3: 1000790715 | D3: MOSQUERA MOSQUERA BRAYAN STIVEN | E3: MOSQUERA | F3: MOSQUERA | G3: BRAYAN | H3: STIVEN | I3: BOGOTA_D.E. | J3: BOGOTA | K3: 1. DEPENDIENTE | L3: NINGUNO | M3: 9 | N3: NO | O3: NO | Q3: Todos los sistemas (ARL, AFP, CCF, EPS) | R3: 46080 | S3: NO | U3: NO | V3: NO | W3: NO | X3: NO | Y3: NO | AA3: NO | AB3: NO | AE3: NO | AH3: NO | AK3: NO | AN3: NO | AO3: NO | AR3: 0 | AU3: NO | AV3: 1750905 | AW3: NO | AX3: NO | AY3: PORVENIR | AZ3: 4 | BA3: 233454 | BB3: 0.16 | BC3: 37400 | BE3: 0 | BF3: 0 | BG3: 0 | BH3: 0 | BI3: 0 | BJ3: 37400 | BK3: NINGUNA | BL3: ALIANSALUD EPS (ANTES COLMEDICA) | BM3: 4 | BN3: 233454 | BO3: 0.04 | BP3: 9400 | BQ3: 0 | BS3: 0 | BU3: 0 | BV3: NINGUNA | BW3: COLMENA | BX3: 4 | BY3: 233454 | BZ3: 0.0696 | CA3: 5 | CB3: CENTRO TRABAJO 24 | CC3: 5711001 | CD3: 16300 | CE3: 4 | CF3: COMPENSAR | CG3: 233454 | CH3: 0.04 | CI3: 9400 | CJ3: 233454 | CK3: 0 | CL3: 0 | CM3: 0 | CN3: 0 | CO3: 0 | CP3: 0 | CQ3: 0 | CR3: 0 | CS3: SI
A4: CAUSADO | B4: CC | C4: 1001798417 | D4: RUA MANGA CARLOS MARIO | E4: RUA | F4: MANGA | G4: CARLOS | H4: MARIO | I4: LA_GUAJIRA | J4: RIOHACHA | K4: 1. DEPENDIENTE | L4: NINGUNO | M4: 204 | N4: NO | O4: NO | Q4: NO | S4: NO | U4: NO | V4: NO | W4: NO | X4: NO | Y4: NO | AA4: SI | AB4: NO | AE4: NO | AH4: NO | AK4: NO | AN4: NO | AO4: NO | AR4: 0 | AU4: NO | AV4: 1889179 | AW4: NO | AX4: NO | AY4: PORVENIR | AZ4: 30 | BA4: 2222363 | BB4: 0.16 | BC4: 355600 | BE4: 0 | BF4: 0 | BG4: 0 | BH4: 0 | BI4: 0 | BJ4: 355600 | BK4: NINGUNA | BL4: SANITAS | BM4: 30 | BN4: 2222363 | BO4: 0.04 | BP4: 88900 | BQ4: 0 | BS4: 0 | BU4: 0 | BV4: NINGUNA | BW4: COLMENA | BX4: 30 | BY4: 2222363 | BZ4: 0.0696 | CA4: 5 | CB4: CENTRO TRABAJO 30 | CC4: 5711001 | CD4: 154700 | CE4: 30 | CF4: COMFAMILIAR GUAJIRA | CG4: 2222363 | CH4: 0.04 | CI4: 88900 | CJ4: 2222363 | CK4: 0 | CL4: 0 | CM4: 0 | CN4: 0 | CO4: 0 | CP4: 0 | CQ4: 0 | CR4: 0 | CS4: SI
A5: CAUSADO | B5: CC | C5: 1001836532 | D5: SANTANA VIDES OSCAR JUNIOR | E5: SANTANA | F5: VIDES | G5: OSCAR | H5: JUNIOR | I5: BOLIVAR | J5: CARTAGENA | K5: 1. DEPENDIENTE | L5: NINGUNO | M5: 201 | N5: NO | O5: NO | Q5: NO | S5: NO | U5: NO | V5: NO | W5: NO | X5: NO | Y5: NO | AA5: SI | AB5: NO | AE5: NO | AH5: NO | AK5: NO | AN5: NO | AO5: NO | AR5: 0 | AU5: NO | AV5: 2308750 | AW5: NO | AX5: NO | AY5: PORVENIR | AZ5: 30 | BA5: 2643077 | BB5: 0.16 | BC5: 422900 | BE5: 0 | BF5: 0 | BG5: 0 | BH5: 0 | BI5: 0 | BJ5: 422900 | BK5: NINGUNA | BL5: NUEVA E.P.S. | BM5: 30 | BN5: 2643077 | BO5: 0.04 | BP5: 105800 | BQ5: 0 | BS5: 0 | BU5: 0 | BV5: NINGUNA | BW5: COLMENA | BX5: 30 | BY5: 2643077 | BZ5: 0.0696 | CA5: 5 | CB5: CENTRO TRABAJO 8 | CC5: 5711001 | CD5: 184000 | CE5: 30 | CF5: COMFENALCO CARTAGENA | CG5: 2584226 | CH5: 0.04 | CI5: 103400 | CJ5: 2584226 | CK5: 0 | CL5: 0 | CM5: 0 | CN5: 0 | CO5: 0 | CP5: 0 | CQ5: 0 | CR5: 0 | CS5: SI
A6: CAUSADO | B6: CC | C6: 1002143370 | D6: CANTILLO PERTUZ GIANTKHRLOOS G. | E6: CANTILLO | F6: PERTUZ | G6: GIANTKHRLOOS | H6: G. | I6: BOGOTA_D.E. | J6: BOGOTA | K6: 1. DEPENDIENTE | L6: NINGUNO | M6: 0 | N6: NO | O6: NO | Q6: NO | S6: NO | U6: NO | V6: NO | W6: NO | X6: NO | Y6: NO | AA6: NO | AB6: NO | AE6: NO | AH6: NO | AK6: LICENCIA REMUNERADA | AL6: 46069 | AM6: 46069 | AN6: NO | AO6: NO | AR6: 0 | AU6: NO | AV6: 1750905 | AW6: NO | AX6: NO | AY6: PORVENIR | AZ6: 1 | BA6: 58364 | BB6: 0.16 | BC6: 9400 | BE6: 0 | BF6: 0 | BG6: 0 | BH6: 0 | BI6: 0 | BJ6: 9400 | BK6: NINGUNA | BL6: SANITAS | BM6: 1 | BN6: 58364 | BO6: 0.04 | BP6: 2400 | BQ6: 0 | BS6: 0 | BU6: 0 | BV6: NINGUNA | BW6: COLMENA | BX6: 1 | BY6: 58364 | BZ6: 0 | CA6: 5 | CB6: CENTRO TRABAJO 24 | CC6: 5711001 | CD6: 0 | CE6: 1 | CF6: COMPENSAR | CG6: 58364 | CH6: 0.04 | CI6: 2400 | CJ6: 58364 | CK6: 0 | CL6: 0 | CM6: 0 | CN6: 0 | CO6: 0 | CP6: 0 | CQ6: 0 | CR6: 0 | CS6: SI
A7: CAUSADO | B7: CC | C7: 1002143370 | D7: CANTILLO PERTUZ GIANTKHRLOOS G. | E7: CANTILLO | F7: PERTUZ | G7: GIANTKHRLOOS | H7: G. | I7: BOGOTA_D.E. | J7: BOGOTA | K7: 1. DEPENDIENTE | L7: NINGUNO | M7: 188 | N7: NO | O7: NO | Q7: NO | S7: NO | U7: NO | V7: NO | W7: NO | X7: NO | Y7: NO | AA7: SI | AB7: NO | AE7: NO | AH7: NO | AK7: NO | AN7: NO | AO7: NO | AR7: 0 | AU7: NO | AV7: 1750905 | AW7: NO | AX7: NO | AY7: PORVENIR | AZ7: 29 | BA7: 2073895 | BB7: 0.16 | BC7: 331900 | BE7: 0 | BF7: 0 | BG7: 0 | BH7: 0 | BI7: 0 | BJ7: 331900 | BK7: NINGUNA | BL7: SANITAS | BM7: 29 | BN7: 2073895 | BO7: 0.04 | BP7: 83000 | BQ7: 0 | BS7: 0 | BU7: 0 | BV7: NINGUNA | BW7: COLMENA | BX7: 29 | BY7: 2073895 | BZ7: 0.0696 | CA7: 5 | CB7: CENTRO TRABAJO 24 | CC7: 5711001 | CD7: 144400 | CE7: 29 | CF7: COMPENSAR | CG7: 2073895 | CH7: 0.04 | CI7: 83000 | CJ7: 2073895 | CK7: 0 | CL7: 0 | CM7: 0 | CN7: 0 | CO7: 0 | CP7: 0 | CQ7: 0 | CR7: 0 | CS7: SI
A8: CAUSADO | B8: CC | C8: 1002487151 | D8: ZABALETA SALCEDO NEL ENRIQUE | E8: ZABALETA | F8: SALCEDO | G8: NEL | H8: ENRIQUE | I8: BOGOTA_D.E. | J8: BOGOTA | K8: 1. DEPENDIENTE | L8: NINGUNO | M8: 0 | N8: NO | O8: NO | Q8: NO | S8: NO | U8: NO | V8: NO | W8: NO | X8: NO | Y8: NO | AA8: NO | AB8: LICENCIA NO REMUNERADA | AC8: 46054 | AD8: 46055 | AE8: NO | AH8: NO | AK8: NO | AN8: NO | AO8: NO | AR8: 0 | AU8: NO | AV8: 1750905 | AW8: NO | AX8: NO | AY8: PORVENIR | AZ8: 2 | BA8: 116727 | BB8: 0.16 | BC8: 18700 | BE8: 0 | BF8: 0 | BG8: 0 | BH8: 0 | BI8: 0 | BJ8: 18700 | BK8: NINGUNA | BL8: SALUD TOTAL | BM8: 2 | BN8: 116727 | BO8: 0 | BP8: 0 | BQ8: 0 | BS8: 0 | BU8: 0 | BV8: NINGUNA | BW8: COLMENA | BX8: 2 | BY8: 116727 | BZ8: 0 | CA8: 5 | CB8: CENTRO TRABAJO 24 | CC8: 5711001 | CD8: 0 | CE8: 2 | CF8: COMPENSAR | CG8: 0 | CH8: 0 | CI8: 0 | CJ8: 0 | CK8: 0 | CL8: 0 | CM8: 0 | CN8: 0 | CO8: 0 | CP8: 0 | CQ8: 0 | CR8: 0 | CS8: SI
A9: CAUSADO | B9: CC | C9: 1002487151 | D9: ZABALETA SALCEDO NEL ENRIQUE | E9: ZABALETA | F9: SALCEDO | G9: NEL | H9: ENRIQUE | I9: BOGOTA_D.E. | J9: BOGOTA | K9: 1. DEPENDIENTE | L9: NINGUNO | M9: 0 | N9: NO | O9: NO | Q9: NO | S9: NO | U9: NO | V9: NO | W9: NO | X9: NO | Y9: NO | AA9: NO | AB9: LICENCIA NO REMUNERADA | AC9: 46055 | AD9: 46061 | AE9: NO | AH9: NO | AK9: NO | AN9: NO | AO9: NO | AR9: 0 | AU9: NO | AV9: 1750905 | AW9: NO | AX9: NO | AY9: PORVENIR | AZ9: 7 | BA9: 408545 | BB9: 0.16 | BC9: 65400 | BE9: 0 | BF9: 0 | BG9: 0 | BH9: 0 | BI9: 0 | BJ9: 65400 | BK9: NINGUNA | BL9: SALUD TOTAL | BM9: 7 | BN9: 408545 | BO9: 0 | BP9: 0 | BQ9: 0 | BS9: 0 | BU9: 0 | BV9: NINGUNA | BW9: COLMENA | BX9: 7 | BY9: 408545 | BZ9: 0 | CA9: 5 | CB9: CENTRO TRABAJO 24 | CC9: 5711001 | CD9: 0 | CE9: 7 | CF9: COMPENSAR | CG9: 0 | CH9: 0 | CI9: 0 | CJ9: 0 | CK9: 0 | CL9: 0 | CM9: 0 | CN9: 0 | CO9: 0 | CP9: 0 | CQ9: 0 | CR9: 0 | CS9: SI
A10: CAUSADO | B10: CC | C10: 1002487151 | D10: ZABALETA SALCEDO NEL ENRIQUE | E10: ZABALETA | F10: SALCEDO | G10: NEL | H10: ENRIQUE | I10: BOGOTA_D.E. | J10: BOGOTA | K10: 1. DEPENDIENTE | L10: NINGUNO | M10: 140 | N10: NO | O10: NO | Q10: NO | S10: NO | U10: NO | V10: NO | W10: NO | X10: NO | Y10: NO | AA10: SI | AB10: NO | AE10: NO | AH10: NO | AK10: NO | AN10: NO | AO10: NO | AR10: 0 | AU10: NO | AV10: 1750905 | AW10: NO | AX10: NO | AY10: PORVENIR | AZ10: 21 | BA10: 1545572 | BB10: 0.16 | BC10: 247300 | BE10: 0 | BF10: 0 | BG10: 0 | BH10: 0 | BI10: 0 | BJ10: 247300 | BK10: NINGUNA | BL10: SALUD TOTAL | BM10: 21 | BN10: 1545572 | BO10: 0.04 | BP10: 61900 | BQ10: 0 | BS10: 0 | BU10: 0 | BV10: NINGUNA | BW10: COLMENA | BX10: 21 | BY10: 1545572 | BZ10: 0.0696 | CA10: 5 | CB10: CENTRO TRABAJO 24 | CC10: 5711001 | CD10: 107600 | CE10: 21 | CF10: COMPENSAR | CG10: 1545572 | CH10: 0.04 | CI10: 61900 | CJ10: 1545572 | CK10: 0 | CL10: 0 | CM10: 0 | CN10: 0 | CO10: 0 | CP10: 0 | CQ10: 0 | CR10: 0 | CS10: SI
A11: CAUSADO | B11: CC | C11: 1002559775 | D11: SANCHEZ VARGAS OMAR ALEJANDRO | E11: SANCHEZ | F11: VARGAS | G11: OMAR | H11: ALEJANDRO | I11: BOGOTA_D.E. | J11: BOGOTA | K11: 1. DEPENDIENTE | L11: NINGUNO | M11: 162 | N11: NO | O11: NO | Q11: Todos los sistemas (ARL, AFP, CCF, EPS) | R11: 46059 | S11: NO | U11: NO | V11: NO | W11: NO | X11: NO | Y11: NO | AA11: SI | AB11: NO | AE11: NO | AH11: NO | AK11: NO | AN11: NO | AO11: NO | AR11: 0 | AU11: NO | AV11: 2223339 | AW11: NO | AX11: NO | AY11: PORVENIR | AZ11: 25 | BA11: 2334844 | BB11: 0.16 | BC11: 373600 | BE11: 0 | BF11: 0 | BG11: 0 | BH11: 0 | BI11: 0 | BJ11: 373600 | BK11: NINGUNA | BL11: NUEVA E.P.S. | BM11: 25 | BN11: 2334844 | BO11: 0.04 | BP11: 93400 | BQ11: 0 | BS11: 0 | BU11: 0 | BV11: NINGUNA | BW11: COLMENA | BX11: 25 | BY11: 2334844 | BZ11: 0.0696 | CA11: 5 | CB11: CENTRO TRABAJO 24 | CC11: 5711001 | CD11: 162600 | CE11: 25 | CF11: COMPENSAR | CG11: 2334844 | CH11: 0.04 | CI11: 93400 | CJ11: 2334844 | CK11: 0 | CL11: 0 | CM11: 0 | CN11: 0 | CO11: 0 | CP11: 0 | CQ11: 0 | CR11: 0 | CS11: SI
A12: CAUSADO | B12: CC | C12: 1003252787 | D12: MANGA FRIA JUAN LUIS | E12: MANGA | F12: FRIA | G12: JUAN | H12: LUIS | I12: LA_GUAJIRA | J12: RIOHACHA | K12: 1. DEPENDIENTE | L12: NINGUNO | M12: 0 | N12: NO | O12: NO | Q12: NO | S12: NO | U12: NO | V12: NO | W12: NO | X12: NO | Y12: NO | AA12: NO | AB12: LICENCIA NO REMUNERADA | AC12: 46054 | AD12: 46054 | AE12: NO | AH12: NO | AK12: NO | AN12: NO | AO12: NO | AR12: 0 | AU12: NO | AV12: 1750905 | AW12: NO | AX12: NO | AY12: PORVENIR | AZ12: 1 | BA12: 58364 | BB12: 0.16 | BC12: 9400 | BE12: 0 | BF12: 0 | BG12: 0 | BH12: 0 | BI12: 0 | BJ12: 9400 | BK12: NINGUNA | BL12: COOSALUD MOVILIDAD | BM12: 1 | BN12: 58364 | BO12: 0 | BP12: 0 | BQ12: 0 | BS12: 0 | BU12: 0 | BV12: NINGUNA | BW12: COLMENA | BX12: 1 | BY12: 58364 | BZ12: 0 | CA12: 5 | CB12: CENTRO TRABAJO 30 | CC12: 5711001 | CD12: 0 | CE12: 1 | CF12: COMFAMILIAR GUAJIRA | CG12: 0 | CH12: 0 | CI12: 0 | CJ12: 0 | CK12: 0 | CL12: 0 | CM12: 0 | CN12: 0 | CO12: 0 | CP12: 0 | CQ12: 0 | CR12: 0 | CS12: SI
A13: CAUSADO | B13: CC | C13: 1003252787 | D13: MANGA FRIA JUAN LUIS | E13: MANGA | F13: FRIA | G13: JUAN | H13: LUIS | I13: LA_GUAJIRA | J13: RIOHACHA | K13: 1. DEPENDIENTE | L13: NINGUNO | M13: 0 | N13: NO | O13: NO | Q13: NO | S13: NO | U13: NO | V13: NO | W13: NO | X13: NO | Y13: NO | AA13: NO | AB13: LICENCIA NO REMUNERADA | AC13: 46069 | AD13: 46069 | AE13: NO | AH13: NO | AK13: NO | AN13: NO | AO13: NO | AR13: 0 | AU13: NO | AV13: 1750905 | AW13: NO | AX13: NO | AY13: PORVENIR | AZ13: 1 | BA13: 58364 | BB13: 0.16 | BC13: 9400 | BE13: 0 | BF13: 0 | BG13: 0 | BH13: 0 | BI13: 0 | BJ13: 9400 | BK13: NINGUNA | BL13: COOSALUD MOVILIDAD | BM13: 1 | BN13: 58364 | BO13: 0 | BP13: 0 | BQ13: 0 | BS13: 0 | BU13: 0 | BV13: NINGUNA | BW13: COLMENA | BX13: 1 | BY13: 58364 | BZ13: 0 | CA13: 5 | CB13: CENTRO TRABAJO 30 | CC13: 5711001 | CD13: 0 | CE13: 1 | CF13: COMFAMILIAR GUAJIRA | CG13: 0 | CH13: 0 | CI13: 0 | CJ13: 0 | CK13: 0 | CL13: 0 | CM13: 0 | CN13: 0 | CO13: 0 | CP13: 0 | CQ13: 0 | CR13: 0 | CS13: SI
A14: CAUSADO | B14: CC | C14: 1003252787 | D14: MANGA FRIA JUAN LUIS | E14: MANGA | F14: FRIA | G14: JUAN | H14: LUIS | I14: LA_GUAJIRA | J14: RIOHACHA | K14: 1. DEPENDIENTE | L14: NINGUNO | M14: 198 | N14: NO | O14: NO | Q14: NO | S14: NO | U14: NO | V14: NO | W14: NO | X14: NO | Y14: NO | AA14: SI | AB14: NO | AE14: NO | AH14: NO | AK14: NO | AN14: NO | AO14: NO | AR14: 0 | AU14: NO | AV14: 1750905 | AW14: NO | AX14: NO | AY14: PORVENIR | AZ14: 28 | BA14: 1972818 | BB14: 0.16 | BC14: 315700 | BE14: 0 | BF14: 0 | BG14: 0 | BH14: 0 | BI14: 0 | BJ14: 315700 | BK14: NINGUNA | BL14: COOSALUD MOVILIDAD | BM14: 28 | BN14: 1972818 | BO14: 0.04 | BP14: 79000 | BQ14: 0 | BS14: 0 | BU14: 0 | BV14: NINGUNA | BW14: COLMENA | BX14: 28 | BY14: 1972818 | BZ14: 0.0696 | CA14: 5 | CB14: CENTRO TRABAJO 30 | CC14: 5711001 | CD14: 137400 | CE14: 28 | CF14: COMFAMILIAR GUAJIRA | CG14: 1972819 | CH14: 0.04 | CI14: 79000 | CJ14: 1972819 | CK14: 0 | CL14: 0 | CM14: 0 | CN14: 0 | CO14: 0 | CP14: 0 | CQ14: 0 | CR14: 0 | CS14: SI
A15: CAUSADO | B15: CC | C15: 1003557217 | D15: OSORIO HERNANDEZ KEVIN ALBERTO | E15: OSORIO | F15: HERNANDEZ | G15: KEVIN | H15: ALBERTO | I15: BOGOTA_D.E. | J15: BOGOTA | K15: 1. DEPENDIENTE | L15: NINGUNO | M15: 0 | N15: NO | O15: NO | Q15: Todos los sistemas (ARL, AFP, CCF, EPS) | R15: 46081 | S15: NO | U15: NO | V15: NO | W15: NO | X15: NO | Y15: NO | AA15: NO | AB15: NO | AE15: NO | AH15: NO | AK15: NO | AN15: NO | AO15: NO | AR15: 0 | AU15: NO | AV15: 1785595 | AW15: NO | AX15: NO | AY15: COLPENSIONES | AZ15: 3 | BA15: 178560 | BB15: 0.16 | BC15: 28600 | BE15: 0 | BF15: 0 | BG15: 0 | BH15: 0 | BI15: 0 | BJ15: 28600 | BK15: NINGUNA | BL15: FONDO DE FERROCARRILES NACIONALES DE COLOMBIA | BM15: 3 | BN15: 178560 | BO15: 0.04 | BP15: 7200 | BQ15: 0 | BS15: 0 | BU15: 0 | BV15: NINGUNA | BW15: COLMENA | BX15: 3 | BY15: 178560 | BZ15: 0.0696 | CA15: 5 | CB15: CENTRO TRABAJO 24 | CC15: 5711001 | CD15: 12500 | CE15: 3 | CF15: COMPENSAR | CG15: 178560 | CH15: 0.04 | CI15: 7200 | CJ15: 178560 | CK15: 0 | CL15: 0 | CM15: 0 | CN15: 0 | CO15: 0 | CP15: 0 | CQ15: 0 | CR15: 0 | CS15: SI
A16: CAUSADO | B16: CC | C16: 1003736605 | D16: ALVAREZ CORREA JOSE ANGEL | E16: ALVAREZ | F16: CORREA | G16: JOSE | H16: ANGEL | I16: LA_GUAJIRA | J16: RIOHACHA | K16: 1. DEPENDIENTE | L16: NINGUNO | M16: 0 | N16: NO | O16: NO | Q16: NO | S16: NO | U16: NO | V16: NO | W16: NO | X16: NO | Y16: NO | AA16: NO | AB16: LICENCIA NO REMUNERADA | AC16: 46054 | AD16: 46054 | AE16: NO | AH16: NO | AK16: NO | AN16: NO | AO16: NO | AR16: 0 | AU16: NO | AV16: 1785595 | AW16: NO | AX16: NO | AY16: PORVENIR | AZ16: 1 | BA16: 59520 | BB16: 0.16 | BC16: 9600 | BE16: 0 | BF16: 0 | BG16: 0 | BH16: 0 | BI16: 0 | BJ16: 9600 | BK16: NINGUNA | BL16: CAJACOPI | BM16: 1 | BN16: 59520 | BO16: 0 | BP16: 0 | BQ16: 0 | BS16: 0 | BU16: 0 | BV16: NINGUNA | BW16: COLMENA | BX16: 1 | BY16: 59520 | BZ16: 0 | CA16: 5 | CB16: CENTRO TRABAJO 30 | CC16: 5711001 | CD16: 0 | CE16: 1 | CF16: COMFAMILIAR GUAJIRA | CG16: 0 | CH16: 0 | CI16: 0 | CJ16: 0 | CK16: 0 | CL16: 0 | CM16: 0 | CN16: 0 | CO16: 0 | CP16: 0 | CQ16: 0 | CR16: 0 | CS16: SI
A17: CAUSADO | B17: CC | C17: 1003736605 | D17: ALVAREZ CORREA JOSE ANGEL | E17: ALVAREZ | F17: CORREA | G17: JOSE | H17: ANGEL | I17: LA_GUAJIRA | J17: RIOHACHA | K17: 1. DEPENDIENTE | L17: NINGUNO | M17: 0 | N17: NO | O17: NO | Q17: NO | S17: NO | U17: NO | V17: NO | W17: NO | X17: NO | Y17: NO | AA17: NO | AB17: NO | AE17: INCAPACIDAD GENERAL | AF17: 46056 | AG17: 46056 | AH17: NO | AK17: NO | AN17: NO | AO17: NO | AR17: 0 | AU17: NO | AV17: 1785595 | AW17: NO | AX17: NO | AY17: PORVENIR | AZ17: 1 | BA17: 69937 | BB17: 0.16 | BC17: 11200 | BE17: 0 | BF17: 0 | BG17: 0 | BH17: 0 | BI17: 0 | BJ17: 11200 | BK17: NINGUNA | BL17: CAJACOPI | BM17: 1 | BN17: 69937 | BO17: 0.04 | BP17: 2800 | BQ17: 0 | BS17: 0 | BU17: 0 | BV17: NINGUNA | BW17: COLMENA | BX17: 1 | BY17: 69937 | BZ17: 0 | CA17: 5 | CB17: CENTRO TRABAJO 30 | CC17: 5711001 | CD17: 0 | CE17: 1 | CF17: COMFAMILIAR GUAJIRA | CG17: 0 | CH17: 0 | CI17: 0 | CJ17: 0 | CK17: 0 | CL17: 0 | CM17: 0 | CN17: 0 | CO17: 0 | CP17: 0 | CQ17: 0 | CR17: 0 | CS17: SI
A18: CAUSADO | B18: CC | C18: 1003736605 | D18: ALVAREZ CORREA JOSE ANGEL | E18: ALVAREZ | F18: CORREA | G18: JOSE | H18: ANGEL | I18: LA_GUAJIRA | J18: RIOHACHA | K18: 1. DEPENDIENTE | L18: NINGUNO | M18: 192 | N18: NO | O18: NO | Q18: NO | S18: Todos los sistemas (ARL, AFP, CCF, EPS) | T18: 46079 | U18: NO | V18: NO | W18: NO | X18: NO | Y18: NO | AA18: SI | AB18: NO | AE18: NO | AH18: NO | AK18: NO | AN18: NO | AO18: NO | AR18: 0 | AU18: NO | AV18: 1785595 | AW18: NO | AX18: NO | AY18: PORVENIR | AZ18: 24 | BA18: 2913713 | BB18: 0.16 | BC18: 466200 | BE18: 0 | BF18: 0 | BG18: 0 | BH18: 0 | BI18: 0 | BJ18: 466200 | BK18: NINGUNA | BL18: CAJACOPI | BM18: 24 | BN18: 2913713 | BO18: 0.04 | BP18: 116600 | BQ18: 0 | BS18: 0 | BU18: 0 | BV18: NINGUNA | BW18: COLMENA | BX18: 24 | BY18: 2913713 | BZ18: 0.0696 | CA18: 5 | CB18: CENTRO TRABAJO 30 | CC18: 5711001 | CD18: 202800 | CE18: 24 | CF18: COMFAMILIAR GUAJIRA | CG18: 4259565 | CH18: 0.04 | CI18: 170400 | CJ18: 4259565 | CK18: 0 | CL18: 0 | CM18: 0 | CN18: 0 | CO18: 0 | CP18: 0 | CQ18: 0 | CR18: 0 | CS18: SI
A19: CAUSADO | B19: CC | C19: 1003903787 | D19: MALDONADO LOSADA EDINSON ANDRES | E19: MALDONADO | F19: LOSADA | G19: EDINSON | H19: ANDRES | I19: BOGOTA_D.E. | J19: BOGOTA | K19: 1. DEPENDIENTE | L19: NINGUNO | M19: 0 | N19: NO | O19: NO | Q19: NO | S19: NO | U19: NO | V19: NO | W19: NO | X19: NO | Y19: NO | AA19: NO | AB19: NO | AE19: NO | AH19: NO | AK19: LICENCIA REMUNERADA | AL19: 46054 | AM19: 46054 | AN19: NO | AO19: NO | AR19: 0 | AU19: NO | AV19: 1750905 | AW19: NO | AX19: NO | AY19: PORVENIR | AZ19: 1 | BA19: 58364 | BB19: 0.16 | BC19: 9400 | BE19: 0 | BF19: 0 | BG19: 0 | BH19: 0 | BI19: 0 | BJ19: 9400 | BK19: NINGUNA | BL19: SALUD TOTAL | BM19: 1 | BN19: 58364 | BO19: 0.04 | BP19: 2400 | BQ19: 0 | BS19: 0 | BU19: 0 | BV19: NINGUNA | BW19: COLMENA | BX19: 1 | BY19: 58364 | BZ19: 0 | CA19: 5 | CB19: CENTRO TRABAJO 24 | CC19: 5711001 | CD19: 0 | CE19: 1 | CF19: COMPENSAR | CG19: 58364 | CH19: 0.04 | CI19: 2400 | CJ19: 58364 | CK19: 0 | CL19: 0 | CM19: 0 | CN19: 0 | CO19: 0 | CP19: 0 | CQ19: 0 | CR19: 0 | CS19: SI
A20: CAUSADO | B20: CC | C20: 1003903787 | D20: MALDONADO LOSADA EDINSON ANDRES | E20: MALDONADO | F20: LOSADA | G20: EDINSON | H20: ANDRES | I20: BOGOTA_D.E. | J20: BOGOTA | K20: 1. DEPENDIENTE | L20: NINGUNO | M20: 0 | N20: NO | O20: NO | Q20: NO | S20: NO | U20: NO | V20: NO | W20: NO | X20: NO | Y20: NO | AA20: NO | AB20: NO | AE20: INCAPACIDAD GENERAL | AF20: 46062 | AG20: 46063 | AH20: NO | AK20: NO | AN20: NO | AO20: NO | AR20: 0 | AU20: NO | AV20: 1750905 | AW20: NO | AX20: NO | AY20: PORVENIR | AZ20: 2 | BA20: 205820 | BB20: 0.16 | BC20: 33000 | BE20: 0 | BF20: 0 | BG20: 0 | BH20: 0 | BI20: 0 | BJ20: 33000 | BK20: NINGUNA | BL20: SALUD TOTAL | BM20: 2 | BN20: 205820 | BO20: 0.04 | BP20: 8300 | BQ20: 0 | BS20: 0 | BU20: 0 | BV20: NINGUNA | BW20: COLMENA | BX20: 2 | BY20: 205820 | BZ20: 0 | CA20: 5 | CB20: CENTRO TRABAJO 24 | CC20: 5711001 | CD20: 0 | CE20: 2 | CF20: COMPENSAR | CG20: 0 | CH20: 0 | CI20: 0 | CJ20: 0 | CK20: 0 | CL20: 0 | CM20: 0 | CN20: 0 | CO20: 0 | CP20: 0 | CQ20: 0 | CR20: 0 | CS20: SI
A21: CAUSADO | B21: CC | C21: 1003903787 | D21: MALDONADO LOSADA EDINSON ANDRES | E21: MALDONADO | F21: LOSADA | G21: EDINSON | H21: ANDRES | I21: BOGOTA_D.E. | J21: BOGOTA | K21: 1. DEPENDIENTE | L21: NINGUNO | M21: 0 | N21: NO | O21: NO | Q21: NO | S21: NO | U21: NO | V21: NO | W21: NO | X21: NO | Y21: NO | AA21: NO | AB21: LICENCIA NO REMUNERADA | AC21: 46069 | AD21: 46070 | AE21: NO | AH21: NO | AK21: NO | AN21: NO | AO21: NO | AR21: 0 | AU21: NO | AV21: 1750905 | AW21: NO | AX21: NO | AY21: PORVENIR | AZ21: 2 | BA21: 116727 | BB21: 0.16 | BC21: 18700 | BE21: 0 | BF21: 0 | BG21: 0 | BH21: 0 | BI21: 0 | BJ21: 18700 | BK21: NINGUNA | BL21: SALUD TOTAL | BM21: 2 | BN21: 116727 | BO21: 0 | BP21: 0 | BQ21: 0 | BS21: 0 | BU21: 0 | BV21: NINGUNA | BW21: COLMENA | BX21: 2 | BY21: 116727 | BZ21: 0 | CA21: 5 | CB21: CENTRO TRABAJO 24 | CC21: 5711001 | CD21: 0 | CE21: 2 | CF21: COMPENSAR | CG21: 0 | CH21: 0 | CI21: 0 | CJ21: 0 | CK21: 0 | CL21: 0 | CM21: 0 | CN21: 0 | CO21: 0 | CP21: 0 | CQ21: 0 | CR21: 0 | CS21: SI
A22: CAUSADO | B22: CC | C22: 1003903787 | D22: MALDONADO LOSADA EDINSON ANDRES | E22: MALDONADO | F22: LOSADA | G22: EDINSON | H22: ANDRES | I22: BOGOTA_D.E. | J22: BOGOTA | K22: 1. DEPENDIENTE | L22: NINGUNO | M22: 124 | N22: NO | O22: NO | Q22: NO | S22: Todos los sistemas (ARL, AFP, CCF, EPS) | T22: 46074 | U22: NO | V22: NO | W22: NO | X22: NO | Y22: NO | AA22: SI | AB22: NO | AE22: NO | AH22: NO | AK22: NO | AN22: NO | AO22: NO | AR22: 0 | AU22: NO | AV22: 1750905 | AW22: NO | AX22: NO | AY22: PORVENIR | AZ22: 16 | BA22: 1600632 | BB22: 0.16 | BC22: 256200 | BE22: 0 | BF22: 0 | BG22: 0 | BH22: 0 | BI22: 0 | BJ22: 256200 | BK22: NINGUNA | BL22: SALUD TOTAL | BM22: 16 | BN22: 1600632 | BO22: 0.04 | BP22: 64100 | BQ22: 0 | BS22: 0 | BU22: 0 | BV22: NINGUNA | BW22: COLMENA | BX22: 16 | BY22: 1600632 | BZ22: 0.0696 | CA22: 5 | CB22: CENTRO TRABAJO 24 | CC22: 5711001 | CD22: 111500 | CE22: 16 | CF22: COMPENSAR | CG22: 2098116 | CH22: 0.04 | CI22: 84000 | CJ22: 2098116 | CK22: 0 | CL22: 0 | CM22: 0 | CN22: 0 | CO22: 0 | CP22: 0 | CQ22: 0 | CR22: 0 | CS22: SI
A23: CAUSADO | B23: CC | C23: 1004271898 | D23: DE AVILA ARRIETA BRAYAN RAFAEL | E23: DE AVILA | F23: ARRIETA | G23: BRAYAN | H23: RAFAEL | I23: BOGOTA_D.E. | J23: BOGOTA | K23: 1. DEPENDIENTE | L23: NINGUNO | M23: 24 | N23: NO | O23: NO | Q23: NO | S23: Todos los sistemas (ARL, AFP, CCF, EPS) | T23: 46055 | U23: NO | V23: NO | W23: NO | X23: NO | Y23: NO | AA23: SI | AB23: NO | AE23: NO | AH23: NO | AK23: NO | AN23: NO | AO23: NO | AR23: 0 | AU23: NO | AV23: 2223339 | AW23: NO | AX23: NO | AY23: PORVENIR | AZ23: 2 | BA23: 980747 | BB23: 0.16 | BC23: 157000 | BE23: 0 | BF23: 0 | BG23: 0 | BH23: 0 | BI23: 0 | BJ23: 157000 | BK23: NINGUNA | BL23: SALUD TOTAL | BM23: 2 | BN23: 980747 | BO23: 0.125 | BP23: 122600 | BQ23: 0 | BS23: 0 | BU23: 0 | BV23: NINGUNA | BW23: COLMENA | BX23: 2 | BY23: 980747 | BZ23: 0.0696 | CA23: 5 | CB23: CENTRO TRABAJO 24 | CC23: 5711001 | CD23: 68300 | CE23: 2 | CF23: COMPENSAR | CG23: 1535765 | CH23: 0.04 | CI23: 61500 | CJ23: 1535765 | CK23: 0.02 | CL23: 30800 | CM23: 0.03 | CN23: 46100 | CO23: 0 | CP23: 0 | CQ23: 0 | CR23: 0 | CS23: SI
A24: CAUSADO | B24: CC | C24: 1004308195 | D24: RODRIGUEZ CONTRERAS BLADIMIR JOSE | E24: RODRIGUEZ | F24: CONTRERAS | G24: BLADIMIR | H24: JOSE | I24: LA_GUAJIRA | J24: RIOHACHA | K24: 1. DEPENDIENTE | L24: NINGUNO | M24: 203 | N24: NO | O24: NO | Q24: NO | S24: NO | U24: NO | V24: NO | W24: NO | X24: NO | Y24: NO | AA24: SI | AB24: NO | AE24: NO | AH24: NO | AK24: NO | AN24: NO | AO24: NO | AR24: 0 | AU24: NO | AV24: 2223339 | AW24: NO | AX24: NO | AY24: PORVENIR | AZ24: 30 | BA24: 2602824 | BB24: 0.16 | BC24: 416500 | BE24: 0 | BF24: 0 | BG24: 0 | BH24: 0 | BI24: 0 | BJ24: 416500 | BK24: NINGUNA | BL24: SALUD TOTAL | BM24: 30 | BN24: 2602824 | BO24: 0.04 | BP24: 104200 | BQ24: 0 | BS24: 0 | BU24: 0 | BV24: NINGUNA | BW24: COLMENA | BX24: 30 | BY24: 2602824 | BZ24: 0.0696 | CA24: 5 | CB24: CENTRO TRABAJO 30 | CC24: 5711001 | CD24: 181200 | CE24: 30 | CF24: COMFAMILIAR GUAJIRA | CG24: 2602824 | CH24: 0.04 | CI24: 104200 | CJ24: 2602824 | CK24: 0 | CL24: 0 | CM24: 0 | CN24: 0 | CO24: 0 | CP24: 0 | CQ24: 0 | CR24: 0 | CS24: SI
A25: CAUSADO | B25: CC | C25: 1006713857 | D25: PACHECO AGUDELO DANIEL JOSE | E25: PACHECO | F25: AGUDELO | G25: DANIEL | H25: JOSE | I25: LA_GUAJIRA | J25: RIOHACHA | K25: 1. DEPENDIENTE | L25: NINGUNO | M25: 204 | N25: NO | O25: NO | Q25: NO | S25: NO | U25: NO | V25: NO | W25: NO | X25: NO | Y25: NO | AA25: SI | AB25: NO | AE25: NO | AH25: NO | AK25: NO | AN25: NO | AO25: NO | AR25: 0 | AU25: NO | AV25: 1750905 | AW25: NO | AX25: NO | AY25: PORVENIR | AZ25: 30 | BA25: 2059702 | BB25: 0.16 | BC25: 329600 | BE25: 0 | BF25: 0 | BG25: 0 | BH25: 0 | BI25: 0 | BJ25: 329600 | BK25: NINGUNA | BL25: NUEVA E.P.S. | BM25: 30 | BN25: 2059702 | BO25: 0.04 | BP25: 82400 | BQ25: 0 | BS25: 0 | BU25: 0 | BV25: NINGUNA | BW25: COLMENA | BX25: 30 | BY25: 2059702 | BZ25: 0.0696 | CA25: 5 | CB25: CENTRO TRABAJO 30 | CC25: 5711001 | CD25: 143400 | CE25: 30 | CF25: COMFAMILIAR GUAJIRA | CG25: 2059702 | CH25: 0.04 | CI25: 82400 | CJ25: 2059702 | CK25: 0 | CL25: 0 | CM25: 0 | CN25: 0 | CO25: 0 | CP25: 0 | CQ25: 0 | CR25: 0 | CS25: SI
A26: CAUSADO | B26: CC | C26: 1006727380 | D26: CERVANTES MUÑOZ ONER DAVID | E26: CERVANTES | F26: MUÑOZ | G26: ONER | H26: DAVID | I26: BOGOTA_D.E. | J26: BOGOTA | K26: 1. DEPENDIENTE | L26: NINGUNO | M26: 0 | N26: NO | O26: NO | Q26: NO | S26: NO | U26: NO | V26: NO | W26: NO | X26: NO | Y26: NO | AA26: NO | AB26: LICENCIA NO REMUNERADA | AC26: 46054 | AD26: 46055 | AE26: NO | AH26: NO | AK26: NO | AN26: NO | AO26: NO | AR26: 0 | AU26: NO | AV26: 1750905 | AW26: NO | AX26: NO | AY26: PROTECCION | AZ26: 2 | BA26: 116727 | BB26: 0.16 | BC26: 18700 | BE26: 0 | BF26: 0 | BG26: 0 | BH26: 0 | BI26: 0 | BJ26: 18700 | BK26: NINGUNA | BL26: SALUD TOTAL | BM26: 2 | BN26: 116727 | BO26: 0 | BP26: 0 | BQ26: 0 | BS26: 0 | BU26: 0 | BV26: NINGUNA | BW26: COLMENA | BX26: 2 | BY26: 116727 | BZ26: 0 | CA26: 5 | CB26: CENTRO TRABAJO 24 | CC26: 5711001 | CD26: 0 | CE26: 2 | CF26: COMPENSAR | CG26: 0 | CH26: 0 | CI26: 0 | CJ26: 0 | CK26: 0 | CL26: 0 | CM26: 0 | CN26: 0 | CO26: 0 | CP26: 0 | CQ26: 0 | CR26: 0 | CS26: SI
A27: CAUSADO | B27: CC | C27: 1006727380 | D27: CERVANTES MUÑOZ ONER DAVID | E27: CERVANTES | F27: MUÑOZ | G27: ONER | H27: DAVID | I27: BOGOTA_D.E. | J27: BOGOTA | K27: 1. DEPENDIENTE | L27: NINGUNO | M27: 24 | N27: NO | O27: NO | Q27: NO | S27: Todos los sistemas (ARL, AFP, CCF, EPS) | T27: 46056 | U27: NO | V27: NO | W27: NO | X27: NO | Y27: NO | AA27: SI | AB27: NO | AE27: NO | AH27: NO | AK27: NO | AN27: NO | AO27: NO | AR27: 0 | AU27: NO | AV27: 1750905 | AW27: NO | AX27: NO | AY27: PROTECCION | AZ27: 1 | BA27: 721400 | BB27: 0.16 | BC27: 115500 | BE27: 0 | BF27: 0 | BG27: 0 | BH27: 0 | BI27: 0 | BJ27: 115500 | BK27: NINGUNA | BL27: SALUD TOTAL | BM27: 1 | BN27: 721400 | BO27: 0.04 | BP27: 28900 | BQ27: 0 | BS27: 0 | BU27: 0 | BV27: NINGUNA | BW27: COLMENA | BX27: 1 | BY27: 721400 | BZ27: 0.0696 | CA27: 5 | CB27: CENTRO TRABAJO 24 | CC27: 5711001 | CD27: 50300 | CE27: 1 | CF27: COMPENSAR | CG27: 1302414 | CH27: 0.04 | CI27: 52100 | CJ27: 1302414 | CK27: 0 | CL27: 0 | CM27: 0 | CN27: 0 | CO27: 0 | CP27: 0 | CQ27: 0 | CR27: 0 | CS27: SI
A28: CAUSADO | B28: CC | C28: 1006733914 | D28: CUEVA CONTRERAS EDAIR ALEJANDRO | E28: CUEVA | F28: CONTRERAS | G28: EDAIR | H28: ALEJANDRO | I28: LA_GUAJIRA | J28: RIOHACHA | K28: 1. DEPENDIENTE | L28: NINGUNO | M28: 205 | N28: NO | O28: NO | Q28: NO | S28: NO | U28: NO | V28: NO | W28: NO | X28: NO | Y28: NO | AA28: SI | AB28: NO | AE28: NO | AH28: NO | AK28: NO | AN28: NO | AO28: NO | AR28: 0 | AU28: NO | AV28: 1785595 | AW28: NO | AX28: NO | AY28: PORVENIR | AZ28: 30 | BA28: 2110655 | BB28: 0.16 | BC28: 337800 | BE28: 0 | BF28: 0 | BG28: 0 | BH28: 0 | BI28: 0 | BJ28: 337800 | BK28: NINGUNA | BL28: NUEVA E.P.S. | BM28: 30 | BN28: 2110655 | BO28: 0.04 | BP28: 84500 | BQ28: 0 | BS28: 0 | BU28: 0 | BV28: NINGUNA | BW28: COLMENA | BX28: 30 | BY28: 2110655 | BZ28: 0.0696 | CA28: 5 | CB28: CENTRO TRABAJO 30 | CC28: 5711001 | CD28: 147000 | CE28: 30 | CF28: COMFAMILIAR GUAJIRA | CG28: 2110655 | CH28: 0.04 | CI28: 84500 | CJ28: 2110655 | CK28: 0 | CL28: 0 | CM28: 0 | CN28: 0 | CO28: 0 | CP28: 0 | CQ28: 0 | CR28: 0 | CS28: SI
A29: CAUSADO | B29: CC | C29: 1006734131 | D29: GOMEZ ORTEGA JEINER JOSE | E29: GOMEZ | F29: ORTEGA | G29: JEINER | H29: JOSE | I29: LA_GUAJIRA | J29: RIOHACHA | K29: 1. DEPENDIENTE | L29: NINGUNO | M29: 0 | N29: NO | O29: NO | Q29: NO | S29: NO | U29: NO | V29: NO | W29: NO | X29: NO | Y29: NO | AA29: NO | AB29: NO | AE29: INCAPACIDAD GENERAL | AF29: 46055 | AG29: 46056 | AH29: NO | AK29: NO | AN29: NO | AO29: NO | AR29: 0 | AU29: NO | AV29: 2074908 | AW29: NO | AX29: NO | AY29: PORVENIR | AZ29: 2 | BA29: 162980 | BB29: 0.16 | BC29: 26100 | BE29: 0 | BF29: 0 | BG29: 0 | BH29: 0 | BI29: 0 | BJ29: 26100 | BK29: NINGUNA | BL29: NUEVA E.P.S. | BM29: 2 | BN29: 162980 | BO29: 0.04 | BP29: 6600 | BQ29: 0 | BS29: 0 | BU29: 0 | BV29: NINGUNA | BW29: COLMENA | BX29: 2 | BY29: 162980 | BZ29: 0 | CA29: 5 | CB29: CENTRO TRABAJO 30 | CC29: 5711001 | CD29: 0 | CE29: 2 | CF29: COMFAMILIAR GUAJIRA | CG29: 0 | CH29: 0 | CI29: 0 | CJ29: 0 | CK29: 0 | CL29: 0 | CM29: 0 | CN29: 0 | CO29: 0 | CP29: 0 | CQ29: 0 | CR29: 0 | CS29: SI
A30: CAUSADO | B30: CC | C30: 1006734131 | D30: GOMEZ ORTEGA JEINER JOSE | E30: GOMEZ | F30: ORTEGA | G30: JEINER | H30: JOSE | I30: LA_GUAJIRA | J30: RIOHACHA | K30: 1. DEPENDIENTE | L30: NINGUNO | M30: 184 | N30: NO | O30: NO | Q30: NO | S30: NO | U30: NO | V30: NO | W30: NO | X30: NO | Y30: NO | AA30: SI | AB30: NO | AE30: NO | AH30: NO | AK30: NO | AN30: NO | AO30: NO | AR30: 0 | AU30: NO | AV30: 2074908 | AW30: NO | AX30: NO | AY30: PORVENIR | AZ30: 28 | BA30: 2237443 | BB30: 0.16 | BC30: 358000 | BE30: 0 | BF30: 0 | BG30: 0 | BH30: 0 | BI30: 0 | BJ30: 358000 | BK30: NINGUNA | BL30: NUEVA E.P.S. | BM30: 28 | BN30: 2237443 | BO30: 0.04 | BP30: 89500 | BQ30: 0 | BS30: 0 | BU30: 0 | BV30: NINGUNA | BW30: COLMENA | BX30: 28 | BY30: 2237443 | BZ30: 0.0696 | CA30: 5 | CB30: CENTRO TRABAJO 30 | CC30: 5711001 | CD30: 155800 | CE30: 28 | CF30: COMFAMILIAR GUAJIRA | CG30: 2237443 | CH30: 0.04 | CI30: 89500 | CJ30: 2237443 | CK30: 0 | CL30: 0 | CM30: 0 | CN30: 0 | CO30: 0 | CP30: 0 | CQ30: 0 | CR30: 0 | CS30: SI
A31: CAUSADO | B31: CC | C31: 1006734275 | D31: BRITO BRITO NEIDER IVAN | E31: BRITO | F31: BRITO | G31: NEIDER | H31: IVAN | I31: LA_GUAJIRA | J31: RIOHACHA | K31: 1. DEPENDIENTE | L31: NINGUNO | M31: 205 | N31: NO | O31: NO | Q31: NO | S31: NO | U31: NO | V31: NO | W31: NO | X31: NO | Y31: NO | AA31: SI | AB31: NO | AE31: NO | AH31: NO | AK31: NO | AN31: NO | AO31: NO | AR31: 0 | AU31: NO | AV31: 1750905 | AW31: NO | AX31: NO | AY31: PORVENIR | AZ31: 30 | BA31: 2069651 | BB31: 0.16 | BC31: 331200 | BE31: 0 | BF31: 0 | BG31: 0 | BH31: 0 | BI31: 0 | BJ31: 331200 | BK31: NINGUNA | BL31: NUEVA E.P.S. | BM31: 30 | BN31: 2069651 | BO31: 0.04 | BP31: 82800 | BQ31: 0 | BS31: 0 | BU31: 0 | BV31: NINGUNA | BW31: COLMENA | BX31: 30 | BY31: 2069651 | BZ31: 0.0696 | CA31: 5 | CB31: CENTRO TRABAJO 30 | CC31: 5711001 | CD31: 144100 | CE31: 30 | CF31: COMFAMILIAR GUAJIRA | CG31: 2069651 | CH31: 0.04 | CI31: 82800 | CJ31: 2069651 | CK31: 0 | CL31: 0 | CM31: 0 | CN31: 0 | CO31: 0 | CP31: 0 | CQ31: 0 | CR31: 0 | CS31: SI
A32: CAUSADO | B32: CC | C32: 1006734430 | D32: MARTINEZ LARA CAMILO ENRIQUE | E32: MARTINEZ | F32: LARA | G32: CAMILO | H32: ENRIQUE | I32: LA_GUAJIRA | J32: RIOHACHA | K32: 1. DEPENDIENTE | L32: NINGUNO | M32: 0 | N32: NO | O32: NO | Q32: NO | S32: NO | U32: NO | V32: NO | W32: NO | X32: NO | Y32: NO | AA32: NO | AB32: LICENCIA NO REMUNERADA | AC32: 46054 | AD32: 46054 | AE32: NO | AH32: NO | AK32: NO | AN32: NO | AO32: NO | AR32: 0 | AU32: NO | AV32: 1750905 | AW32: NO | AX32: NO | AY32: PROTECCION | AZ32: 1 | BA32: 58364 | BB32: 0.16 | BC32: 9400 | BE32: 0 | BF32: 0 | BG32: 0 | BH32: 0 | BI32: 0 | BJ32: 9400 | BK32: NINGUNA | BL32: SANITAS | BM32: 1 | BN32: 58364 | BO32: 0 | BP32: 0 | BQ32: 0 | BS32: 0 | BU32: 0 | BV32: NINGUNA | BW32: COLMENA | BX32: 1 | BY32: 58364 | BZ32: 0 | CA32: 5 | CB32: CENTRO TRABAJO 30 | CC32: 5711001 | CD32: 0 | CE32: 1 | CF32: COMFAMILIAR GUAJIRA | CG32: 0 | CH32: 0 | CI32: 0 | CJ32: 0 | CK32: 0 | CL32: 0 | CM32: 0 | CN32: 0 | CO32: 0 | CP32: 0 | CQ32: 0 | CR32: 0 | CS32: SI
A33: CAUSADO | B33: CC | C33: 1006734430 | D33: MARTINEZ LARA CAMILO ENRIQUE | E33: MARTINEZ | F33: LARA | G33: CAMILO | H33: ENRIQUE | I33: LA_GUAJIRA | J33: RIOHACHA | K33: 1. DEPENDIENTE | L33: NINGUNO | M33: 0 | N33: NO | O33: NO | Q33: NO | S33: NO | U33: NO | V33: NO | W33: NO | X33: NO | Y33: NO | AA33: NO | AB33: LICENCIA NO REMUNERADA | AC33: 46069 | AD33: 46070 | AE33: NO | AH33: NO | AK33: NO | AN33: NO | AO33: NO | AR33: 0 | AU33: NO | AV33: 1750905 | AW33: NO | AX33: NO | AY33: PROTECCION | AZ33: 2 | BA33: 116727 | BB33: 0.16 | BC33: 18700 | BE33: 0 | BF33: 0 | BG33: 0 | BH33: 0 | BI33: 0 | BJ33: 18700 | BK33: NINGUNA | BL33: SANITAS | BM33: 2 | BN33: 116727 | BO33: 0 | BP33: 0 | BQ33: 0 | BS33: 0 | BU33: 0 | BV33: NINGUNA | BW33: COLMENA | BX33: 2 | BY33: 116727 | BZ33: 0 | CA33: 5 | CB33: CENTRO TRABAJO 30 | CC33: 5711001 | CD33: 0 | CE33: 2 | CF33: COMFAMILIAR GUAJIRA | CG33: 0 | CH33: 0 | CI33: 0 | CJ33: 0 | CK33: 0 | CL33: 0 | CM33: 0 | CN33: 0 | CO33: 0 | CP33: 0 | CQ33: 0 | CR33: 0 | CS33: SI
A34: CAUSADO | B34: CC | C34: 1006734430 | D34: MARTINEZ LARA CAMILO ENRIQUE | E34: MARTINEZ | F34: LARA | G34: CAMILO | H34: ENRIQUE | I34: LA_GUAJIRA | J34: RIOHACHA | K34: 1. DEPENDIENTE | L34: NINGUNO | M34: 187 | N34: NO | O34: NO | Q34: NO | S34: NO | U34: NO | V34: NO | W34: NO | X34: NO | Y34: NO | AA34: SI | AB34: NO | AE34: NO | AH34: NO | AK34: NO | AN34: NO | AO34: NO | AR34: 0 | AU34: NO | AV34: 1750905 | AW34: NO | AX34: NO | AY34: PROTECCION | AZ34: 27 | BA34: 1859541 | BB34: 0.16 | BC34: 297600 | BE34: 0 | BF34: 0 | BG34: 0 | BH34: 0 | BI34: 0 | BJ34: 297600 | BK34: NINGUNA | BL34: SANITAS | BM34: 27 | BN34: 1859541 | BO34: 0.04 | BP34: 74400 | BQ34: 0 | BS34: 0 | BU34: 0 | BV34: NINGUNA | BW34: COLMENA | BX34: 27 | BY34: 1859541 | BZ34: 0.0696 | CA34: 5 | CB34: CENTRO TRABAJO 30 | CC34: 5711001 | CD34: 129500 | CE34: 27 | CF34: COMFAMILIAR GUAJIRA | CG34: 1859541 | CH34: 0.04 | CI34: 74400 | CJ34: 1859541 | CK34: 0 | CL34: 0 | CM34: 0 | CN34: 0 | CO34: 0 | CP34: 0 | CQ34: 0 | CR34: 0 | CS34: SI
A35: CAUSADO | B35: CC | C35: 1006734693 | D35: IPUANA URIANA SAMIR ANTONIO | E35: IPUANA | F35: URIANA | G35: SAMIR | H35: ANTONIO | I35: LA_GUAJIRA | J35: RIOHACHA | K35: 1. DEPENDIENTE | L35: NINGUNO | M35: 0 | N35: NO | O35: NO | Q35: NO | S35: NO | U35: NO | V35: NO | W35: NO | X35: NO | Y35: NO | AA35: NO | AB35: LICENCIA NO REMUNERADA | AC35: 46054 | AD35: 46054 | AE35: NO | AH35: NO | AK35: NO | AN35: NO | AO35: NO | AR35: 0 | AU35: NO | AV35: 1750905 | AW35: NO | AX35: NO | AY35: PROTECCION | AZ35: 1 | BA35: 58364 | BB35: 0.16 | BC35: 9400 | BE35: 0 | BF35: 0 | BG35: 0 | BH35: 0 | BI35: 0 | BJ35: 9400 | BK35: NINGUNA | BL35: NUEVA E.P.S. | BM35: 1 | BN35: 58364 | BO35: 0 | BP35: 0 | BQ35: 0 | BS35: 0 | BU35: 0 | BV35: NINGUNA | BW35: COLMENA | BX35: 1 | BY35: 58364 | BZ35: 0 | CA35: 5 | CB35: CENTRO TRABAJO 30 | CC35: 5711001 | CD35: 0 | CE35: 1 | CF35: COMFAMILIAR GUAJIRA | CG35: 0 | CH35: 0 | CI35: 0 | CJ35: 0 | CK35: 0 | CL35: 0 | CM35: 0 | CN35: 0 | CO35: 0 | CP35: 0 | CQ35: 0 | CR35: 0 | CS35: SI
A36: CAUSADO | B36: CC | C36: 1006734693 | D36: IPUANA URIANA SAMIR ANTONIO | E36: IPUANA | F36: URIANA | G36: SAMIR | H36: ANTONIO | I36: LA_GUAJIRA | J36: RIOHACHA | K36: 1. DEPENDIENTE | L36: NINGUNO | M36: 211 | N36: NO | O36: NO | Q36: NO | S36: NO | U36: NO | V36: NO | W36: NO | X36: NO | Y36: NO | AA36: SI | AB36: NO | AE36: NO | AH36: NO | AK36: NO | AN36: NO | AO36: NO | AR36: 0 | AU36: NO | AV36: 1750905 | AW36: NO | AX36: NO | AY36: PROTECCION | AZ36: 29 | BA36: 2035959 | BB36: 0.16 | BC36: 325800 | BE36: 0 | BF36: 0 | BG36: 0 | BH36: 0 | BI36: 0 | BJ36: 325800 | BK36: NINGUNA | BL36: NUEVA E.P.S. | BM36: 29 | BN36: 2035959 | BO36: 0.04 | BP36: 81500 | BQ36: 0 | BS36: 0 | BU36: 0 | BV36: NINGUNA | BW36: COLMENA | BX36: 29 | BY36: 2035959 | BZ36: 0.0696 | CA36: 5 | CB36: CENTRO TRABAJO 30 | CC36: 5711001 | CD36: 141800 | CE36: 29 | CF36: COMFAMILIAR GUAJIRA | CG36: 2035959 | CH36: 0.04 | CI36: 81500 | CJ36: 2035959 | CK36: 0 | CL36: 0 | CM36: 0 | CN36: 0 | CO36: 0 | CP36: 0 | CQ36: 0 | CR36: 0 | CS36: SI
A37: CAUSADO | B37: CC | C37: 1006734779 | D37: RIZO RIVAS ANDRES MANUEL | E37: RIZO | F37: RIVAS | G37: ANDRES | H37: MANUEL | I37: LA_GUAJIRA | J37: RIOHACHA | K37: 1. DEPENDIENTE | L37: NINGUNO | M37: 0 | N37: NO | O37: NO | Q37: NO | S37: NO | U37: NO | V37: NO | W37: NO | X37: NO | Y37: NO | AA37: NO | AB37: LICENCIA NO REMUNERADA | AC37: 46054 | AD37: 46055 | AE37: NO | AH37: NO | AK37: NO | AN37: NO | AO37: NO | AR37: 0 | AU37: NO | AV37: 1750905 | AW37: NO | AX37: NO | AY37: COLPENSIONES | AZ37: 2 | BA37: 116727 | BB37: 0.16 | BC37: 18700 | BE37: 0 | BF37: 0 | BG37: 0 | BH37: 0 | BI37: 0 | BJ37: 18700 | BK37: NINGUNA | BL37: DUSAKAWI | BM37: 2 | BN37: 116727 | BO37: 0 | BP37: 0 | BQ37: 0 | BS37: 0 | BU37: 0 | BV37: NINGUNA | BW37: COLMENA | BX37: 2 | BY37: 116727 | BZ37: 0 | CA37: 5 | CB37: CENTRO TRABAJO 30 | CC37: 5711001 | CD37: 0 | CE37: 2 | CF37: COMFAMILIAR GUAJIRA | CG37: 0 | CH37: 0 | CI37: 0 | CJ37: 0 | CK37: 0 | CL37: 0 | CM37: 0 | CN37: 0 | CO37: 0 | CP37: 0 | CQ37: 0 | CR37: 0 | CS37: SI
A38: CAUSADO | B38: CC | C38: 1006734779 | D38: RIZO RIVAS ANDRES MANUEL | E38: RIZO | F38: RIVAS | G38: ANDRES | H38: MANUEL | I38: LA_GUAJIRA | J38: RIOHACHA | K38: 1. DEPENDIENTE | L38: NINGUNO | M38: 199 | N38: NO | O38: NO | Q38: NO | S38: NO | U38: NO | V38: NO | W38: NO | X38: NO | Y38: NO | AA38: SI | AB38: NO | AE38: NO | AH38: NO | AK38: NO | AN38: NO | AO38: NO | AR38: 0 | AU38: NO | AV38: 1750905 | AW38: NO | AX38: NO | AY38: COLPENSIONES | AZ38: 28 | BA38: 1982769 | BB38: 0.16 | BC38: 317300 | BE38: 0 | BF38: 0 | BG38: 0 | BH38: 0 | BI38: 0 | BJ38: 317300 | BK38: NINGUNA | BL38: DUSAKAWI | BM38: 28 | BN38: 1982769 | BO38: 0.04 | BP38: 79400 | BQ38: 0 | BS38: 0 | BU38: 0 | BV38: NINGUNA | BW38: COLMENA | BX38: 28 | BY38: 1982769 | BZ38: 0.0696 | CA38: 5 | CB38: CENTRO TRABAJO 30 | CC38: 5711001 | CD38: 138100 | CE38: 28 | CF38: COMFAMILIAR GUAJIRA | CG38: 1982769 | CH38: 0.04 | CI38: 79400 | CJ38: 1982769 | CK38: 0 | CL38: 0 | CM38: 0 | CN38: 0 | CO38: 0 | CP38: 0 | CQ38: 0 | CR38: 0 | CS38: SI
A39: CAUSADO | B39: CC | C39: 1006817439 | D39: DIAZ LOPEZ JAIME LUIS | E39: DIAZ | F39: LOPEZ | G39: JAIME | H39: LUIS | I39: LA_GUAJIRA | J39: RIOHACHA | K39: 1. DEPENDIENTE | L39: NINGUNO | M39: 204 | N39: NO | O39: NO | Q39: NO | S39: Todos los sistemas (ARL, AFP, CCF, EPS) | T39: 46076 | U39: NO | V39: NO | W39: NO | X39: NO | Y39: NO | AA39: SI | AB39: NO | AE39: NO | AH39: NO | AK39: NO | AN39: NO | AO39: NO | AR39: 0 | AU39: NO | AV39: 1750905 | AW39: NO | AX39: NO | AY39: PORVENIR | AZ39: 23 | BA39: 2062991 | BB39: 0.16 | BC39: 330100 | BE39: 0 | BF39: 0 | BG39: 0 | BH39: 0 | BI39: 0 | BJ39: 330100 | BK39: NINGUNA | BL39: NUEVA E.P.S. | BM39: 23 | BN39: 2062991 | BO39: 0.04 | BP39: 82600 | BQ39: 0 | BS39: 0 | BU39: 0 | BV39: NINGUNA | BW39: COLMENA | BX39: 23 | BY39: 2062991 | BZ39: 0.0696 | CA39: 5 | CB39: CENTRO TRABAJO 30 | CC39: 5711001 | CD39: 143600 | CE39: 23 | CF39: COMFAMILIAR GUAJIRA | CG39: 2780760 | CH39: 0.04 | CI39: 111300 | CJ39: 2780760 | CK39: 0 | CL39: 0 | CM39: 0 | CN39: 0 | CO39: 0 | CP39: 0 | CQ39: 0 | CR39: 0 | CS39: SI
A40: CAUSADO | B40: CC | C40: 1007855319 | D40: MENDOZA VALDEZ ARAMIS | E40: MENDOZA | F40: VALDEZ | G40: ARAMIS | I40: BOGOTA_D.E. | J40: BOGOTA | K40: 1. DEPENDIENTE | L40: NINGUNO | M40: 225 | N40: NO | O40: NO | Q40: NO | S40: NO | U40: NO | V40: NO | W40: NO | X40: NO | Y40: NO | AA40: SI | AB40: NO | AE40: NO | AH40: NO | AK40: NO | AN40: NO | AO40: NO | AR40: 0 | AU40: NO | AV40: 2074908 | AW40: NO | AX40: NO | AY40: PORVENIR | AZ40: 30 | BA40: 3157161 | BB40: 0.16 | BC40: 505200 | BE40: 0 | BF40: 0 | BG40: 0 | BH40: 0 | BI40: 0 | BJ40: 505200 | BK40: NINGUNA | BL40: SALUD TOTAL | BM40: 30 | BN40: 3157161 | BO40: 0.04 | BP40: 126300 | BQ40: 0 | BS40: 0 | BU40: 0 | BV40: NINGUNA | BW40: COLMENA | BX40: 30 | BY40: 3157161 | BZ40: 0.0696 | CA40: 5 | CB40: CENTRO TRABAJO 24 | CC40: 5711001 | CD40: 219800 | CE40: 30 | CF40: COMPENSAR | CG40: 3157161 | CH40: 0.04 | CI40: 126300 | CJ40: 3157161 | CK40: 0 | CL40: 0 | CM40: 0 | CN40: 0 | CO40: 0 | CP40: 0 | CQ40: 0 | CR40: 0 | CS40: SI
A41: CAUSADO | B41: CC | C41: 1010049805 | D41: MEJIA SIERRA ABRAHAN JOSE | E41: MEJIA | F41: SIERRA | G41: ABRAHAN | H41: JOSE | I41: LA_GUAJIRA | J41: RIOHACHA | K41: 1. DEPENDIENTE | L41: NINGUNO | M41: 0 | N41: NO | O41: NO | Q41: NO | S41: NO | U41: NO | V41: NO | W41: NO | X41: NO | Y41: NO | AA41: NO | AB41: LICENCIA NO REMUNERADA | AC41: 46069 | AD41: 46069 | AE41: NO | AH41: NO | AK41: NO | AN41: NO | AO41: NO | AR41: 0 | AU41: NO | AV41: 1785595 | AW41: NO | AX41: NO | AY41: PROTECCION | AZ41: 1 | BA41: 59520 | BB41: 0.16 | BC41: 9600 | BE41: 0 | BF41: 0 | BG41: 0 | BH41: 0 | BI41: 0 | BJ41: 9600 | BK41: NINGUNA | BL41: SANITAS | BM41: 1 | BN41: 59520 | BO41: 0 | BP41: 0 | BQ41: 0 | BS41: 0 | BU41: 0 | BV41: NINGUNA | BW41: COLMENA | BX41: 1 | BY41: 59520 | BZ41: 0 | CA41: 5 | CB41: CENTRO TRABAJO 30 | CC41: 5711001 | CD41: 0 | CE41: 1 | CF41: COMFAMILIAR GUAJIRA | CG41: 0 | CH41: 0 | CI41: 0 | CJ41: 0 | CK41: 0 | CL41: 0 | CM41: 0 | CN41: 0 | CO41: 0 | CP41: 0 | CQ41: 0 | CR41: 0 | CS41: SI
A42: CAUSADO | B42: CC | C42: 1010049805 | D42: MEJIA SIERRA ABRAHAN JOSE | E42: MEJIA | F42: SIERRA | G42: ABRAHAN | H42: JOSE | I42: LA_GUAJIRA | J42: RIOHACHA | K42: 1. DEPENDIENTE | L42: NINGUNO | M42: 162 | N42: NO | O42: NO | Q42: NO | S42: Todos los sistemas (ARL, AFP, CCF, EPS) | T42: 46076 | U42: NO | V42: NO | W42: NO | X42: NO | Y42: NO | AA42: SI | AB42: NO | AE42: NO | AH42: NO | AK42: NO | AN42: NO | AO42: NO | AR42: 0 | AU42: NO | AV42: 1785595 | AW42: NO | AX42: NO | AY42: PROTECCION | AZ42: 22 | BA42: 1682166 | BB42: 0.16 | BC42: 269200 | BE42: 0 | BF42: 0 | BG42: 0 | BH42: 0 | BI42: 0 | BJ42: 269200 | BK42: NINGUNA | BL42: SANITAS | BM42: 22 | BN42: 1682166 | BO42: 0.04 | BP42: 67300 | BQ42: 0 | BS42: 0 | BU42: 0 | BV42: NINGUNA | BW42: COLMENA | BX42: 22 | BY42: 1682166 | BZ42: 0.0696 | CA42: 5 | CB42: CENTRO TRABAJO 30 | CC42: 5711001 | CD42: 117100 | CE42: 22 | CF42: COMFAMILIAR GUAJIRA | CG42: 2503076 | CH42: 0.04 | CI42: 100200 | CJ42: 2503076 | CK42: 0 | CL42: 0 | CM42: 0 | CN42: 0 | CO42: 0 | CP42: 0 | CQ42: 0 | CR42: 0 | CS42: SI
A43: CAUSADO | B43: CC | C43: 1010102552 | D43: SIERRA CASTRO JUAN DAVID | E43: SIERRA | F43: CASTRO | G43: JUAN | H43: DAVID | I43: LA_GUAJIRA | J43: RIOHACHA | K43: 1. DEPENDIENTE | L43: NINGUNO | M43: 205 | N43: NO | O43: NO | Q43: NO | S43: NO | U43: NO | V43: NO | W43: NO | X43: NO | Y43: NO | AA43: SI | AB43: NO | AE43: NO | AH43: NO | AK43: NO | AN43: NO | AO43: NO | AR43: 0 | AU43: NO | AV43: 2074908 | AW43: NO | AX43: NO | AY43: PORVENIR | AZ43: 30 | BA43: 2452635 | BB43: 0.16 | BC43: 392500 | BE43: 0 | BF43: 0 | BG43: 0 | BH43: 0 | BI43: 0 | BJ43: 392500 | BK43: NINGUNA | BL43: NUEVA E.P.S. | BM43: 30 | BN43: 2452635 | BO43: 0.04 | BP43: 98200 | BQ43: 0 | BS43: 0 | BU43: 0 | BV43: NINGUNA | BW43: COLMENA | BX43: 30 | BY43: 2452635 | BZ43: 0.0696 | CA43: 5 | CB43: CENTRO TRABAJO 30 | CC43: 5711001 | CD43: 170800 | CE43: 30 | CF43: COMFAMILIAR GUAJIRA | CG43: 2452635 | CH43: 0.04 | CI43: 98200 | CJ43: 2452635 | CK43: 0 | CL43: 0 | CM43: 0 | CN43: 0 | CO43: 0 | CP43: 0 | CQ43: 0 | CR43: 0 | CS43: SI
A44: CAUSADO | B44: CE | C44: 1011020 | D44: HEREDIA MENDOZA HECTOR YOHAN | E44: HEREDIA | F44: MENDOZA | G44: HECTOR | H44: YOHAN | I44: VALLE | J44: CALI | K44: 1. DEPENDIENTE | L44: NINGUNO | M44: 0 | N44: NO | O44: NO | Q44: NO | S44: NO | U44: NO | V44: NO | W44: NO | X44: NO | Y44: NO | AA44: NO | AB44: NO | AE44: NO | AH44: NO | AK44: LICENCIA REMUNERADA | AL44: 46069 | AM44: 46075 | AN44: NO | AO44: NO | AR44: 0 | AU44: NO | AV44: 7656636 | AW44: NO | AX44: NO | AY44: SKANDIA | AZ44: 7 | BA44: 1786549 | BB44: 0.16 | BC44: 285900 | BE44: 0 | BF44: 0 | BG44: 9000 | BH44: 9000 | BI44: 0 | BJ44: 303900 | BK44: NINGUNA | BL44: SANITAS | BM44: 7 | BN44: 1786549 | BO44: 0.04 | BP44: 71500 | BQ44: 0 | BS44: 0 | BU44: 0 | BV44: NINGUNA | BW44: COLMENA | BX44: 7 | BY44: 1786549 | BZ44: 0 | CA44: 5 | CB44: CENTRO TRABAJO 56 | CC44: 5711001 | CD44: 0 | CE44: 7 | CF44: COMFENALCO VALLE | CG44: 1786549 | CH44: 0.04 | CI44: 71500 | CJ44: 1786549 | CK44: 0 | CL44: 0 | CM44: 0 | CN44: 0 | CO44: 0 | CP44: 0 | CQ44: 0 | CR44: 0 | CS44: SI
A45: CAUSADO | B45: CE | C45: 1011020 | D45: HEREDIA MENDOZA HECTOR YOHAN | E45: HEREDIA | F45: MENDOZA | G45: HECTOR | H45: YOHAN | I45: VALLE | J45: CALI | K45: 1. DEPENDIENTE | L45: NINGUNO | M45: 135 | N45: NO | O45: NO | Q45: NO | S45: NO | U45: NO | V45: NO | W45: NO | X45: NO | Y45: SI | Z45: 46054 | AA45: NO | AB45: NO | AE45: NO | AH45: NO | AK45: NO | AN45: NO | AO45: NO | AR45: 0 | AU45: NO | AV45: 7656636 | AW45: NO | AX45: NO | AY45: SKANDIA | AZ45: 23 | BA45: 5870088 | BB45: 0.16 | BC45: 939300 | BE45: 0 | BF45: 0 | BG45: 29400 | BH45: 29400 | BI45: 0 | BJ45: 998100 | BK45: NINGUNA | BL45: SANITAS | BM45: 23 | BN45: 5870088 | BO45: 0.04 | BP45: 234900 | BQ45: 0 | BS45: 0 | BU45: 0 | BV45: NINGUNA | BW45: COLMENA | BX45: 23 | BY45: 5870088 | BZ45: 0.0696 | CA45: 5 | CB45: CENTRO TRABAJO 56 | CC45: 5711001 | CD45: 408600 | CE45: 23 | CF45: COMFENALCO VALLE | CG45: 5870088 | CH45: 0.04 | CI45: 234900 | CJ45: 5870088 | CK45: 0 | CL45: 0 | CM45: 0 | CN45: 0 | CO45: 0 | CP45: 0 | CQ45: 0 | CR45: 0 | CS45: SI
A46: CAUSADO | B46: CC | C46: 1012373455 | D46: VARGAS PARRA JUAN MANUEL | E46: VARGAS | F46: PARRA | G46: JUAN | H46: MANUEL | I46: BOGOTA_D.E. | J46: BOGOTA | K46: 1. DEPENDIENTE | L46: NINGUNO | M46: 74 | N46: NO | O46: NO | Q46: Todos los sistemas (ARL, AFP, CCF, EPS) | R46: 46071 | S46: NO | U46: NO | V46: NO | W46: NO | X46: NO | Y46: NO | AA46: SI | AB46: NO | AE46: NO | AH46: NO | AK46: NO | AN46: NO | AO46: NO | AR46: 0 | AU46: NO | AV46: 2074908 | AW46: NO | AX46: NO | AY46: PROTECCION | AZ46: 13 | BA46: 922706 | BB46: 0.16 | BC46: 147700 | BE46: 0 | BF46: 0 | BG46: 0 | BH46: 0 | BI46: 0 | BJ46: 147700 | BK46: NINGUNA | BL46: COMPENSAR | BM46: 13 | BN46: 922706 | BO46: 0.04 | BP46: 37000 | BQ46: 0 | BS46: 0 | BU46: 0 | BV46: NINGUNA | BW46: COLMENA | BX46: 13 | BY46: 922706 | BZ46: 0.0696 | CA46: 5 | CB46: CENTRO TRABAJO 24 | CC46: 5711001 | CD46: 64300 | CE46: 13 | CF46: COMPENSAR | CG46: 922706 | CH46: 0.04 | CI46: 37000 | CJ46: 922706 | CK46: 0 | CL46: 0 | CM46: 0 | CN46: 0 | CO46: 0 | CP46: 0 | CQ46: 0 | CR46: 0 | CS46: SI
A47: CAUSADO | B47: CC | C47: 1013103308 | D47: CORREA SANCHEZ LUISA FERNANDA | E47: CORREA | F47: SANCHEZ | G47: LUISA | H47: FERNANDA | I47: BOGOTA_D.E. | J47: BOGOTA | K47: 1. DEPENDIENTE | L47: NINGUNO | M47: 74 | N47: NO | O47: NO | Q47: Todos los sistemas (ARL, AFP, CCF, EPS) | R47: 46071 | S47: NO | U47: NO | V47: NO | W47: NO | X47: NO | Y47: NO | AA47: SI | AB47: NO | AE47: NO | AH47: NO | AK47: NO | AN47: NO | AO47: NO | AR47: 0 | AU47: NO | AV47: 1785595 | AW47: NO | AX47: NO | AY47: COLPENSIONES | AZ47: 13 | BA47: 794049 | BB47: 0.16 | BC47: 127100 | BE47: 0 | BF47: 0 | BG47: 0 | BH47: 0 | BI47: 0 | BJ47: 127100 | BK47: NINGUNA | BL47: NUEVA E.P.S. | BM47: 13 | BN47: 794049 | BO47: 0.04 | BP47: 31800 | BQ47: 0 | BS47: 0 | BU47: 0 | BV47: NINGUNA | BW47: COLMENA | BX47: 13 | BY47: 794049 | BZ47: 0.0696 | CA47: 5 | CB47: CENTRO TRABAJO 24 | CC47: 5711001 | CD47: 55300 | CE47: 13 | CF47: COMPENSAR | CG47: 794049 | CH47: 0.04 | CI47: 31800 | CJ47: 794049 | CK47: 0 | CL47: 0 | CM47: 0 | CN47: 0 | CO47: 0 | CP47: 0 | CQ47: 0 | CR47: 0 | CS47: SI
A48: CAUSADO | B48: CC | C48: 1013642764 | D48: GIRALDO MONSALVE JONATHAN ALEXANDER | E48: GIRALDO | F48: MONSALVE | G48: JONATHAN | H48: ALEXANDER | I48: BOGOTA_D.E. | J48: BOGOTA | K48: 1. DEPENDIENTE | L48: NINGUNO | M48: 0 | N48: NO | O48: NO | Q48: NO | S48: NO | U48: NO | V48: NO | W48: NO | X48: NO | Y48: NO | AA48: NO | AB48: NO | AE48: NO | AH48: NO | AK48: LICENCIA REMUNERADA | AL48: 46054 | AM48: 46054 | AN48: NO | AO48: NO | AR48: 0 | AU48: NO | AV48: 8150490 | AW48: NO | AX48: NO | AY48: PROTECCION | AZ48: 1 | BA48: 271683 | BB48: 0.16 | BC48: 43500 | BE48: 0 | BF48: 0 | BG48: 1400 | BH48: 1400 | BI48: 0 | BJ48: 46300 | BK48: NINGUNA | BL48: EPS SURA (ANTES SUSALUD) | BM48: 1 | BN48: 271683 | BO48: 0.04 | BP48: 10900 | BQ48: 0 | BS48: 0 | BU48: 0 | BV48: NINGUNA | BW48: COLMENA | BX48: 1 | BY48: 271683 | BZ48: 0 | CA48: 5 | CB48: CENTRO TRABAJO 24 | CC48: 5711001 | CD48: 0 | CE48: 1 | CF48: COMPENSAR | CG48: 271683 | CH48: 0.04 | CI48: 10900 | CJ48: 271683 | CK48: 0 | CL48: 0 | CM48: 0 | CN48: 0 | CO48: 0 | CP48: 0 | CQ48: 0 | CR48: 0 | CS48: SI
A49: CAUSADO | B49: CC | C49: 1013642764 | D49: GIRALDO MONSALVE JONATHAN ALEXANDER | E49: GIRALDO | F49: MONSALVE | G49: JONATHAN | H49: ALEXANDER | I49: BOGOTA_D.E. | J49: BOGOTA | K49: 1. DEPENDIENTE | L49: NINGUNO | M49: 0 | N49: NO | O49: NO | Q49: NO | S49: NO | U49: NO | V49: NO | W49: NO | X49: NO | Y49: NO | AA49: NO | AB49: NO | AE49: NO | AH49: NO | AK49: LICENCIA REMUNERADA | AL49: 46069 | AM49: 46069 | AN49: NO | AO49: NO | AR49: 0 | AU49: NO | AV49: 8150490 | AW49: NO | AX49: NO | AY49: PROTECCION | AZ49: 1 | BA49: 271683 | BB49: 0.16 | BC49: 43500 | BE49: 0 | BF49: 0 | BG49: 1400 | BH49: 1400 | BI49: 0 | BJ49: 46300 | BK49: NINGUNA | BL49: EPS SURA (ANTES SUSALUD) | BM49: 1 | BN49: 271683 | BO49: 0.04 | BP49: 10900 | BQ49: 0 | BS49: 0 | BU49: 0 | BV49: NINGUNA | BW49: COLMENA | BX49: 1 | BY49: 271683 | BZ49: 0 | CA49: 5 | CB49: CENTRO TRABAJO 24 | CC49: 5711001 | CD49: 0 | CE49: 1 | CF49: COMPENSAR | CG49: 271683 | CH49: 0.04 | CI49: 10900 | CJ49: 271683 | CK49: 0 | CL49: 0 | CM49: 0 | CN49: 0 | CO49: 0 | CP49: 0 | CQ49: 0 | CR49: 0 | CS49: SI
A50: CAUSADO | B50: CC | C50: 1013642764 | D50: GIRALDO MONSALVE JONATHAN ALEXANDER | E50: GIRALDO | F50: MONSALVE | G50: JONATHAN | H50: ALEXANDER | I50: BOGOTA_D.E. | J50: BOGOTA | K50: 1. DEPENDIENTE | L50: NINGUNO | M50: 171 | N50: NO | O50: NO | Q50: NO | S50: NO | U50: NO | V50: NO | W50: NO | X50: NO | Y50: SI | Z50: 46054 | AA50: SI | AB50: NO | AE50: NO | AH50: NO | AK50: NO | AN50: NO | AO50: NO | AR50: 0 | AU50: NO | AV50: 8150490 | AW50: NO | AX50: NO | AY50: PROTECCION | AZ50: 28 | BA50: 7844229 | BB50: 0.16 | BC50: 1255100 | BE50: 0 | BF50: 0 | BG50: 39300 | BH50: 39300 | BI50: 0 | BJ50: 1333700 | BK50: NINGUNA | BL50: EPS SURA (ANTES SUSALUD) | BM50: 28 | BN50: 7844229 | BO50: 0.04 | BP50: 313800 | BQ50: 0 | BS50: 0 | BU50: 0 | BV50: NINGUNA | BW50: COLMENA | BX50: 28 | BY50: 7844229 | BZ50: 0.0696 | CA50: 5 | CB50: CENTRO TRABAJO 24 | CC50: 5711001 | CD50: 546000 | CE50: 28 | CF50: COMPENSAR | CG50: 7844229 | CH50: 0.04 | CI50: 313800 | CJ50: 7844229 | CK50: 0 | CL50: 0 | CM50: 0 | CN50: 0 | CO50: 0 | CP50: 0 | CQ50: 0 | CR50: 0 | CS50: SI
A51: CAUSADO | B51: CC | C51: 1013652019 | D51: VEGA LARA IVAN ENRIQUE | E51: VEGA | F51: LARA | G51: IVAN | H51: ENRIQUE | I51: BOGOTA_D.E. | J51: BOGOTA | K51: 1. DEPENDIENTE | L51: NINGUNO | M51: 180 | N51: NO | O51: NO | Q51: NO | S51: NO | U51: NO | V51: NO | W51: NO | X51: NO | Y51: NO | AA51: SI | AB51: NO | AE51: NO | AH51: NO | AK51: NO | AN51: NO | AO51: NO | AR51: 0 | AU51: NO | AV51: 3637686 | AW51: NO | AX51: NO | AY51: PROTECCION | AZ51: 30 | BA51: 3822877 | BB51: 0.16 | BC51: 611700 | BE51: 0 | BF51: 0 | BG51: 0 | BH51: 0 | BI51: 0 | BJ51: 611700 | BK51: NINGUNA | BL51: FAMISANAR | BM51: 30 | BN51: 3822877 | BO51: 0.04 | BP51: 153000 | BQ51: 0 | BS51: 0 | BU51: 0 | BV51: NINGUNA | BW51: COLMENA | BX51: 30 | BY51: 3822877 | BZ51: 0.0696 | CA51: 5 | CB51: CENTRO TRABAJO 24 | CC51: 5711001 | CD51: 266100 | CE51: 30 | CF51: COMPENSAR | CG51: 3822877 | CH51: 0.04 | CI51: 153000 | CJ51: 3822877 | CK51: 0 | CL51: 0 | CM51: 0 | CN51: 0 | CO51: 0 | CP51: 0 | CQ51: 0 | CR51: 0 | CS51: SI
A52: CAUSADO | B52: CC | C52: 1013658036 | D52: CONTRERAS LOPEZ MARIA CLARA | E52: CONTRERAS | F52: LOPEZ | G52: MARIA | H52: CLARA | I52: BOGOTA_D.E. | J52: BOGOTA | K52: 1. DEPENDIENTE | L52: NINGUNO | M52: 188 | N52: NO | O52: NO | Q52: NO | S52: NO | U52: NO | V52: NO | W52: NO | X52: NO | Y52: SI | Z52: 46054 | AA52: NO | AB52: NO | AE52: NO | AH52: NO | AK52: NO | AN52: NO | AO52: NO | AR52: 0 | AU52: NO | AV52: 2859404 | AW52: NO | AX52: NO | AY52: PROTECCION | AZ52: 30 | BA52: 2859404 | BB52: 0.16 | BC52: 457600 | BE52: 0 | BF52: 0 | BG52: 0 | BH52: 0 | BI52: 0 | BJ52: 457600 | BK52: NINGUNA | BL52: SANITAS | BM52: 30 | BN52: 2859404 | BO52: 0.04 | BP52: 114400 | BQ52: 0 | BS52: 0 | BU52: 0 | BV52: NINGUNA | BW52: COLMENA | BX52: 30 | BY52: 2859404 | BZ52: 0.00522 | CA52: 1 | CB52: CENTRO TRABAJO 24 | CC52: 1711001 | CD52: 15000 | CE52: 30 | CF52: COMPENSAR | CG52: 2859404 | CH52: 0.04 | CI52: 114400 | CJ52: 2859404 | CK52: 0 | CL52: 0 | CM52: 0 | CN52: 0 | CO52: 0 | CP52: 0 | CQ52: 0 | CR52: 0 | CS52: SI
A53: CAUSADO | B53: CC | C53: 1014201150 | D53: MATEUS RUEDA DANIEL RICARDO | E53: MATEUS | F53: RUEDA | G53: DANIEL | H53: RICARDO | I53: BOGOTA_D.E. | J53: BOGOTA | K53: 1. DEPENDIENTE | L53: NINGUNO | M53: 188 | N53: NO | O53: NO | Q53: NO | S53: NO | U53: NO | V53: NO | W53: NO | X53: NO | Y53: NO | AA53: SI | AB53: NO | AE53: NO | AH53: NO | AK53: NO | AN53: NO | AO53: NO | AR53: 0 | AU53: NO | AV53: 8150490 | AW53: NO | AX53: NO | AY53: PORVENIR | AZ53: 30 | BA53: 11436796 | BB53: 0.16 | BC53: 1829900 | BE53: 0 | BF53: 0 | BG53: 57200 | BH53: 57200 | BI53: 0 | BJ53: 1944300 | BK53: NINGUNA | BL53: COMPENSAR | BM53: 30 | BN53: 11436796 | BO53: 0.04 | BP53: 457500 | BQ53: 0 | BS53: 0 | BU53: 0 | BV53: NINGUNA | BW53: COLMENA | BX53: 30 | BY53: 11436796 | BZ53: 0.0696 | CA53: 5 | CB53: CENTRO TRABAJO 24 | CC53: 5711001 | CD53: 796100 | CE53: 30 | CF53: COMPENSAR | CG53: 11436796 | CH53: 0.04 | CI53: 457500 | CJ53: 11436796 | CK53: 0 | CL53: 0 | CM53: 0 | CN53: 0 | CO53: 0 | CP53: 0 | CQ53: 0 | CR53: 0 | CS53: SI
A54: CAUSADO | B54: CC | C54: 1014237269 | D54: MORENO MONTAÑO JENIFER | E54: MORENO | F54: MONTAÑO | G54: JENIFER | I54: BOGOTA_D.E. | J54: BOGOTA | K54: 1. DEPENDIENTE | L54: NINGUNO | M54: 180 | N54: NO | O54: NO | Q54: NO | S54: NO | U54: NO | V54: NO | W54: NO | X54: NO | Y54: SI | Z54: 46054 | AA54: NO | AB54: NO | AE54: NO | AH54: NO | AK54: NO | AN54: NO | AO54: NO | AR54: 0 | AU54: NO | AV54: 3660341 | AW54: NO | AX54: NO | AY54: PROTECCION | AZ54: 30 | BA54: 3660341 | BB54: 0.16 | BC54: 585700 | BE54: 0 | BF54: 0 | BG54: 0 | BH54: 0 | BI54: 0 | BJ54: 585700 | BK54: NINGUNA | BL54: SANITAS | BM54: 30 | BN54: 3660341 | BO54: 0.04 | BP54: 146500 | BQ54: 0 | BS54: 0 | BU54: 0 | BV54: NINGUNA | BW54: COLMENA | BX54: 30 | BY54: 3660341 | BZ54: 0.0696 | CA54: 5 | CB54: CENTRO TRABAJO 24 | CC54: 5711001 | CD54: 254800 | CE54: 30 | CF54: COMPENSAR | CG54: 3660341 | CH54: 0.04 | CI54: 146500 | CJ54: 3660341 | CK54: 0 | CL54: 0 | CM54: 0 | CN54: 0 | CO54: 0 | CP54: 0 | CQ54: 0 | CR54: 0 | CS54: SI
A55: CAUSADO | B55: CC | C55: 1014246981 | D55: SAENZ VARGAS FABIO MAURICIO | E55: SAENZ | F55: VARGAS | G55: FABIO | H55: MAURICIO | I55: BOGOTA_D.E. | J55: BOGOTA | K55: 1. DEPENDIENTE | L55: NINGUNO | M55: 188 | N55: NO | O55: NO | Q55: NO | S55: NO | U55: NO | V55: NO | W55: NO | X55: NO | Y55: SI | Z55: 46054 | AA55: NO | AB55: NO | AE55: NO | AH55: NO | AK55: NO | AN55: NO | AO55: NO | AR55: 0 | AU55: NO | AV55: 5676577 | AW55: NO | AX55: NO | AY55: PORVENIR | AZ55: 30 | BA55: 5676577 | BB55: 0.16 | BC55: 908300 | BE55: 0 | BF55: 0 | BG55: 0 | BH55: 0 | BI55: 0 | BJ55: 908300 | BK55: NINGUNA | BL55: COMPENSAR | BM55: 30 | BN55: 5676577 | BO55: 0.04 | BP55: 227100 | BQ55: 0 | BS55: 0 | BU55: 0 | BV55: NINGUNA | BW55: COLMENA | BX55: 30 | BY55: 5676577 | BZ55: 0.0696 | CA55: 5 | CB55: CENTRO TRABAJO 24 | CC55: 5711001 | CD55: 395100 | CE55: 30 | CF55: COMPENSAR | CG55: 5676577 | CH55: 0.04 | CI55: 227100 | CJ55: 5676577 | CK55: 0 | CL55: 0 | CM55: 0 | CN55: 0 | CO55: 0 | CP55: 0 | CQ55: 0 | CR55: 0 | CS55: SI
A56: CAUSADO | B56: CC | C56: 1014292676 | D56: QUIROGA CASTIBLANCO ANDRES EDUARDO | E56: QUIROGA | F56: CASTIBLANCO | G56: ANDRES | H56: EDUARDO | I56: BOGOTA_D.E. | J56: BOGOTA | K56: 1. DEPENDIENTE | L56: NINGUNO | M56: 188 | N56: NO | O56: NO | Q56: NO | S56: NO | U56: NO | V56: NO | W56: NO | X56: NO | Y56: SI | Z56: 46054 | AA56: NO | AB56: NO | AE56: NO | AH56: NO | AK56: NO | AN56: NO | AO56: NO | AR56: 0 | AU56: NO | AV56: 4798033 | AW56: NO | AX56: NO | AY56: PORVENIR | AZ56: 30 | BA56: 4798033 | BB56: 0.16 | BC56: 767700 | BE56: 0 | BF56: 0 | BG56: 0 | BH56: 0 | BI56: 0 | BJ56: 767700 | BK56: NINGUNA | BL56: COMPENSAR | BM56: 30 | BN56: 4798033 | BO56: 0.04 | BP56: 192000 | BQ56: 0 | BS56: 0 | BU56: 0 | BV56: NINGUNA | BW56: COLMENA | BX56: 30 | BY56: 4798033 | BZ56: 0.00522 | CA56: 1 | CB56: CENTRO TRABAJO 24 | CC56: 1711001 | CD56: 25100 | CE56: 30 | CF56: COMPENSAR | CG56: 4798033 | CH56: 0.04 | CI56: 192000 | CJ56: 4798033 | CK56: 0 | CL56: 0 | CM56: 0 | CN56: 0 | CO56: 0 | CP56: 0 | CQ56: 0 | CR56: 0 | CS56: SI
A57: CAUSADO | B57: CC | C57: 1015436314 | D57: VELASQUEZ SANTIAGO NICOLAS | E57: VELASQUEZ | F57: SANTIAGO | G57: NICOLAS | I57: BOGOTA_D.E. | J57: BOGOTA | K57: 1. DEPENDIENTE | L57: NINGUNO | M57: 180 | N57: NO | O57: NO | Q57: NO | S57: NO | U57: NO | V57: NO | W57: NO | X57: NO | Y57: SI | Z57: 46054 | AA57: NO | AB57: NO | AE57: NO | AH57: NO | AK57: NO | AN57: NO | AO57: NO | AR57: 0 | AU57: NO | AV57: 5209465 | AW57: NO | AX57: NO | AY57: PORVENIR | AZ57: 30 | BA57: 5209465 | BB57: 0.16 | BC57: 833600 | BE57: 0 | BF57: 0 | BG57: 0 | BH57: 0 | BI57: 0 | BJ57: 833600 | BK57: NINGUNA | BL57: SANITAS | BM57: 30 | BN57: 5209465 | BO57: 0.04 | BP57: 208400 | BQ57: 0 | BS57: 0 | BU57: 0 | BV57: NINGUNA | BW57: COLMENA | BX57: 30 | BY57: 5209465 | BZ57: 0.00522 | CA57: 1 | CB57: CENTRO TRABAJO 24 | CC57: 1711001 | CD57: 27200 | CE57: 30 | CF57: COMPENSAR | CG57: 5209465 | CH57: 0.04 | CI57: 208400 | CJ57: 5209465 | CK57: 0 | CL57: 0 | CM57: 0 | CN57: 0 | CO57: 0 | CP57: 0 | CQ57: 0 | CR57: 0 | CS57: SI
A58: CAUSADO | B58: CC | C58: 1016003023 | D58: TORRES SONZA ANDRES | E58: TORRES | F58: SONZA | G58: ANDRES | I58: BOGOTA_D.E. | J58: BOGOTA | K58: 1. DEPENDIENTE | L58: NINGUNO | M58: 206 | N58: NO | O58: NO | Q58: NO | S58: NO | U58: NO | V58: NO | W58: NO | X58: NO | Y58: NO | AA58: SI | AB58: NO | AE58: NO | AH58: NO | AK58: NO | AN58: NO | AO58: NO | AR58: 0 | AU58: NO | AV58: 1785595 | AW58: NO | AX58: NO | AY58: PORVENIR | AZ58: 30 | BA58: 2056817 | BB58: 0.16 | BC58: 329100 | BE58: 0 | BF58: 0 | BG58: 0 | BH58: 0 | BI58: 0 | BJ58: 329100 | BK58: NINGUNA | BL58: SALUD TOTAL | BM58: 30 | BN58: 2056817 | BO58: 0.04 | BP58: 82300 | BQ58: 0 | BS58: 0 | BU58: 0 | BV58: NINGUNA | BW58: COLMENA | BX58: 30 | BY58: 2056817 | BZ58: 0.0696 | CA58: 5 | CB58: CENTRO TRABAJO 24 | CC58: 5711001 | CD58: 143200 | CE58: 30 | CF58: COMPENSAR | CG58: 2056817 | CH58: 0.04 | CI58: 82300 | CJ58: 2056817 | CK58: 0 | CL58: 0 | CM58: 0 | CN58: 0 | CO58: 0 | CP58: 0 | CQ58: 0 | CR58: 0 | CS58: SI
A59: CAUSADO | B59: CC | C59: 1016008194 | D59: MORENO QUINTANA IVAN ERNESTO | E59: MORENO | F59: QUINTANA | G59: IVAN | H59: ERNESTO | I59: BOGOTA_D.E. | J59: BOGOTA | K59: 1. DEPENDIENTE | L59: NINGUNO | M59: 238 | N59: NO | O59: NO | Q59: NO | S59: NO | U59: NO | V59: NO | W59: NO | X59: NO | Y59: NO | AA59: SI | AB59: NO | AE59: NO | AH59: NO | AK59: NO | AN59: NO | AO59: NO | AR59: 0 | AU59: NO | AV59: 2074908 | AW59: NO | AX59: NO | AY59: PORVENIR | AZ59: 30 | BA59: 3179561 | BB59: 0.16 | BC59: 508800 | BE59: 0 | BF59: 0 | BG59: 0 | BH59: 0 | BI59: 0 | BJ59: 508800 | BK59: NINGUNA | BL59: NUEVA E.P.S. | BM59: 30 | BN59: 3179561 | BO59: 0.04 | BP59: 127200 | BQ59: 0 | BS59: 0 | BU59: 0 | BV59: NINGUNA | BW59: COLMENA | BX59: 30 | BY59: 3179561 | BZ59: 0.0696 | CA59: 5 | CB59: CENTRO TRABAJO 24 | CC59: 5711001 | CD59: 221300 | CE59: 30 | CF59: COMPENSAR | CG59: 3179561 | CH59: 0.04 | CI59: 127200 | CJ59: 3179561 | CK59: 0 | CL59: 0 | CM59: 0 | CN59: 0 | CO59: 0 | CP59: 0 | CQ59: 0 | CR59: 0 | CS59: SI
A60: CAUSADO | B60: CC | C60: 1018404223 | D60: CASTILLO DUARTE DEIBY HERNAN | E60: CASTILLO | F60: DUARTE | G60: DEIBY | H60: HERNAN | I60: BOGOTA_D.E. | J60: BOGOTA | K60: 1. DEPENDIENTE | L60: NINGUNO | M60: 9 | N60: NO | O60: NO | Q60: Todos los sistemas (ARL, AFP, CCF, EPS) | R60: 46080 | S60: NO | U60: NO | V60: NO | W60: NO | X60: NO | Y60: NO | AA60: NO | AB60: NO | AE60: NO | AH60: NO | AK60: NO | AN60: NO | AO60: NO | AR60: 0 | AU60: NO | AV60: 2223339 | AW60: NO | AX60: NO | AY60: PROTECCION | AZ60: 4 | BA60: 296446 | BB60: 0.16 | BC60: 47500 | BE60: 0 | BF60: 0 | BG60: 0 | BH60: 0 | BI60: 0 | BJ60: 47500 | BK60: NINGUNA | BL60: NUEVA E.P.S. | BM60: 4 | BN60: 296446 | BO60: 0.04 | BP60: 11900 | BQ60: 0 | BS60: 0 | BU60: 0 | BV60: NINGUNA | BW60: COLMENA | BX60: 4 | BY60: 296446 | BZ60: 0.0696 | CA60: 5 | CB60: CENTRO TRABAJO 24 | CC60: 5711001 | CD60: 20700 | CE60: 4 | CF60: COMPENSAR | CG60: 296446 | CH60: 0.04 | CI60: 11900 | CJ60: 296446 | CK60: 0 | CL60: 0 | CM60: 0 | CN60: 0 | CO60: 0 | CP60: 0 | CQ60: 0 | CR60: 0 | CS60: SI
A61: CAUSADO | B61: CC | C61: 1019021939 | D61: RAMIREZ RIVADENEIRA EDUARDO ENRIQUE | E61: RAMIREZ | F61: RIVADENEIRA | G61: EDUARDO | H61: ENRIQUE | I61: BOGOTA_D.E. | J61: BOGOTA | K61: 1. DEPENDIENTE | L61: NINGUNO | M61: 180 | N61: NO | O61: NO | Q61: NO | S61: NO | U61: NO | V61: NO | W61: NO | X61: NO | Y61: NO | AA61: NO | AB61: NO | AE61: NO | AH61: NO | AK61: NO | AN61: NO | AO61: NO | AR61: 0 | AU61: NO | AV61: 11650406 | AW61: NO | AX61: SI | AY61: PORVENIR | AZ61: 30 | BA61: 11650406 | BB61: 0.16 | BC61: 1864100 | BE61: 0 | BF61: 0 | BG61: 58300 | BH61: 58300 | BI61: 0 | BJ61: 1980700 | BK61: NINGUNA | BL61: EPS SURA (ANTES SUSALUD) | BM61: 30 | BN61: 11650406 | BO61: 0.125 | BP61: 466100 | BQ61: 0 | BS61: 0 | BU61: 0 | BV61: NINGUNA | BW61: COLMENA | BX61: 30 | BY61: 11650406 | BZ61: 0.0696 | CA61: 5 | CB61: CENTRO TRABAJO 24 | CC61: 5711001 | CD61: 810900 | CE61: 30 | CF61: COMPENSAR | CG61: 10485365 | CH61: 0.04 | CI61: 419500 | CJ61: 10485365 | CK61: 0 | CL61: 0 | CM61: 0 | CN61: 0 | CO61: 0 | CP61: 0 | CQ61: 0 | CR61: 0 | CS61: SI
A62: CAUSADO | B62: CC | C62: 1019068610 | D62: QUIJANO ALARCON JOHAN STIVEN | E62: QUIJANO | F62: ALARCON | G62: JOHAN | H62: STIVEN | I62: BOGOTA_D.E. | J62: BOGOTA | K62: 1. DEPENDIENTE | L62: NINGUNO | M62: 207 | N62: NO | O62: NO | Q62: NO | S62: NO | U62: NO | V62: NO | W62: NO | X62: NO | Y62: NO | AA62: SI | AB62: NO | AE62: NO | AH62: NO | AK62: NO | AN62: NO | AO62: NO | AR62: 0 | AU62: NO | AV62: 2620709 | AW62: NO | AX62: NO | AY62: PORVENIR | AZ62: 30 | BA62: 2911072 | BB62: 0.16 | BC62: 465800 | BE62: 0 | BF62: 0 | BG62: 0 | BH62: 0 | BI62: 0 | BJ62: 465800 | BK62: NINGUNA | BL62: FAMISANAR | BM62: 30 | BN62: 2911072 | BO62: 0.04 | BP62: 116500 | BQ62: 0 | BS62: 0 | BU62: 0 | BV62: NINGUNA | BW62: COLMENA | BX62: 30 | BY62: 2911072 | BZ62: 0.0696 | CA62: 5 | CB62: CENTRO TRABAJO 24 | CC62: 5711001 | CD62: 202700 | CE62: 30 | CF62: COMPENSAR | CG62: 2911072 | CH62: 0.04 | CI62: 116500 | CJ62: 2911072 | CK62: 0 | CL62: 0 | CM62: 0 | CN62: 0 | CO62: 0 | CP62: 0 | CQ62: 0 | CR62: 0 | CS62: SI
A63: CAUSADO | B63: CC | C63: 1019088253 | D63: ANTOLINEZ GARCIA CAMILO ANDRES | E63: ANTOLINEZ | F63: GARCIA | G63: CAMILO | H63: ANDRES | I63: LA_GUAJIRA | J63: RIOHACHA | K63: 1. DEPENDIENTE | L63: NINGUNO | M63: 180 | N63: NO | O63: NO | Q63: NO | S63: NO | U63: NO | V63: NO | W63: NO | X63: NO | Y63: NO | AA63: NO | AB63: NO | AE63: NO | AH63: NO | AK63: NO | AN63: NO | AO63: NO | AR63: 0 | AU63: NO | AV63: 5676577 | AW63: NO | AX63: NO | AY63: PROTECCION | AZ63: 30 | BA63: 5676577 | BB63: 0.16 | BC63: 908300 | BE63: 0 | BF63: 0 | BG63: 0 | BH63: 0 | BI63: 0 | BJ63: 908300 | BK63: NINGUNA | BL63: COMPENSAR | BM63: 30 | BN63: 5676577 | BO63: 0.04 | BP63: 227100 | BQ63: 0 | BS63: 0 | BU63: 0 | BV63: NINGUNA | BW63: COLMENA | BX63: 30 | BY63: 5676577 | BZ63: 0.0696 | CA63: 5 | CB63: CENTRO TRABAJO 30 | CC63: 5711001 | CD63: 395100 | CE63: 30 | CF63: COMFAMILIAR GUAJIRA | CG63: 5676577 | CH63: 0.04 | CI63: 227100 | CJ63: 5676577 | CK63: 0 | CL63: 0 | CM63: 0 | CN63: 0 | CO63: 0 | CP63: 0 | CQ63: 0 | CR63: 0 | CS63: SI
A64: CAUSADO | B64: CC | C64: 1020712729 | D64: OLMOS ROMERO NELSON BERNARDO | E64: OLMOS | F64: ROMERO | G64: NELSON | H64: BERNARDO | I64: BOGOTA_D.E. | J64: BOGOTA | K64: 1. DEPENDIENTE | L64: NINGUNO | M64: 180 | N64: NO | O64: NO | Q64: NO | S64: NO | U64: NO | V64: NO | W64: NO | X64: NO | Y64: NO | AA64: NO | AB64: NO | AE64: NO | AH64: NO | AK64: NO | AN64: NO | AO64: NO | AR64: 0 | AU64: NO | AV64: 11650406 | AW64: NO | AX64: SI | AY64: PORVENIR | AZ64: 30 | BA64: 11650406 | BB64: 0.16 | BC64: 1864100 | BE64: 0 | BF64: 0 | BG64: 58300 | BH64: 58300 | BI64: 0 | BJ64: 1980700 | BK64: NINGUNA | BL64: COMPENSAR | BM64: 30 | BN64: 11650406 | BO64: 0.125 | BP64: 1456400 | BQ64: 0 | BS64: 0 | BU64: 0 | BV64: NINGUNA | BW64: COLMENA | BX64: 30 | BY64: 11650406 | BZ64: 0.0696 | CA64: 5 | CB64: CENTRO TRABAJO 24 | CC64: 5711001 | CD64: 810900 | CE64: 30 | CF64: COMPENSAR | CG64: 11650406 | CH64: 0.04 | CI64: 466100 | CJ64: 11650406 | CK64: 0.02 | CL64: 233100 | CM64: 0.03 | CN64: 349600 | CO64: 0 | CP64: 0 | CQ64: 0 | CR64: 0 | CS64: SI
A65: CAUSADO | B65: CC | C65: 1020761014 | D65: OSPINA VILLAMIL ALEJANDRA | E65: OSPINA | F65: VILLAMIL | G65: ALEJANDRA | I65: BOGOTA_D.E. | J65: BOGOTA | K65: 1. DEPENDIENTE | L65: NINGUNO | M65: 0 | N65: NO | O65: NO | Q65: NO | S65: NO | U65: NO | V65: NO | W65: NO | X65: NO | Y65: NO | AA65: NO | AB65: NO | AE65: NO | AH65: NO | AK65: LICENCIA REMUNERADA | AL65: 46069 | AM65: 46069 | AN65: NO | AO65: NO | AR65: 0 | AU65: NO | AV65: 5209465 | AW65: NO | AX65: NO | AY65: COLFONDOS | AZ65: 1 | BA65: 173649 | BB65: 0.16 | BC65: 27800 | BE65: 0 | BF65: 0 | BG65: 0 | BH65: 0 | BI65: 0 | BJ65: 27800 | BK65: NINGUNA | BL65: COMPENSAR | BM65: 1 | BN65: 173649 | BO65: 0.04 | BP65: 7000 | BQ65: 0 | BS65: 0 | BU65: 0 | BV65: NINGUNA | BW65: COLMENA | BX65: 1 | BY65: 173649 | BZ65: 0 | CA65: 5 | CB65: CENTRO TRABAJO 24 | CC65: 5711001 | CD65: 0 | CE65: 1 | CF65: COMPENSAR | CG65: 173649 | CH65: 0.04 | CI65: 7000 | CJ65: 173649 | CK65: 0 | CL65: 0 | CM65: 0 | CN65: 0 | CO65: 0 | CP65: 0 | CQ65: 0 | CR65: 0 | CS65: SI
A66: CAUSADO | B66: CC | C66: 1020761014 | D66: OSPINA VILLAMIL ALEJANDRA | E66: OSPINA | F66: VILLAMIL | G66: ALEJANDRA | I66: BOGOTA_D.E. | J66: BOGOTA | K66: 1. DEPENDIENTE | L66: NINGUNO | M66: 171 | N66: NO | O66: NO | Q66: NO | S66: NO | U66: NO | V66: NO | W66: NO | X66: NO | Y66: NO | AA66: NO | AB66: NO | AE66: NO | AH66: NO | AK66: NO | AN66: NO | AO66: NO | AR66: 0 | AU66: NO | AV66: 5209465 | AW66: NO | AX66: NO | AY66: COLFONDOS | AZ66: 29 | BA66: 5035817 | BB66: 0.16 | BC66: 805800 | BE66: 0 | BF66: 0 | BG66: 0 | BH66: 0 | BI66: 0 | BJ66: 805800 | BK66: NINGUNA | BL66: COMPENSAR | BM66: 29 | BN66: 5035817 | BO66: 0.04 | BP66: 201500 | BQ66: 0 | BS66: 0 | BU66: 0 | BV66: NINGUNA | BW66: COLMENA | BX66: 29 | BY66: 5035817 | BZ66: 0.0696 | CA66: 5 | CB66: CENTRO TRABAJO 24 | CC66: 5711001 | CD66: 350500 | CE66: 29 | CF66: COMPENSAR | CG66: 5035817 | CH66: 0.04 | CI66: 201500 | CJ66: 5035817 | CK66: 0 | CL66: 0 | CM66: 0 | CN66: 0 | CO66: 0 | CP66: 0 | CQ66: 0 | CR66: 0 | CS66: SI
A67: CAUSADO | B67: CC | C67: 1020844204 | D67: MONTOYA VILLAMIZAR MARIA CAMILA | E67: MONTOYA | F67: VILLAMIZAR | G67: MARIA | H67: CAMILA | I67: BOGOTA_D.E. | J67: BOGOTA | K67: 1. DEPENDIENTE | L67: NINGUNO | M67: 188 | N67: NO | O67: NO | Q67: NO | S67: NO | U67: NO | V67: NO | W67: NO | X67: NO | Y67: SI | Z67: 46054 | AA67: NO | AB67: NO | AE67: NO | AH67: NO | AK67: NO | AN67: NO | AO67: NO | AR67: 0 | AU67: NO | AV67: 4024292 | AW67: NO | AX67: NO | AY67: SKANDIA | AZ67: 30 | BA67: 7086256 | BB67: 0.16 | BC67: 1133900 | BE67: 0 | BF67: 0 | BG67: 35500 | BH67: 35500 | BI67: 0 | BJ67: 1204900 | BK67: NINGUNA | BL67: SANITAS | BM67: 30 | BN67: 7086256 | BO67: 0.04 | BP67: 283500 | BQ67: 0 | BS67: 0 | BU67: 0 | BV67: NINGUNA | BW67: COLMENA | BX67: 30 | BY67: 7086256 | BZ67: 0.00522 | CA67: 1 | CB67: CENTRO TRABAJO 24 | CC67: 1711001 | CD67: 37000 | CE67: 30 | CF67: COMPENSAR | CG67: 4024292 | CH67: 0.04 | CI67: 161000 | CJ67: 4024292 | CK67: 0 | CL67: 0 | CM67: 0 | CN67: 0 | CO67: 0 | CP67: 0 | CQ67: 0 | CR67: 0 | CS67: SI
A68: CAUSADO | B68: CC | C68: 1022344711 | D68: MALDONADO MARTINEZ EDWARD ALEXANDER | E68: MALDONADO | F68: MARTINEZ | G68: EDWARD | H68: ALEXANDER | I68: BOGOTA_D.E. | J68: BOGOTA | K68: 1. DEPENDIENTE | L68: NINGUNO | M68: 0 | N68: NO | O68: NO | Q68: NO | S68: NO | U68: NO | V68: NO | W68: NO | X68: NO | Y68: NO | AA68: NO | AB68: NO | AE68: NO | AH68: NO | AK68: LICENCIA REMUNERADA | AL68: 46069 | AM68: 46069 | AN68: NO | AO68: NO | AR68: 0 | AU68: NO | AV68: 2223339 | AW68: NO | AX68: NO | AY68: PROTECCION | AZ68: 1 | BA68: 74112 | BB68: 0.16 | BC68: 11900 | BE68: 0 | BF68: 0 | BG68: 0 | BH68: 0 | BI68: 0 | BJ68: 11900 | BK68: NINGUNA | BL68: SALUD TOTAL | BM68: 1 | BN68: 74112 | BO68: 0.04 | BP68: 3000 | BQ68: 0 | BS68: 0 | BU68: 0 | BV68: NINGUNA | BW68: COLMENA | BX68: 1 | BY68: 74112 | BZ68: 0 | CA68: 5 | CB68: CENTRO TRABAJO 24 | CC68: 5711001 | CD68: 0 | CE68: 1 | CF68: COMPENSAR | CG68: 74112 | CH68: 0.04 | CI68: 3000 | CJ68: 74112 | CK68: 0 | CL68: 0 | CM68: 0 | CN68: 0 | CO68: 0 | CP68: 0 | CQ68: 0 | CR68: 0 | CS68: SI
A69: CAUSADO | B69: CC | C69: 1022344711 | D69: MALDONADO MARTINEZ EDWARD ALEXANDER | E69: MALDONADO | F69: MARTINEZ | G69: EDWARD | H69: ALEXANDER | I69: BOGOTA_D.E. | J69: BOGOTA | K69: 1. DEPENDIENTE | L69: NINGUNO | M69: 0 | N69: NO | O69: NO | Q69: NO | S69: NO | U69: NO | V69: NO | W69: NO | X69: NO | Y69: NO | AA69: NO | AB69: NO | AE69: INCAPACIDAD GENERAL | AF69: 46077 | AG69: 46078 | AH69: NO | AK69: NO | AN69: NO | AO69: NO | AR69: 0 | AU69: NO | AV69: 2223339 | AW69: NO | AX69: NO | AY69: PROTECCION | AZ69: 2 | BA69: 217110 | BB69: 0.16 | BC69: 34800 | BE69: 0 | BF69: 0 | BG69: 0 | BH69: 0 | BI69: 0 | BJ69: 34800 | BK69: NINGUNA | BL69: SALUD TOTAL | BM69: 2 | BN69: 217110 | BO69: 0.04 | BP69: 8700 | BQ69: 0 | BS69: 0 | BU69: 0 | BV69: NINGUNA | BW69: COLMENA | BX69: 2 | BY69: 217110 | BZ69: 0 | CA69: 5 | CB69: CENTRO TRABAJO 24 | CC69: 5711001 | CD69: 0 | CE69: 2 | CF69: COMPENSAR | CG69: 0 | CH69: 0 | CI69: 0 | CJ69: 0 | CK69: 0 | CL69: 0 | CM69: 0 | CN69: 0 | CO69: 0 | CP69: 0 | CQ69: 0 | CR69: 0 | CS69: SI
A70: CAUSADO | B70: CC | C70: 1022344711 | D70: MALDONADO MARTINEZ EDWARD ALEXANDER | E70: MALDONADO | F70: MARTINEZ | G70: EDWARD | H70: ALEXANDER | I70: BOGOTA_D.E. | J70: BOGOTA | K70: 1. DEPENDIENTE | L70: NINGUNO | M70: 199 | N70: NO | O70: NO | Q70: NO | S70: Todos los sistemas (ARL, AFP, CCF, EPS) | T70: 46081 | U70: NO | V70: NO | W70: NO | X70: NO | Y70: NO | AA70: SI | AB70: NO | AE70: NO | AH70: NO | AK70: NO | AN70: NO | AO70: NO | AR70: 0 | AU70: NO | AV70: 2223339 | AW70: NO | AX70: NO | AY70: PROTECCION | AZ70: 27 | BA70: 3088757 | BB70: 0.16 | BC70: 494300 | BE70: 0 | BF70: 0 | BG70: 0 | BH70: 0 | BI70: 0 | BJ70: 494300 | BK70: NINGUNA | BL70: SALUD TOTAL | BM70: 27 | BN70: 3088757 | BO70: 0.04 | BP70: 123600 | BQ70: 0 | BS70: 0 | BU70: 0 | BV70: NINGUNA | BW70: COLMENA | BX70: 27 | BY70: 3088757 | BZ70: 0.0696 | CA70: 5 | CB70: CENTRO TRABAJO 24 | CC70: 5711001 | CD70: 215000 | CE70: 27 | CF70: COMPENSAR | CG70: 3490022 | CH70: 0.04 | CI70: 139700 | CJ70: 3490022 | CK70: 0 | CL70: 0 | CM70: 0 | CN70: 0 | CO70: 0 | CP70: 0 | CQ70: 0 | CR70: 0 | CS70: SI
A71: CAUSADO | B71: CC | C71: 1022407941 | D71: VEGA SANCHEZ DANILO ESTEBAN | E71: VEGA | F71: SANCHEZ | G71: DANILO | H71: ESTEBAN | I71: BOGOTA_D.E. | J71: BOGOTA | K71: 1. DEPENDIENTE | L71: NINGUNO | M71: 0 | N71: NO | O71: NO | Q71: NO | S71: NO | U71: NO | V71: NO | W71: NO | X71: NO | Y71: NO | AA71: NO | AB71: NO | AE71: NO | AH71: NO | AK71: LICENCIA REMUNERADA | AL71: 46069 | AM71: 46069 | AN71: NO | AO71: NO | AR71: 0 | AU71: NO | AV71: 4024292 | AW71: NO | AX71: NO | AY71: PORVENIR | AZ71: 1 | BA71: 134144 | BB71: 0.16 | BC71: 21500 | BE71: 0 | BF71: 0 | BG71: 0 | BH71: 0 | BI71: 0 | BJ71: 21500 | BK71: NINGUNA | BL71: SANITAS | BM71: 1 | BN71: 134144 | BO71: 0.04 | BP71: 5400 | BQ71: 0 | BS71: 0 | BU71: 0 | BV71: NINGUNA | BW71: COLMENA | BX71: 1 | BY71: 134144 | BZ71: 0 | CA71: 5 | CB71: CENTRO TRABAJO 24 | CC71: 5711001 | CD71: 0 | CE71: 1 | CF71: COMPENSAR | CG71: 134144 | CH71: 0.04 | CI71: 5400 | CJ71: 134144 | CK71: 0 | CL71: 0 | CM71: 0 | CN71: 0 | CO71: 0 | CP71: 0 | CQ71: 0 | CR71: 0 | CS71: SI
A72: CAUSADO | B72: CC | C72: 1022407941 | D72: VEGA SANCHEZ DANILO ESTEBAN | E72: VEGA | F72: SANCHEZ | G72: DANILO | H72: ESTEBAN | I72: BOGOTA_D.E. | J72: BOGOTA | K72: 1. DEPENDIENTE | L72: NINGUNO | M72: 171 | N72: NO | O72: NO | Q72: NO | S72: NO | U72: NO | V72: NO | W72: NO | X72: NO | Y72: SI | Z72: 46054 | AA72: NO | AB72: NO | AE72: NO | AH72: NO | AK72: NO | AN72: NO | AO72: NO | AR72: 0 | AU72: NO | AV72: 4024292 | AW72: NO | AX72: NO | AY72: PORVENIR | AZ72: 29 | BA72: 3890149 | BB72: 0.16 | BC72: 622500 | BE72: 0 | BF72: 0 | BG72: 0 | BH72: 0 | BI72: 0 | BJ72: 622500 | BK72: NINGUNA | BL72: SANITAS | BM72: 29 | BN72: 3890149 | BO72: 0.04 | BP72: 155700 | BQ72: 0 | BS72: 0 | BU72: 0 | BV72: NINGUNA | BW72: COLMENA | BX72: 29 | BY72: 3890149 | BZ72: 0.0696 | CA72: 5 | CB72: CENTRO TRABAJO 24 | CC72: 5711001 | CD72: 270800 | CE72: 29 | CF72: COMPENSAR | CG72: 3890149 | CH72: 0.04 | CI72: 155700 | CJ72: 3890149 | CK72: 0 | CL72: 0 | CM72: 0 | CN72: 0 | CO72: 0 | CP72: 0 | CQ72: 0 | CR72: 0 | CS72: SI
A73: CAUSADO | B73: CC | C73: 1022934783 | D73: OVALLE LINARES RAMIRO | E73: OVALLE | F73: LINARES | G73: RAMIRO | I73: BOGOTA_D.E. | J73: BOGOTA | K73: 1. DEPENDIENTE | L73: NINGUNO | M73: 188 | N73: NO | O73: NO | Q73: NO | S73: NO | U73: NO | V73: NO | W73: NO | X73: NO | Y73: SI | Z73: 46054 | AA73: NO | AB73: NO | AE73: NO | AH73: NO | AK73: NO | AN73: NO | AO73: NO | AR73: 0 | AU73: NO | AV73: 9740088 | AW73: NO | AX73: SI | AY73: COLFONDOS | AZ73: 30 | BA73: 9740088 | BB73: 0.16 | BC73: 1558500 | BE73: 0 | BF73: 0 | BG73: 48800 | BH73: 48800 | BI73: 0 | BJ73: 1656100 | BK73: NINGUNA | BL73: COMPENSAR | BM73: 30 | BN73: 9740088 | BO73: 0.04 | BP73: 389700 | BQ73: 0 | BS73: 0 | BU73: 0 | BV73: NINGUNA | BW73: COLMENA | BX73: 30 | BY73: 9740088 | BZ73: 0.0696 | CA73: 5 | CB73: CENTRO TRABAJO 24 | CC73: 5711001 | CD73: 678000 | CE73: 30 | CF73: COMPENSAR | CG73: 9740088 | CH73: 0.04 | CI73: 389700 | CJ73: 9740088 | CK73: 0 | CL73: 0 | CM73: 0 | CN73: 0 | CO73: 0 | CP73: 0 | CQ73: 0 | CR73: 0 | CS73: SI
A74: CAUSADO | B74: CC | C74: 1023882608 | D74: MARTINEZ NEIRA SANDRA MILENA | E74: MARTINEZ | F74: NEIRA | G74: SANDRA | H74: MILENA | I74: BOGOTA_D.E. | J74: BOGOTA | K74: 1. DEPENDIENTE | L74: NINGUNO | M74: 180 | N74: NO | O74: NO | Q74: NO | S74: NO | U74: NO | V74: NO | W74: NO | X74: NO | Y74: SI | Z74: 46054 | AA74: NO | AB74: NO | AE74: NO | AH74: NO | AK74: NO | AN74: NO | AO74: NO | AR74: 0 | AU74: NO | AV74: 8812118 | AW74: NO | AX74: NO | AY74: COLFONDOS | AZ74: 30 | BA74: 8812118 | BB74: 0.16 | BC74: 1410000 | BE74: 0 | BF74: 0 | BG74: 44100 | BH74: 44100 | BI74: 0 | BJ74: 1498200 | BK74: NINGUNA | BL74: COMPENSAR | BM74: 30 | BN74: 8812118 | BO74: 0.04 | BP74: 352500 | BQ74: 0 | BS74: 0 | BU74: 0 | BV74: NINGUNA | BW74: COLMENA | BX74: 30 | BY74: 8812118 | BZ74: 0.0696 | CA74: 5 | CB74: CENTRO TRABAJO 24 | CC74: 5711001 | CD74: 613400 | CE74: 30 | CF74: COMPENSAR | CG74: 8812118 | CH74: 0.04 | CI74: 352500 | CJ74: 8812118 | CK74: 0 | CL74: 0 | CM74: 0 | CN74: 0 | CO74: 0 | CP74: 0 | CQ74: 0 | CR74: 0 | CS74: SI
A75: CAUSADO | B75: CC | C75: 1023927871 | D75: BECERRA MELGAREJO KAREN JULIETH | E75: BECERRA | F75: MELGAREJO | G75: KAREN | H75: JULIETH | I75: BOGOTA_D.E. | J75: BOGOTA | K75: 1. DEPENDIENTE | L75: NINGUNO | M75: 0 | N75: NO | O75: NO | Q75: NO | S75: NO | U75: NO | V75: NO | W75: NO | X75: NO | Y75: NO | AA75: NO | AB75: NO | AE75: NO | AH75: NO | AK75: LICENCIA REMUNERADA | AL75: 46054 | AM75: 46054 | AN75: NO | AO75: NO | AR75: 0 | AU75: NO | AV75: 3639331 | AW75: NO | AX75: NO | AY75: PROTECCION | AZ75: 1 | BA75: 121312 | BB75: 0.16 | BC75: 19500 | BE75: 0 | BF75: 0 | BG75: 0 | BH75: 0 | BI75: 0 | BJ75: 19500 | BK75: NINGUNA | BL75: SALUD TOTAL | BM75: 1 | BN75: 121312 | BO75: 0.04 | BP75: 4900 | BQ75: 0 | BS75: 0 | BU75: 0 | BV75: NINGUNA | BW75: COLMENA | BX75: 1 | BY75: 121312 | BZ75: 0 | CA75: 5 | CB75: CENTRO TRABAJO 24 | CC75: 5711001 | CD75: 0 | CE75: 1 | CF75: COMPENSAR | CG75: 121312 | CH75: 0.04 | CI75: 4900 | CJ75: 121312 | CK75: 0 | CL75: 0 | CM75: 0 | CN75: 0 | CO75: 0 | CP75: 0 | CQ75: 0 | CR75: 0 | CS75: SI
A76: CAUSADO | B76: CC | C76: 1023927871 | D76: BECERRA MELGAREJO KAREN JULIETH | E76: BECERRA | F76: MELGAREJO | G76: KAREN | H76: JULIETH | I76: BOGOTA_D.E. | J76: BOGOTA | K76: 1. DEPENDIENTE | L76: NINGUNO | M76: 180 | N76: NO | O76: NO | Q76: NO | S76: NO | U76: NO | V76: NO | W76: NO | X76: NO | Y76: SI | Z76: 46054 | AA76: SI | AB76: NO | AE76: NO | AH76: NO | AK76: NO | AN76: NO | AO76: NO | AR76: 0 | AU76: NO | AV76: 3639331 | AW76: NO | AX76: NO | AY76: PROTECCION | AZ76: 29 | BA76: 3710740 | BB76: 0.16 | BC76: 593800 | BE76: 0 | BF76: 0 | BG76: 0 | BH76: 0 | BI76: 0 | BJ76: 593800 | BK76: NINGUNA | BL76: SALUD TOTAL | BM76: 29 | BN76: 3710740 | BO76: 0.04 | BP76: 148500 | BQ76: 0 | BS76: 0 | BU76: 0 | BV76: NINGUNA | BW76: COLMENA | BX76: 29 | BY76: 3710740 | BZ76: 0.0696 | CA76: 5 | CB76: CENTRO TRABAJO 24 | CC76: 5711001 | CD76: 258300 | CE76: 29 | CF76: COMPENSAR | CG76: 3710740 | CH76: 0.04 | CI76: 148500 | CJ76: 3710740 | CK76: 0 | CL76: 0 | CM76: 0 | CN76: 0 | CO76: 0 | CP76: 0 | CQ76: 0 | CR76: 0 | CS76: SI
A77: CAUSADO | B77: CC | C77: 1023965099 | D77: SACHICA D'ALEMAN KELLY DANIELA | E77: SACHICA | F77: D'ALEMAN | G77: KELLY | H77: DANIELA | I77: BOGOTA_D.E. | J77: BOGOTA | K77: 1. DEPENDIENTE | L77: NINGUNO | M77: 188 | N77: NO | O77: NO | Q77: NO | S77: NO | U77: NO | V77: NO | W77: NO | X77: NO | Y77: NO | AA77: NO | AB77: NO | AE77: NO | AH77: NO | AK77: NO | AN77: NO | AO77: NO | AR77: 0 | AU77: NO | AV77: 1750905 | AW77: NO | AX77: NO | AY77: PROTECCION | AZ77: 30 | BA77: 1750905 | BB77: 0.16 | BC77: 280200 | BE77: 0 | BF77: 0 | BG77: 0 | BH77: 0 | BI77: 0 | BJ77: 280200 | BK77: NINGUNA | BL77: SANITAS | BM77: 30 | BN77: 1750905 | BO77: 0.04 | BP77: 70100 | BQ77: 0 | BS77: 0 | BU77: 0 | BV77: NINGUNA | BW77: COLMENA | BX77: 30 | BY77: 1750905 | BZ77: 0.00522 | CA77: 1 | CB77: CENTRO TRABAJO 24 | CC77: 1711001 | CD77: 9200 | CE77: 30 | CF77: COMPENSAR | CG77: 1750905 | CH77: 0.04 | CI77: 70100 | CJ77: 1750905 | CK77: 0 | CL77: 0 | CM77: 0 | CN77: 0 | CO77: 0 | CP77: 0 | CQ77: 0 | CR77: 0 | CS77: SI
A78: CAUSADO | B78: CC | C78: 1024573844 | D78: BUSTOS OVIEDO OSCAR EDUARDO | E78: BUSTOS | F78: OVIEDO | G78: OSCAR | H78: EDUARDO | I78: BOGOTA_D.E. | J78: BOGOTA | K78: 1. DEPENDIENTE | L78: NINGUNO | M78: 0 | N78: NO | O78: NO | Q78: NO | S78: NO | U78: NO | V78: NO | W78: NO | X78: NO | Y78: NO | AA78: NO | AB78: NO | AE78: NO | AH78: NO | AK78: LICENCIA REMUNERADA | AL78: 46056 | AM78: 46056 | AN78: NO | AO78: NO | AR78: 0 | AU78: NO | AV78: 2074908 | AW78: NO | AX78: NO | AY78: COLFONDOS | AZ78: 1 | BA78: 69164 | BB78: 0.16 | BC78: 11100 | BE78: 0 | BF78: 0 | BG78: 0 | BH78: 0 | BI78: 0 | BJ78: 11100 | BK78: NINGUNA | BL78: FAMISANAR | BM78: 1 | BN78: 69164 | BO78: 0.04 | BP78: 2800 | BQ78: 0 | BS78: 0 | BU78: 0 | BV78: NINGUNA | BW78: COLMENA | BX78: 1 | BY78: 69164 | BZ78: 0 | CA78: 5 | CB78: CENTRO TRABAJO 24 | CC78: 5711001 | CD78: 0 | CE78: 1 | CF78: COMPENSAR | CG78: 69164 | CH78: 0.04 | CI78: 2800 | CJ78: 69164 | CK78: 0 | CL78: 0 | CM78: 0 | CN78: 0 | CO78: 0 | CP78: 0 | CQ78: 0 | CR78: 0 | CS78: SI
A79: CAUSADO | B79: CC | C79: 1024573844 | D79: BUSTOS OVIEDO OSCAR EDUARDO | E79: BUSTOS | F79: OVIEDO | G79: OSCAR | H79: EDUARDO | I79: BOGOTA_D.E. | J79: BOGOTA | K79: 1. DEPENDIENTE | L79: NINGUNO | M79: 0 | N79: NO | O79: NO | Q79: NO | S79: NO | U79: NO | V79: NO | W79: NO | X79: NO | Y79: NO | AA79: NO | AB79: NO | AE79: INCAPACIDAD GENERAL | AF79: 46057 | AG79: 46058 | AH79: NO | AK79: NO | AN79: NO | AO79: NO | AR79: 0 | AU79: NO | AV79: 2074908 | AW79: NO | AX79: NO | AY79: COLFONDOS | AZ79: 2 | BA79: 200102 | BB79: 0.16 | BC79: 32100 | BE79: 0 | BF79: 0 | BG79: 0 | BH79: 0 | BI79: 0 | BJ79: 32100 | BK79: NINGUNA | BL79: FAMISANAR | BM79: 2 | BN79: 200102 | BO79: 0.04 | BP79: 8100 | BQ79: 0 | BS79: 0 | BU79: 0 | BV79: NINGUNA | BW79: COLMENA | BX79: 2 | BY79: 200102 | BZ79: 0 | CA79: 5 | CB79: CENTRO TRABAJO 24 | CC79: 5711001 | CD79: 0 | CE79: 2 | CF79: COMPENSAR | CG79: 0 | CH79: 0 | CI79: 0 | CJ79: 0 | CK79: 0 | CL79: 0 | CM79: 0 | CN79: 0 | CO79: 0 | CP79: 0 | CQ79: 0 | CR79: 0 | CS79: SI
A80: CAUSADO | B80: CC | C80: 1024573844 | D80: BUSTOS OVIEDO OSCAR EDUARDO | E80: BUSTOS | F80: OVIEDO | G80: OSCAR | H80: EDUARDO | I80: BOGOTA_D.E. | J80: BOGOTA | K80: 1. DEPENDIENTE | L80: NINGUNO | M80: 188 | N80: NO | O80: NO | Q80: NO | S80: NO | U80: NO | V80: NO | W80: NO | X80: NO | Y80: NO | AA80: SI | AB80: NO | AE80: NO | AH80: NO | AK80: NO | AN80: NO | AO80: NO | AR80: 0 | AU80: NO | AV80: 2074908 | AW80: NO | AX80: NO | AY80: COLFONDOS | AZ80: 27 | BA80: 2700948 | BB80: 0.16 | BC80: 432200 | BE80: 0 | BF80: 0 | BG80: 0 | BH80: 0 | BI80: 0 | BJ80: 432200 | BK80: NINGUNA | BL80: FAMISANAR | BM80: 27 | BN80: 2700948 | BO80: 0.04 | BP80: 108100 | BQ80: 0 | BS80: 0 | BU80: 0 | BV80: NINGUNA | BW80: COLMENA | BX80: 27 | BY80: 2700948 | BZ80: 0.0696 | CA80: 5 | CB80: CENTRO TRABAJO 24 | CC80: 5711001 | CD80: 188000 | CE80: 27 | CF80: COMPENSAR | CG80: 2700948 | CH80: 0.04 | CI80: 108100 | CJ80: 2700948 | CK80: 0 | CL80: 0 | CM80: 0 | CN80: 0 | CO80: 0 | CP80: 0 | CQ80: 0 | CR80: 0 | CS80: SI
A81: CAUSADO | B81: CC | C81: 1024588921 | D81: MARTINEZ JARAMILLO ANGIE XIOMARA | E81: MARTINEZ | F81: JARAMILLO | G81: ANGIE | H81: XIOMARA | I81: BOGOTA_D.E. | J81: BOGOTA | K81: 1. DEPENDIENTE | L81: NINGUNO | M81: 0 | N81: NO | O81: NO | Q81: NO | S81: NO | U81: NO | V81: NO | W81: NO | X81: NO | Y81: NO | AA81: NO | AB81: LICENCIA NO REMUNERADA | AC81: 46054 | AD81: 46056 | AE81: NO | AH81: NO | AK81: NO | AN81: NO | AO81: NO | AR81: 0 | AU81: NO | AV81: 1785595 | AW81: NO | AX81: NO | AY81: PORVENIR | AZ81: 3 | BA81: 178560 | BB81: 0.16 | BC81: 28600 | BE81: 0 | BF81: 0 | BG81: 0 | BH81: 0 | BI81: 0 | BJ81: 28600 | BK81: NINGUNA | BL81: SANITAS | BM81: 3 | BN81: 178560 | BO81: 0 | BP81: 0 | BQ81: 0 | BS81: 0 | BU81: 0 | BV81: NINGUNA | BW81: COLMENA | BX81: 3 | BY81: 178560 | BZ81: 0 | CA81: 5 | CB81: CENTRO TRABAJO 24 | CC81: 5711001 | CD81: 0 | CE81: 3 | CF81: COMPENSAR | CG81: 0 | CH81: 0 | CI81: 0 | CJ81: 0 | CK81: 0 | CL81: 0 | CM81: 0 | CN81: 0 | CO81: 0 | CP81: 0 | CQ81: 0 | CR81: 0 | CS81: SI
A82: CAUSADO | B82: CC | C82: 1024588921 | D82: MARTINEZ JARAMILLO ANGIE XIOMARA | E82: MARTINEZ | F82: JARAMILLO | G82: ANGIE | H82: XIOMARA | I82: BOGOTA_D.E. | J82: BOGOTA | K82: 1. DEPENDIENTE | L82: NINGUNO | M82: 0 | N82: NO | O82: NO | Q82: NO | S82: NO | U82: NO | V82: NO | W82: NO | X82: NO | Y82: NO | AA82: NO | AB82: NO | AE82: INCAPACIDAD GENERAL | AF82: 46055 | AG82: 46056 | AH82: NO | AK82: NO | AN82: NO | AO82: NO | AR82: 0 | AU82: NO | AV82: 1785595 | AW82: NO | AX82: NO | AY82: PORVENIR | AZ82: 2 | BA82: 119040 | BB82: 0.16 | BC82: 19100 | BE82: 0 | BF82: 0 | BG82: 0 | BH82: 0 | BI82: 0 | BJ82: 19100 | BK82: NINGUNA | BL82: SANITAS | BM82: 2 | BN82: 119040 | BO82: 0.04 | BP82: 4800 | BQ82: 0 | BS82: 0 | BU82: 0 | BV82: NINGUNA | BW82: COLMENA | BX82: 2 | BY82: 119040 | BZ82: 0 | CA82: 5 | CB82: CENTRO TRABAJO 24 | CC82: 5711001 | CD82: 0 | CE82: 2 | CF82: COMPENSAR | CG82: 0 | CH82: 0 | CI82: 0 | CJ82: 0 | CK82: 0 | CL82: 0 | CM82: 0 | CN82: 0 | CO82: 0 | CP82: 0 | CQ82: 0 | CR82: 0 | CS82: SI
A83: CAUSADO | B83: CC | C83: 1024588921 | D83: MARTINEZ JARAMILLO ANGIE XIOMARA | E83: MARTINEZ | F83: JARAMILLO | G83: ANGIE | H83: XIOMARA | I83: BOGOTA_D.E. | J83: BOGOTA | K83: 1. DEPENDIENTE | L83: NINGUNO | M83: 0 | N83: NO | O83: NO | Q83: NO | S83: NO | U83: NO | V83: NO | W83: NO | X83: NO | Y83: NO | AA83: NO | AB83: LICENCIA NO REMUNERADA | AC83: 46069 | AD83: 46075 | AE83: NO | AH83: NO | AK83: NO | AN83: NO | AO83: NO | AR83: 0 | AU83: NO | AV83: 1785595 | AW83: NO | AX83: NO | AY83: PORVENIR | AZ83: 7 | BA83: 416639 | BB83: 0.16 | BC83: 66700 | BE83: 0 | BF83: 0 | BG83: 0 | BH83: 0 | BI83: 0 | BJ83: 66700 | BK83: NINGUNA | BL83: SANITAS | BM83: 7 | BN83: 416639 | BO83: 0 | BP83: 0 | BQ83: 0 | BS83: 0 | BU83: 0 | BV83: NINGUNA | BW83: COLMENA | BX83: 7 | BY83: 416639 | BZ83: 0 | CA83: 5 | CB83: CENTRO TRABAJO 24 | CC83: 5711001 | CD83: 0 | CE83: 7 | CF83: COMPENSAR | CG83: 0 | CH83: 0 | CI83: 0 | CJ83: 0 | CK83: 0 | CL83: 0 | CM83: 0 | CN83: 0 | CO83: 0 | CP83: 0 | CQ83: 0 | CR83: 0 | CS83: SI
A84: CAUSADO | B84: CC | C84: 1024588921 | D84: MARTINEZ JARAMILLO ANGIE XIOMARA | E84: MARTINEZ | F84: JARAMILLO | G84: ANGIE | H84: XIOMARA | I84: BOGOTA_D.E. | J84: BOGOTA | K84: 1. DEPENDIENTE | L84: NINGUNO | M84: 107 | N84: NO | O84: NO | Q84: NO | S84: NO | U84: NO | V84: NO | W84: NO | X84: NO | Y84: NO | AA84: SI | AB84: NO | AE84: NO | AH84: NO | AK84: NO | AN84: NO | AO84: NO | AR84: 0 | AU84: NO | AV84: 1785595 | AW84: NO | AX84: NO | AY84: PORVENIR | AZ84: 18 | BA84: 1257763 | BB84: 0.16 | BC84: 201300 | BE84: 0 | BF84: 0 | BG84: 0 | BH84: 0 | BI84: 0 | BJ84: 201300 | BK84: NINGUNA | BL84: SANITAS | BM84: 18 | BN84: 1257763 | BO84: 0.04 | BP84: 50400 | BQ84: 0 | BS84: 0 | BU84: 0 | BV84: NINGUNA | BW84: COLMENA | BX84: 18 | BY84: 1257763 | BZ84: 0.0696 | CA84: 5 | CB84: CENTRO TRABAJO 24 | CC84: 5711001 | CD84: 87600 | CE84: 18 | CF84: COMPENSAR | CG84: 1257763 | CH84: 0.04 | CI84: 50400 | CJ84: 1257763 | CK84: 0 | CL84: 0 | CM84: 0 | CN84: 0 | CO84: 0 | CP84: 0 | CQ84: 0 | CR84: 0 | CS84: SI
A85: CAUSADO | B85: CC | C85: 1024599648 | D85: SANCHEZ SOSA DUVAN DAVID | E85: SANCHEZ | F85: SOSA | G85: DUVAN | H85: DAVID | I85: BOGOTA_D.E. | J85: BOGOTA | K85: 1. DEPENDIENTE | L85: NINGUNO | M85: 74 | N85: NO | O85: NO | Q85: Todos los sistemas (ARL, AFP, CCF, EPS) | R85: 46071 | S85: NO | U85: NO | V85: NO | W85: NO | X85: NO | Y85: NO | AA85: SI | AB85: NO | AE85: NO | AH85: NO | AK85: NO | AN85: NO | AO85: NO | AR85: 0 | AU85: NO | AV85: 2223339 | AW85: NO | AX85: NO | AY85: PROTECCION | AZ85: 13 | BA85: 988712 | BB85: 0.16 | BC85: 158200 | BE85: 0 | BF85: 0 | BG85: 0 | BH85: 0 | BI85: 0 | BJ85: 158200 | BK85: NINGUNA | BL85: SANITAS | BM85: 13 | BN85: 988712 | BO85: 0.04 | BP85: 39600 | BQ85: 0 | BS85: 0 | BU85: 0 | BV85: NINGUNA | BW85: COLMENA | BX85: 13 | BY85: 988712 | BZ85: 0.0696 | CA85: 5 | CB85: CENTRO TRABAJO 24 | CC85: 5711001 | CD85: 68900 | CE85: 13 | CF85: COMPENSAR | CG85: 988712 | CH85: 0.04 | CI85: 39600 | CJ85: 988712 | CK85: 0 | CL85: 0 | CM85: 0 | CN85: 0 | CO85: 0 | CP85: 0 | CQ85: 0 | CR85: 0 | CS85: SI
A86: CAUSADO | B86: CC | C86: 1026131564 | D86: PELAEZ TORRES NELSON ALCIDES | E86: PELAEZ | F86: TORRES | G86: NELSON | H86: ALCIDES | I86: BOGOTA_D.E. | J86: BOGOTA | K86: 1. DEPENDIENTE | L86: NINGUNO | M86: 0 | N86: NO | O86: NO | Q86: NO | S86: NO | U86: NO | V86: NO | W86: NO | X86: NO | Y86: NO | AA86: NO | AB86: LICENCIA NO REMUNERADA | AC86: 46069 | AD86: 46070 | AE86: NO | AH86: NO | AK86: NO | AN86: NO | AO86: NO | AR86: 0 | AU86: NO | AV86: 2223339 | AW86: NO | AX86: NO | AY86: COLPENSIONES | AZ86: 2 | BA86: 148223 | BB86: 0.16 | BC86: 23800 | BE86: 0 | BF86: 0 | BG86: 0 | BH86: 0 | BI86: 0 | BJ86: 23800 | BK86: NINGUNA | BL86: EPS SURA (ANTES SUSALUD) | BM86: 2 | BN86: 148223 | BO86: 0 | BP86: 0 | BQ86: 0 | BS86: 0 | BU86: 0 | BV86: NINGUNA | BW86: COLMENA | BX86: 2 | BY86: 148223 | BZ86: 0 | CA86: 5 | CB86: CENTRO TRABAJO 24 | CC86: 5711001 | CD86: 0 | CE86: 2 | CF86: COMPENSAR | CG86: 0 | CH86: 0 | CI86: 0 | CJ86: 0 | CK86: 0 | CL86: 0 | CM86: 0 | CN86: 0 | CO86: 0 | CP86: 0 | CQ86: 0 | CR86: 0 | CS86: SI
A87: CAUSADO | B87: CC | C87: 1026131564 | D87: PELAEZ TORRES NELSON ALCIDES | E87: PELAEZ | F87: TORRES | G87: NELSON | H87: ALCIDES | I87: BOGOTA_D.E. | J87: BOGOTA | K87: 1. DEPENDIENTE | L87: NINGUNO | M87: 157 | N87: NO | O87: NO | Q87: NO | S87: Todos los sistemas (ARL, AFP, CCF, EPS) | T87: 46074 | U87: NO | V87: NO | W87: NO | X87: NO | Y87: NO | AA87: SI | AB87: NO | AE87: NO | AH87: NO | AK87: NO | AN87: NO | AO87: NO | AR87: 0 | AU87: NO | AV87: 2223339 | AW87: NO | AX87: NO | AY87: COLPENSIONES | AZ87: 19 | BA87: 2820641 | BB87: 0.16 | BC87: 451400 | BE87: 0 | BF87: 0 | BG87: 0 | BH87: 0 | BI87: 0 | BJ87: 451400 | BK87: NINGUNA | BL87: EPS SURA (ANTES SUSALUD) | BM87: 19 | BN87: 2820641 | BO87: 0.04 | BP87: 112900 | BQ87: 0 | BS87: 0 | BU87: 0 | BV87: NINGUNA | BW87: COLMENA | BX87: 19 | BY87: 2820641 | BZ87: 0.0696 | CA87: 5 | CB87: CENTRO TRABAJO 24 | CC87: 5711001 | CD87: 196400 | CE87: 19 | CF87: COMPENSAR | CG87: 3254353 | CH87: 0.04 | CI87: 130200 | CJ87: 3254353 | CK87: 0 | CL87: 0 | CM87: 0 | CN87: 0 | CO87: 0 | CP87: 0 | CQ87: 0 | CR87: 0 | CS87: SI
A88: CAUSADO | B88: CC | C88: 1026565492 | D88: AMAYA GARCIA DAVID FABIAN | E88: AMAYA | F88: GARCIA | G88: DAVID | H88: FABIAN | I88: BOGOTA_D.E. | J88: BOGOTA | K88: 1. DEPENDIENTE | L88: NINGUNO | M88: 0 | N88: NO | O88: NO | Q88: NO | S88: NO | U88: NO | V88: NO | W88: NO | X88: NO | Y88: NO | AA88: NO | AB88: LICENCIA NO REMUNERADA | AC88: 46054 | AD88: 46054 | AE88: NO | AH88: NO | AK88: NO | AN88: NO | AO88: NO | AR88: 0 | AU88: NO | AV88: 1956650 | AW88: NO | AX88: NO | AY88: PROTECCION | AZ88: 1 | BA88: 65222 | BB88: 0.16 | BC88: 10500 | BE88: 0 | BF88: 0 | BG88: 0 | BH88: 0 | BI88: 0 | BJ88: 10500 | BK88: NINGUNA | BL88: NUEVA E.P.S. | BM88: 1 | BN88: 65222 | BO88: 0 | BP88: 0 | BQ88: 0 | BS88: 0 | BU88: 0 | BV88: NINGUNA | BW88: COLMENA | BX88: 1 | BY88: 65222 | BZ88: 0 | CA88: 5 | CB88: CENTRO TRABAJO 24 | CC88: 5711001 | CD88: 0 | CE88: 1 | CF88: COMPENSAR | CG88: 0 | CH88: 0 | CI88: 0 | CJ88: 0 | CK88: 0 | CL88: 0 | CM88: 0 | CN88: 0 | CO88: 0 | CP88: 0 | CQ88: 0 | CR88: 0 | CS88: SI
A89: CAUSADO | B89: CC | C89: 1026565492 | D89: AMAYA GARCIA DAVID FABIAN | E89: AMAYA | F89: GARCIA | G89: DAVID | H89: FABIAN | I89: BOGOTA_D.E. | J89: BOGOTA | K89: 1. DEPENDIENTE | L89: NINGUNO | M89: 208 | N89: NO | O89: NO | Q89: NO | S89: NO | U89: NO | V89: NO | W89: NO | X89: NO | Y89: NO | AA89: SI | AB89: NO | AE89: NO | AH89: NO | AK89: NO | AN89: NO | AO89: NO | AR89: 0 | AU89: NO | AV89: 1956650 | AW89: NO | AX89: NO | AY89: PROTECCION | AZ89: 29 | BA89: 2207398 | BB89: 0.16 | BC89: 353200 | BE89: 0 | BF89: 0 | BG89: 0 | BH89: 0 | BI89: 0 | BJ89: 353200 | BK89: NINGUNA | BL89: NUEVA E.P.S. | BM89: 29 | BN89: 2207398 | BO89: 0.04 | BP89: 88300 | BQ89: 0 | BS89: 0 | BU89: 0 | BV89: NINGUNA | BW89: COLMENA | BX89: 29 | BY89: 2207398 | BZ89: 0.0696 | CA89: 5 | CB89: CENTRO TRABAJO 24 | CC89: 5711001 | CD89: 153700 | CE89: 29 | CF89: COMPENSAR | CG89: 2207398 | CH89: 0.04 | CI89: 88300 | CJ89: 2207398 | CK89: 0 | CL89: 0 | CM89: 0 | CN89: 0 | CO89: 0 | CP89: 0 | CQ89: 0 | CR89: 0 | CS89: SI
A90: CAUSADO | B90: CC | C90: 1030559818 | D90: SANCHEZ SUAREZ ROBERT JOSE | E90: SANCHEZ | F90: SUAREZ | G90: ROBERT | H90: JOSE | I90: BOGOTA_D.E. | J90: BOGOTA | K90: 1. DEPENDIENTE | L90: NINGUNO | M90: 90 | N90: NO | O90: NO | Q90: Todos los sistemas (ARL, AFP, CCF, EPS) | R90: 46069 | S90: NO | U90: NO | V90: NO | W90: NO | X90: NO | Y90: NO | AA90: NO | AB90: NO | AE90: NO | AH90: NO | AK90: NO | AN90: NO | AO90: NO | AR90: 0 | AU90: NO | AV90: 3534205 | AW90: NO | AX90: NO | AY90: PORVENIR | AZ90: 15 | BA90: 1767103 | BB90: 0.16 | BC90: 282800 | BE90: 0 | BF90: 0 | BG90: 0 | BH90: 0 | BI90: 0 | BJ90: 282800 | BK90: NINGUNA | BL90: EPS SURA (ANTES SUSALUD) | BM90: 15 | BN90: 1767103 | BO90: 0.04 | BP90: 70700 | BQ90: 0 | BS90: 0 | BU90: 0 | BV90: NINGUNA | BW90: COLMENA | BX90: 15 | BY90: 1767103 | BZ90: 0.0696 | CA90: 5 | CB90: CENTRO TRABAJO 24 | CC90: 5711001 | CD90: 123000 | CE90: 15 | CF90: COMPENSAR | CG90: 1767103 | CH90: 0.04 | CI90: 70700 | CJ90: 1767103 | CK90: 0 | CL90: 0 | CM90: 0 | CN90: 0 | CO90: 0 | CP90: 0 | CQ90: 0 | CR90: 0 | CS90: SI
A91: CAUSADO | B91: CC | C91: 1030591724 | D91: MARTIN RIOS LUIS ANDRES | E91: MARTIN | F91: RIOS | G91: LUIS | H91: ANDRES | I91: BOGOTA_D.E. | J91: BOGOTA | K91: 1. DEPENDIENTE | L91: NINGUNO | M91: 126 | N91: NO | O91: NO | Q91: Todos los sistemas (ARL, AFP, CCF, EPS) | R91: 46063 | S91: NO | U91: NO | V91: NO | W91: NO | X91: NO | Y91: NO | AA91: NO | AB91: NO | AE91: NO | AH91: NO | AK91: NO | AN91: NO | AO91: NO | AR91: 0 | AU91: NO | AV91: 5149192 | AW91: NO | AX91: NO | AY91: COLPENSIONES | AZ91: 21 | BA91: 3604435 | BB91: 0.16 | BC91: 576800 | BE91: 0 | BF91: 0 | BG91: 0 | BH91: 0 | BI91: 0 | BJ91: 576800 | BK91: NINGUNA | BL91: COMPENSAR | BM91: 21 | BN91: 3604435 | BO91: 0.04 | BP91: 144200 | BQ91: 0 | BS91: 0 | BU91: 0 | BV91: NINGUNA | BW91: COLMENA | BX91: 21 | BY91: 3604435 | BZ91: 0.0696 | CA91: 5 | CB91: CENTRO TRABAJO 24 | CC91: 5711001 | CD91: 250900 | CE91: 21 | CF91: COMPENSAR | CG91: 3604435 | CH91: 0.04 | CI91: 144200 | CJ91: 3604435 | CK91: 0 | CL91: 0 | CM91: 0 | CN91: 0 | CO91: 0 | CP91: 0 | CQ91: 0 | CR91: 0 | CS91: SI
A92: CAUSADO | B92: CC | C92: 1030601355 | D92: RIVERA GOMEZ ANGIE LORENA | E92: RIVERA | F92: GOMEZ | G92: ANGIE | H92: LORENA | I92: BOGOTA_D.E. | J92: BOGOTA | K92: 1. DEPENDIENTE | L92: NINGUNO | M92: 180 | N92: NO | O92: NO | Q92: NO | S92: NO | U92: NO | V92: NO | W92: NO | X92: NO | Y92: NO | AA92: NO | AB92: NO | AE92: NO | AH92: NO | AK92: NO | AN92: NO | AO92: NO | AR92: 0 | AU92: NO | AV92: 5209465 | AW92: NO | AX92: NO | AY92: COLFONDOS | AZ92: 30 | BA92: 6819901 | BB92: 0.16 | BC92: 1091200 | BE92: 0 | BF92: 0 | BG92: 0 | BH92: 0 | BI92: 0 | BJ92: 1091200 | BK92: NINGUNA | BL92: SANITAS | BM92: 30 | BN92: 6819901 | BO92: 0.04 | BP92: 272800 | BQ92: 0 | BS92: 0 | BU92: 0 | BV92: NINGUNA | BW92: COLMENA | BX92: 30 | BY92: 6819901 | BZ92: 0.0696 | CA92: 5 | CB92: CENTRO TRABAJO 24 | CC92: 5711001 | CD92: 474700 | CE92: 30 | CF92: COMPENSAR | CG92: 5209465 | CH92: 0.04 | CI92: 208400 | CJ92: 5209465 | CK92: 0 | CL92: 0 | CM92: 0 | CN92: 0 | CO92: 0 | CP92: 0 | CQ92: 0 | CR92: 0 | CS92: SI
A93: CAUSADO | B93: CC | C93: 1030605434 | D93: LOPEZ HURTADO CARLOS ALEXANDER | E93: LOPEZ | F93: HURTADO | G93: CARLOS | H93: ALEXANDER | I93: BOGOTA_D.E. | J93: BOGOTA | K93: 1. DEPENDIENTE | L93: NINGUNO | M93: 188 | N93: NO | O93: NO | Q93: NO | S93: NO | U93: NO | V93: NO | W93: NO | X93: NO | Y93: SI | Z93: 46054 | AA93: NO | AB93: NO | AE93: NO | AH93: NO | AK93: NO | AN93: NO | AO93: NO | AR93: 0 | AU93: NO | AV93: 2859408 | AW93: NO | AX93: NO | AY93: PORVENIR | AZ93: 30 | BA93: 2859408 | BB93: 0.16 | BC93: 457600 | BE93: 0 | BF93: 0 | BG93: 0 | BH93: 0 | BI93: 0 | BJ93: 457600 | BK93: NINGUNA | BL93: SALUD TOTAL | BM93: 30 | BN93: 2859408 | BO93: 0.04 | BP93: 114400 | BQ93: 0 | BS93: 0 | BU93: 0 | BV93: NINGUNA | BW93: COLMENA | BX93: 30 | BY93: 2859408 | BZ93: 0.00522 | CA93: 1 | CB93: CENTRO TRABAJO 24 | CC93: 1711001 | CD93: 15000 | CE93: 30 | CF93: COMPENSAR | CG93: 2859408 | CH93: 0.04 | CI93: 114400 | CJ93: 2859408 | CK93: 0 | CL93: 0 | CM93: 0 | CN93: 0 | CO93: 0 | CP93: 0 | CQ93: 0 | CR93: 0 | CS93: SI
A94: CAUSADO | B94: CC | C94: 1030624661 | D94: TAPIA LEAL HARINSON LEONARDO | E94: TAPIA | F94: LEAL | G94: HARINSON | H94: LEONARDO | I94: BOGOTA_D.E. | J94: BOGOTA | K94: 1. DEPENDIENTE | L94: NINGUNO | M94: 0 | N94: NO | O94: NO | Q94: NO | S94: NO | U94: NO | V94: NO | W94: NO | X94: NO | Y94: NO | AA94: NO | AB94: NO | AE94: INCAPACIDAD GENERAL | AF94: 46069 | AG94: 46070 | AH94: NO | AK94: NO | AN94: NO | AO94: NO | AR94: 0 | AU94: NO | AV94: 1750905 | AW94: NO | AX94: NO | AY94: COLPENSIONES | AZ94: 2 | BA94: 128936 | BB94: 0.16 | BC94: 20700 | BE94: 0 | BF94: 0 | BG94: 0 | BH94: 0 | BI94: 0 | BJ94: 20700 | BK94: NINGUNA | BL94: CAPITAL SALUD | BM94: 2 | BN94: 128936 | BO94: 0.04 | BP94: 5200 | BQ94: 0 | BS94: 0 | BU94: 0 | BV94: NINGUNA | BW94: COLMENA | BX94: 2 | BY94: 128936 | BZ94: 0 | CA94: 5 | CB94: CENTRO TRABAJO 24 | CC94: 5711001 | CD94: 0 | CE94: 2 | CF94: COMPENSAR | CG94: 0 | CH94: 0 | CI94: 0 | CJ94: 0 | CK94: 0 | CL94: 0 | CM94: 0 | CN94: 0 | CO94: 0 | CP94: 0 | CQ94: 0 | CR94: 0 | CS94: SI
A95: CAUSADO | B95: CC | C95: 1030624661 | D95: TAPIA LEAL HARINSON LEONARDO | E95: TAPIA | F95: LEAL | G95: HARINSON | H95: LEONARDO | I95: BOGOTA_D.E. | J95: BOGOTA | K95: 1. DEPENDIENTE | L95: NINGUNO | M95: 177 | N95: NO | O95: NO | Q95: NO | S95: NO | U95: NO | V95: NO | W95: NO | X95: NO | Y95: NO | AA95: SI | AB95: NO | AE95: NO | AH95: NO | AK95: NO | AN95: NO | AO95: NO | AR95: 0 | AU95: NO | AV95: 1750905 | AW95: NO | AX95: NO | AY95: COLPENSIONES | AZ95: 28 | BA95: 1878311 | BB95: 0.16 | BC95: 300600 | BE95: 0 | BF95: 0 | BG95: 0 | BH95: 0 | BI95: 0 | BJ95: 300600 | BK95: NINGUNA | BL95: CAPITAL SALUD | BM95: 28 | BN95: 1878311 | BO95: 0.04 | BP95: 75200 | BQ95: 0 | BS95: 0 | BU95: 0 | BV95: NINGUNA | BW95: COLMENA | BX95: 28 | BY95: 1878311 | BZ95: 0.0696 | CA95: 5 | CB95: CENTRO TRABAJO 24 | CC95: 5711001 | CD95: 130800 | CE95: 28 | CF95: COMPENSAR | CG95: 1878311 | CH95: 0.04 | CI95: 75200 | CJ95: 1878311 | CK95: 0 | CL95: 0 | CM95: 0 | CN95: 0 | CO95: 0 | CP95: 0 | CQ95: 0 | CR95: 0 | CS95: SI
A96: CAUSADO | B96: CC | C96: 1032392951 | D96: PALACIOS ORJUELA JENNY ALEJANDRA | E96: PALACIOS | F96: ORJUELA | G96: JENNY | H96: ALEJANDRA | I96: BOGOTA_D.E. | J96: BOGOTA | K96: 1. DEPENDIENTE | L96: NINGUNO | M96: 180 | N96: NO | O96: NO | Q96: NO | S96: NO | U96: NO | V96: NO | W96: NO | X96: NO | Y96: NO | AA96: NO | AB96: NO | AE96: NO | AH96: NO | AK96: NO | AN96: NO | AO96: NO | AR96: 0 | AU96: NO | AV96: 4891516 | AW96: NO | AX96: NO | AY96: COLFONDOS | AZ96: 30 | BA96: 4891516 | BB96: 0.16 | BC96: 782700 | BE96: 0 | BF96: 0 | BG96: 0 | BH96: 0 | BI96: 0 | BJ96: 782700 | BK96: NINGUNA | BL96: SANITAS | BM96: 30 | BN96: 4891516 | BO96: 0.04 | BP96: 195700 | BQ96: 0 | BS96: 0 | BU96: 0 | BV96: NINGUNA | BW96: COLMENA | BX96: 30 | BY96: 4891516 | BZ96: 0.0696 | CA96: 5 | CB96: CENTRO TRABAJO 24 | CC96: 5711001 | CD96: 340500 | CE96: 30 | CF96: COMPENSAR | CG96: 4891516 | CH96: 0.04 | CI96: 195700 | CJ96: 4891516 | CK96: 0 | CL96: 0 | CM96: 0 | CN96: 0 | CO96: 0 | CP96: 0 | CQ96: 0 | CR96: 0 | CS96: SI
A97: CAUSADO | B97: CC | C97: 1032402045 | D97: OYUELA RODRIGUEZ JUAN PABLO | E97: OYUELA | F97: RODRIGUEZ | G97: JUAN | H97: PABLO | I97: BOGOTA_D.E. | J97: BOGOTA | K97: 1. DEPENDIENTE | L97: NINGUNO | M97: 0 | N97: NO | O97: NO | Q97: NO | S97: NO | U97: NO | V97: NO | W97: NO | X97: NO | Y97: NO | AA97: NO | AB97: NO | AE97: NO | AH97: NO | AK97: LICENCIA REMUNERADA | AL97: 46054 | AM97: 46054 | AN97: NO | AO97: NO | AR97: 0 | AU97: NO | AV97: 5209465 | AW97: NO | AX97: NO | AY97: COLPENSIONES | AZ97: 1 | BA97: 173649 | BB97: 0.16 | BC97: 27800 | BE97: 0 | BF97: 0 | BG97: 0 | BH97: 0 | BI97: 0 | BJ97: 27800 | BK97: NINGUNA | BL97: SALUD TOTAL | BM97: 1 | BN97: 173649 | BO97: 0.04 | BP97: 7000 | BQ97: 0 | BS97: 0 | BU97: 0 | BV97: NINGUNA | BW97: COLMENA | BX97: 1 | BY97: 173649 | BZ97: 0 | CA97: 5 | CB97: CENTRO TRABAJO 24 | CC97: 5711001 | CD97: 0 | CE97: 1 | CF97: COMPENSAR | CG97: 173649 | CH97: 0.04 | CI97: 7000 | CJ97: 173649 | CK97: 0 | CL97: 0 | CM97: 0 | CN97: 0 | CO97: 0 | CP97: 0 | CQ97: 0 | CR97: 0 | CS97: SI
A98: CAUSADO | B98: CC | C98: 1032402045 | D98: OYUELA RODRIGUEZ JUAN PABLO | E98: OYUELA | F98: RODRIGUEZ | G98: JUAN | H98: PABLO | I98: BOGOTA_D.E. | J98: BOGOTA | K98: 1. DEPENDIENTE | L98: NINGUNO | M98: 180 | N98: NO | O98: NO | Q98: NO | S98: NO | U98: NO | V98: NO | W98: NO | X98: NO | Y98: NO | AA98: NO | AB98: NO | AE98: NO | AH98: NO | AK98: NO | AN98: NO | AO98: NO | AR98: 0 | AU98: NO | AV98: 5209465 | AW98: NO | AX98: NO | AY98: COLPENSIONES | AZ98: 29 | BA98: 5035817 | BB98: 0.16 | BC98: 805800 | BE98: 0 | BF98: 0 | BG98: 0 | BH98: 0 | BI98: 0 | BJ98: 805800 | BK98: NINGUNA | BL98: SALUD TOTAL | BM98: 29 | BN98: 5035817 | BO98: 0.04 | BP98: 201500 | BQ98: 0 | BS98: 0 | BU98: 0 | BV98: NINGUNA | BW98: COLMENA | BX98: 29 | BY98: 5035817 | BZ98: 0.0696 | CA98: 5 | CB98: CENTRO TRABAJO 24 | CC98: 5711001 | CD98: 350500 | CE98: 29 | CF98: COMPENSAR | CG98: 5035817 | CH98: 0.04 | CI98: 201500 | CJ98: 5035817 | CK98: 0 | CL98: 0 | CM98: 0 | CN98: 0 | CO98: 0 | CP98: 0 | CQ98: 0 | CR98: 0 | CS98: SI
A99: CAUSADO | B99: CC | C99: 1032403143 | D99: DIAZ LEGUIZAMON YESID ALEJANDRO | E99: DIAZ | F99: LEGUIZAMON | G99: YESID | H99: ALEJANDRO | I99: BOGOTA_D.E. | J99: BOGOTA | K99: 1. DEPENDIENTE | L99: NINGUNO | M99: 27 | N99: NO | O99: NO | Q99: Todos los sistemas (ARL, AFP, CCF, EPS) | R99: 46058 | S99: Todos los sistemas (ARL, AFP, CCF, EPS) | T99: 46062 | U99: NO | V99: NO | W99: NO | X99: NO | Y99: NO | AA99: NO | AB99: NO | AE99: NO | AH99: NO | AK99: NO | AN99: NO | AO99: NO | AR99: 0 | AU99: NO | AV99: 2223339 | AW99: NO | AX99: NO | AY99: PORVENIR | AZ99: 5 | BA99: 291818 | BB99: 0.16 | BC99: 46700 | BE99: 0 | BF99: 0 | BG99: 0 | BH99: 0 | BI99: 0 | BJ99: 46700 | BK99: NINGUNA | BL99: SANITAS | BM99: 5 | BN99: 291818 | BO99: 0.04 | BP99: 11700 | BQ99: 0 | BS99: 0 | BU99: 0 | BV99: NINGUNA | BW99: COLMENA | BX99: 5 | BY99: 291818 | BZ99: 0.0696 | CA99: 5 | CB99: CENTRO TRABAJO 24 | CC99: 5711001 | CD99: 20400 | CE99: 5 | CF99: COMPENSAR | CG99: 237897 | CH99: 0.04 | CI99: 9600 | CJ99: 237897 | CK99: 0 | CL99: 0 | CM99: 0 | CN99: 0 | CO99: 0 | CP99: 0 | CQ99: 0 | CR99: 0 | CS99: SI
A100: CAUSADO | B100: CC | C100: 1032445329 | D100: MOLINA PAEZ JOHN EDINSSON | E100: MOLINA | F100: PAEZ | G100: JOHN | H100: EDINSSON | I100: BOGOTA_D.E. | J100: BOGOTA | K100: 1. DEPENDIENTE | L100: NINGUNO | M100: 94 | N100: NO | O100: NO | Q100: Todos los sistemas (ARL, AFP, CCF, EPS) | R100: 46069 | S100: NO | U100: NO | V100: NO | W100: NO | X100: NO | Y100: NO | AA100: NO | AB100: NO | AE100: NO | AH100: NO | AK100: NO | AN100: NO | AO100: NO | AR100: 0 | AU100: NO | AV100: 5676577 | AW100: NO | AX100: SI | AY100: SKANDIA | AZ100: 15 | BA100: 2838289 | BB100: 0.16 | BC100: 454200 | BE100: 0 | BF100: 0 | BG100: 0 | BH100: 0 | BI100: 0 | BJ100: 454200 | BK100: NINGUNA | BL100: FAMISANAR | BM100: 15 | BN100: 2838289 | BO100: 0.04 | BP100: 113600 | BQ100: 0 | BS100: 0 | BU100: 0 | BV100: NINGUNA | BW100: COLMENA | BX100: 15 | BY100: 2838289 | BZ100: 0.0696 | CA100: 5 | CB100: CENTRO TRABAJO 24 | CC100: 5711001 | CD100: 197600 | CE100: 15 | CF100: COMPENSAR | CG100: 2838289 | CH100: 0.04 | CI100: 113600 | CJ100: 2838289 | CK100: 0 | CL100: 0 | CM100: 0 | CN100: 0 | CO100: 0 | CP100: 0 | CQ100: 0 | CR100: 0 | CS100: SI
...

Sheet Dinamica
A2: AFP
A3: Suma de Total | D3: No.
A4: No ID | B4: APELLIDOS Y NOMBRES | C4: Administradora | D4: CAUSADO | E4: PAGADO | F4: Total general
A5: 1003736605 | B5: ALVAREZ CORREA JOSE ANGEL | C5: PORVENIR | D5: 487000 | E5: 487000 | F5: 974000 | H5: =+D5-E5 -> 0
A6: 1007855319 | B6: MENDOZA VALDEZ ARAMIS | C6: PORVENIR | D6: 505200 | E6: 505200 | F6: 1010400 | H6: =+D6-E6 -> 0
A7: 1011020 | B7: HEREDIA MENDOZA HECTOR YOHAN | C7: SKANDIA | D7: 1302000 | E7: 1302000 | F7: 2604000 | H7: =+D7-E7 -> 0
A8: 1013642764 | B8: GIRALDO MONSALVE JONATHAN ALEXANDER | C8: PROTECCION | D8: 1426300 | E8: 1426300 | F8: 2852600 | H8: =+D8-E8 -> 0
A9: 1013652019 | B9: VEGA LARA IVAN ENRIQUE | C9: PROTECCION | D9: 611700 | E9: 611700 | F9: 1223400 | H9: =+D9-E9 -> 0
A10: 1014201150 | B10: MATEUS RUEDA DANIEL RICARDO | C10: PORVENIR | D10: 1944300 | E10: 1944300 | F10: 3888600 | H10: =+D10-E10 -> 0
A11: 1014237269 | B11: MORENO MONTAÑO JENIFER | C11: PROTECCION | D11: 585700 | E11: 585700 | F11: 1171400 | H11: =+D11-E11 -> 0
A12: 1014246981 | B12: SAENZ VARGAS FABIO MAURICIO | C12: PORVENIR | D12: 908300 | E12: 908300 | F12: 1816600 | H12: =+D12-E12 -> 0
A13: 1014292676 | B13: QUIROGA CASTIBLANCO ANDRES EDUARDO | C13: PORVENIR | D13: 767700 | E13: 767700 | F13: 1535400 | H13: =+D13-E13 -> 0
A14: 1015436314 | B14: VELASQUEZ SANTIAGO NICOLAS | C14: PORVENIR | D14: 833600 | E14: 833600 | F14: 1667200 | H14: =+D14-E14 -> 0
A15: 1016008194 | B15: MORENO QUINTANA IVAN ERNESTO | C15: PORVENIR | D15: 508800 | E15: 508800 | F15: 1017600 | H15: =+D15-E15 -> 0
A16: 1019021939 | B16: RAMIREZ RIVADENEIRA EDUARDO ENRIQUE | C16: PORVENIR | D16: 1980700 | E16: 2178700 | F16: 4159400 | H16: =+D16-E16 -> -198000
... A42: 1120740098 | B42: MENDOZA SIERRA ELBERT | C42: PORVENIR | D42: 392500 | E42: 392500 | F42: 785000 | H42: =+D42-E42 -> 0
A43: 1121297352 | B43: PUCHAINA IPUANA JUAN DAVID | C43: COLFONDOS | D43: 343500 | F43: 343500 | H43: =+D43-E43 -> 343500
A44: 1121297352 | B44: PUSHAINA IPUANA JUAN DAVID | C44: COLFONDOS | E44: 343500 | F44: 343500 | H44: =+D44-E44 -> -343500
A45: 1121303103 | B45: DE ARMAS GOMEZ EDILFREDO | C45: PORVENIR | D45: 334700 | E45: 334700 | F45: 669400 | H45: =+D45-E45 -> 0
A46: 11234131 | B46: AVELLANEDA CHOACHI JUAN CARLOS | C46: COLPENSIONES | D46: 1904400 | E46: 1904400 | F46: 3808800 | H46: =+D46-E46 -> 0
A47: 1128060281 | B47: ROMERO AVILA YORLAN MANUEL | C47: PROTECCION | D47: 833600 | E47: 833600 | F47: 1667200 | H47: =+D47-E47 -> 0
A48: 1143350898 | B48: VILLALOBOS DE LA BARRERA ERWIN EMILIO | C48: PORVENIR | D48: 1021600 | E48: 1021600 | F48: 2043200 | H48: =+D48-E48 -> 0
A49: 11442086 | B49: OBANDO CORTES LUIS EDSON | C49: COLPENSIONES | D49: 4519800 | E49: 4519800 | F49: 9039600 | H49: =+D49-E49 -> 0
A50: 11442343 | B50: MATEUS ALMONACID GIOVANNI FRANCESCO | C50: PORVENIR | D50: 1739500 | E50: 1739500 | F50: 3479000 | H50: =+D50-E50 -> 0
A51: 12280057 | B51: NUÑEZ POLANIA CRISTIAN MANUEL | C51: COLPENSIONES | D51: 748700 | E51: 748700 | F51: 1497400 | H51: =+D51-E51 -> 0
A52: 26996654 | B52: MENDOZA SIERRA EILIS | C52: PORVENIR | D52: 444700 | E52: 444700 | F52: 889400 | H52: =+D52-E52 -> 0
A53: 30236463 | B53: ARANGO GRISALES SANDRA MILENA | C53: COLPENSIONES | D53: 1385900 | E53: 1385900 | F53: 2771800 | H53: =+D53-E53 -> 0
A54: 39786135 | B54: LONDOÑO BRIGARD MONICA | C54: COLPENSIONES | D54: 1814400 | E54: 1814400 | F54: 3628800 | H54: =+D54-E54 -> 0
A55: 4147388 | B55: SAENZ AMADO JAIRO ARMANDO | C55: COLPENSIONES | D55: 1309100 | E55: 1290500 | F55: 2599600 | H55: =+D55-E55 -> 18600
A56: 4165737 | B56: CARDENAS VARGAS HECTOR HERNAN | C56: COLPENSIONES | D56: 471400 | E56: 471400 | F56: 942800 | H56: =+D56-E56 -> 0
... A70: 60446101 | B70: PALENCIA MORA LUZ AIDEE | C70: PROTECCION | D70: 833600 | E70: 833600 | F70: 1667200 | H70: =+D70-E70 -> 0
A71: 64550520 | B71: CANOLES PELUFFO KADIS ARELIS DEL CARMEN | C71: (en blanco) | D71: 0 | F71: 0 | H71: =+D71-E71 -> 0
A72: 64550520 | B72: CANOLES PELUFFO KADIS ARELIS DEL CARMEN | C72: NINGUNA | E72: 0 | F72: 0 | H72: =+D72-E72 -> 0
A73: 6565638 | B73: GALLEGO CAICEDO CARLOS EMILIO | C73: COLPENSIONES | D73: 338000 | E73: 338000 | F73: 676000 | H73: =+D73-E73 -> 0
A74: 65709021 | B74: ENTENCIPA MENDOZA LUZ ANGELA | C74: PROTECCION | D74: 291200 | E74: 291200 | F74: 582400 | H74: =+D74-E74 -> 0
A75: 7225978 | B75: NUÑEZ ROJAS JOSE DAVID | C75: COLPENSIONES | D75: 589800 | E75: 580200 | F75: 1170000 | H75: =+D75-E75 -> 9600
A76: 7229763 | B76: TAMAYO PEDRAZA JUAN MANUEL | C76: COLPENSIONES | D76: 1904400 | E76: 1904400 | F76: 3808800 | H76: =+D76-E76 -> 0
A77: 73144545 | B77: VANEGAS PATERNINA JAIRO RAMON | C77: COLPENSIONES | D77: 716400 | E77: 716400 | F77: 1432800 | H77: =+D77-E77 -> 0
A78: 74180943 | B78: LEON MARTINEZ CARLOS ABEL | C78: COLPENSIONES | D78: 2940800 | E78: 2940800 | F78: 5881600 | H78: =+D78-E78 -> 0
A79: 74324181 | B79: GARZON OSORIO RODRIGO ALBERTO | C79: COLPENSIONES | D79: 1980800 | E79: 1980800 | F79: 3961600 | H79: =+D79-E79 -> 0
A80: 74378398 | B80: ZAMUDIO MENDOZA CAMILO ANDRES | C80: PROTECCION | D80: 1565000 | E80: 1565000 | F80: 3130000 | H80: =+D80-E80 -> 0
A81: 77190624 | B81: CAMARGO MAESTRE JOSE FERNANDO | C81: PORVENIR | D81: 2447200 | E81: 2447200 | F81: 4894400 | H81: =+D81-E81 -> 0
A82: 79046010 | B82: HERRERA PEREZ LUIS ALFONSO | C82: COLFONDOS | D82: 517800 | E82: 517800 | F82: 1035600 | H82: =+D82-E82 -> 0
A83: 79127197 | B83: RINCON GUERRERO HECTOR JAIME | C83: COLPENSIONES | D83: 1021600 | E83: 1021600 | F83: 2043200 | H83: =+D83-E83 -> 0
A84: 79387048 | B84: VELASQUEZ TORRES JOSE | C84: COLPENSIONES | D84: 1422700 | E84: 1422700 | F84: 2845400 | H84: =+D84-E84 -> 0
... A142: 1065848632 | B142: ARISTIZABAL CORONADO ARLIN JOSE | C142: PORVENIR | D142: 517800 | E142: 517800 | F142: 1035600 | H142: =+D142-E142 -> 0
A143: 1120747452 | B143: TORRES COBO XABIER ALFONSO | C143: PORVENIR | D143: 392500 | F143: 392500 | H143: =+D143-E143 -> 392500
A144: 1120747452 | B144: TORRES COBO XAVIER ALFONSO | C144: PORVENIR | E144: 392500 | F144: 392500 | H144: =+D144-E144 -> -392500
A145: 1121041870 | B145: FERNANDEZ DAZA ALVARO JAVIER | C145: PORVENIR | D145: 330500 | E145: 330500 | F145: 661000 | H145: =+D145-E145 -> 0
A146: 1192784397 | B146: EPIAYU EPIAYU JOSE ESNEIDER | C146: PORVENIR | D146: 347100 | E146: 347100 | F146: 694200 | H146: =+D146-E146 -> 0
A147: 1192903372 | B147: SOTO EPIAYU NOLVER SEGUNDO | C147: PORVENIR | D147: 343900 | E147: 343900 | F147: 687800 | H147: =+D147-E147 -> 0
A148: 1192921948 | B148: HERNANDEZ BERNAL DANIEL | C148: PORVENIR | D148: 313200 | E148: 313200 | F148: 626400 | H148: =+D148-E148 -> 0
A149: 1193428618 | B149: EPINAYU SAJAUT JEFREY ALBERTO | C149: PORVENIR | D149: 335400 | E149: 335400 | F149: 670800 | H149: =+D149-E149 -> 0
A150: 1193485217 | B150: VIDAL URIANA FABIAN CAMILO | C150: PORVENIR | D150: 345500 | E150: 345500 | F150: 691000 | H150: =+D150-E150 -> 0
A151: 1235253332 | B151: JIMENEZ MORENO JUAN CARLOS | C151: PROTECCION | D151: 326300 | E151: 326300 | F151: 652600 | H151: =+D151-E151 -> 0
A152: 19593689 | B152: CASTRO GARCIA MILTON RAFAEL | C152: PROTECCION | D152: 430100 | E152: 430100 | F152: 860200 | H152: =+D152-E152 -> 0
A153: 5135410 | B153: ARRIETA MOLINA FREDIS HERNAN | C153: PORVENIR | D153: 337800 | E153: 337800 | F153: 675600 | H153: =+D153-E153 -> 0
A154: 5607565 | B154: COMAS GARCIA FRANK HENRIS | C154: PORVENIR | D154: 363000 | E154: 363000 | F154: 726000 | H154: =+D154-E154 -> 0
A155: 8485443 | B155: AREVALO MEJIA ALDERSON ENRIQUE | C155: PORVENIR | D155: 501800 | E155: 501800 | F155: 1003600 | H155: =+D155-E155 -> 0
A156: 93382704 | B156: POVEDA TOBAR ROBERT | C156: COLPENSIONES | D156: 898600 | E156: 898600 | F156: 1797200 | H156: =+D156-E156 -> 0
... A161: 11347571 | B161: ALVAREZ CAÑON CARLOS EFREN | C161: PROTECCION | D161: 458100 | E161: 458100 | F161: 916200 | H161: =+D161-E161 -> 0
A162: 1018505650 | B162: ZAMUDIO CORDOVA SANTIAGO | C162: NINGUNA | E162: 0 | F162: 0 | H162: =+D162-E162 -> 0
A163: 1003252787 | B163: MANGA FRIA JUAN LUIS | C163: PORVENIR | D163: 334500 | E163: 334500 | F163: 669000 | H163: =+D163-E163 -> 0
A164: 1006733914 | B164: CUEVA CONTRERAS EDAIR ALEJANDRO | C164: PORVENIR | D164: 337800 | E164: 337800 | F164: 675600 | H164: =+D164-E164 -> 0
A165: 1006734131 | B165: GOMEZ ORTEGA JEINER JOSE | C165: PORVENIR | D165: 384100 | E165: 384100 | F165: 768200 | H165: =+D165-E165 -> 0
A166: 1006734275 | B166: BRITO BRITO NEIDER IVAN | C166: PORVENIR | D166: 331200 | E166: 331200 | F166: 662400 | H166: =+D166-E166 -> 0
A167: 1006734779 | B167: RIZO RIVAS ANDRES MANUEL | C167: COLPENSIONES | D167: 336000 | E167: 336000 | F167: 672000 | H167: =+D167-E167 -> 0
A168: 1006817439 | B168: DIAZ LOPEZ JAIME LUIS | C168: PORVENIR | D168: 330100 | E168: 330100 | F168: 660200 | H168: =+D168-E168 -> 0
A169: 1043848010 | B169: SANDOVAL RODRIGUEZ IRON LUIS | C169: PORVENIR | D169: 365700 | E169: 365700 | F169: 731400 | H169: =+D169-E169 -> 0
A170: 1050201056 | B170: TIGA RODRIGUEZ JHORDAN SNEIDER | C170: COLPENSIONES | D170: 413400 | E170: 413400 | F170: 826800 | H170: =+D170-E170 -> 0
A171: 1051444380 | B171: AHUMEDO CARABALLO LUIS ALFREDO | C171: PROTECCION | D171: 546700 | E171: 546700 | F171: 1093400 | H171: =+D171-E171 -> 0
A172: 1057591543 | B172: VELA RODAS KEVIN STEVENSON | C172: PROTECCION | D172: 664400 | E172: 664400 | F172: 1328800 | H172: =+D172-E172 -> 0
A173: 1061046957 | B173: FERNANDEZ CONTRERAS DIEGO FERNANDO | C173: COLFONDOS | D173: 592400 | E173: 592400 | F173: 1184800 | H173: =+D173-E173 -> 0
A174: 1075655385 | B174: RODRIGUEZ LIZARAZO CARLOS ANDRES | C174: PORVENIR | D174: 488500 | E174: 488500 | F174: 977000 | H174: =+D174-E174 -> 0
... A177: 1128436217 | B177: VARGAS BERNAL OSWALDO JOSE | C177: PROTECCION | D177: 507800 | E177: 507800 | F177: 1015600 | H177: =+D177-E177 -> 0
A178: 11338086 | B178: SARMIENTO CASTILLO GERMAN | C178: COLPENSIONES | D178: 239900 | F178: 239900 | H178: =+D178-E178 -> 239900
A179: 11338086 | B179: SARMIENTO CASTILLO GERMAN | C179: NINGUNA | E179: 0 | F179: 0 | H179: =+D179-E179 -> 0
A180: 11339799 | B180: GONZALEZ GARZON MARCO ANTONIO | C180: COLPENSIONES | D180: 663000 | E180: 663000 | F180: 1326000 | H180: =+D180-E180 -> 0
A181: 11348515 | B181: ALONSO SANTANA WILSON OSWALDO | C181: COLPENSIONES | D181: 456200 | E181: 456200 | F181: 912400 | H181: =+D181-E181 -> 0
A182: 1192768905 | B182: BRITO EPIAYU ARLEY ALFREDO | C182: PORVENIR | D182: 322500 | E182: 322500 | F182: 645000 | H182: =+D182-E182 -> 0
A183: 1192818361 | B183: SARMIENTO DAZA SANTIAGO | C183: PORVENIR | D183: 410500 | E183: 410500 | F183: 821000 | H183: =+D183-E183 -> 0
A184: 1192897058 | B184: ARREGOCES USTATE MAURICIO ALBERTO | C184: PORVENIR | D184: 328800 | E184: 328800 | F184: 657600 | H184: =+D184-E184 -> 0
A185: 17957153 | B185: ROJAS GUERRA LUIS DAVID | C185: PORVENIR | D185: 331200 | E185: 331200 | F185: 662400 | H185: =+D185-E185 -> 0
A186: 17959473 | B186: EPINAYU SAJAUT JOHAN DAVID | C186: PORVENIR | D186: 334600 | E186: 334600 | F186: 669200 | H186: =+D186-E186 -> 0
A187: 17973465 | B187: ARGOTE DUARTE LUIS ALFREDO | C187: PROTECCION | D187: 541700 | E187: 541700 | F187: 1083400 | H187: =+D187-E187 -> 0
A188: 70326398 | B188: CATAÑO CADAVID IVAN DARIO | C188: COLPENSIONES | D188: 596300 | E188: 596300 | F188: 1192600 | H188: =+D188-E188 -> 0
A189: 72173200 | B189: LAVALLE MORENO FIDILBERTO | C189: COLPENSIONES | D189: 865500 | E189: 865500 | F189: 1731000 | H189: =+D189-E189 -> 0
A190: 73199286 | B190: LEAL RODRIGUEZ GUILLERMO LUIS | C190: PORVENIR | D190: 717500 | E190: 717500 | F190: 1435000 | H190: =+D190-E190 -> 0
A191: 74365756 | B191: CASTRO DIAZ LIBARDO | C191: COLFONDOS | D191: 416200 | E191: 416200 | F191: 832400 | H191: =+D191-E191 -> 0
... A198: 1020761014 | B198: OSPINA VILLAMIL ALEJANDRA | C198: COLFONDOS | D198: 833600 | E198: 833600 | F198: 1667200 | H198: =+D198-E198 -> 0
A199: 1042420943 | B199: HERNANDEZ MERCHAN JHONATHAN EDGARDO | C199: PORVENIR | D199: 358000 | F199: 358000 | H199: =+D199-E199 -> 358000
A200: 1042420943 | B200: HERNANDEZ MERCHAN JONATHAN EDGARDO | C200: PORVENIR | E200: 358000 | F200: 358000 | H200: =+D200-E200 -> -358000
A201: 1051656145 | B201: ECHAVEZ VASQUEZ ALVARO JOSE | C201: PORVENIR | D201: 364600 | E201: 364600 | F201: 729200 | H201: =+D201-E201 -> 0
A202: 1051670217 | B202: ECHAVEZ VASQUEZ JOSE DANIEL | C202: PROTECCION | D202: 377600 | E202: 377600 | F202: 755200 | H202: =+D202-E202 -> 0
A203: 1052953775 | B203: ZABALA RICARDO LEONARDO JOSE | C203: PORVENIR | D203: 339200 | E203: 339200 | F203: 678400 | H203: =+D203-E203 -> 0
A204: 1082917859 | B204: QUIROZ GARCIA JOSE LUIS | C204: COLFONDOS | D204: 593400 | E204: 593400 | F204: 1186800 | H204: =+D204-E204 -> 0
A205: 5842924 | B205: ALVAREZ BELIZARIO JOHAN ALEJANDRO | C205: PROTECCION | D205: 337700 | E205: 337700 | F205: 675400 | H205: =+D205-E205 -> 0
A206: 65631300 | B206: ISAACS GUERRA MARIA ISABEL | C206: PORVENIR | E206: 488400 | F206: 488400 | H206: =+D206-E206 -> -488400
A207: 65631300 | B207: ISSAACS GUERRA MARIA ISABEL | C207: PORVENIR | D207: 488400 | F207: 488400 | H207: =+D207-E207 -> 488400
A208: 72143920 | B208: BARRAZA SOLANO DEBIS ALBERTO | C208: PORVENIR | D208: 619200 | E208: 619200 | F208: 1238400 | H208: =+D208-E208 -> 0
...

Sheet Ajuste
A1: Tipo | B1: Documento | C1: Nombre | D1: Entidad Cuasada | E1: Entidad Pagada | F1: Valor Causado | G1: Valor Pagado | H1: Dif | I1: Observacion
A2: PENSIÓN | B2: 1019021939 | C2: RAMIREZ RIVADENEIRA EDUARDO ENRIQUE | D2: PORVENIR | E2: PORVENIR | F2: =1980700+58201 -> 2038901 | G2: 2178700 | H2: =+G2-F2 -> 139799 | I2: =(IF(H2>0,"AJUSTE POR MAYOR VALOR PAGADO",IF(H2<0,"AJUSTE POR MENOR VALOR PAGADO","CRUCE DE ENTIDADES"))) -> AJUSTE POR MAYOR VALOR PAGADO | K2: =SUMIFS(Hoja1!I:I,Hoja1!B:B,"PENSION",Hoja1!D:D,Ajuste!B2) -> 0
A3: PENSIÓN | B3: 1036964545 | C3: MORALES VANEGAS MARIA FERNANDA | D3: COLPENSIONES | E3: COLPENSIONES | F3: 579400 | G3: 582500 | H3: =+G3-F3 -> 3100 | I3: =(IF(H3>0,"AJUSTE POR MAYOR VALOR PAGADO",IF(H3<0,"AJUSTE POR MENOR VALOR PAGADO","CRUCE DE ENTIDADES"))) -> AJUSTE POR MAYOR VALOR PAGADO | K3: =SUMIFS(Hoja1!I:I,Hoja1!B:B,"PENSION",Hoja1!D:D,Ajuste!B3) -> 0
A4: PENSIÓN | B4: 1043605841 | C4: POLO CABALLERO ESTEFER JOSE | D4: PROTECCION | E4: PROTECCION | F4: 302300 | G4: 305000 | H4: =+G4-F4 -> 2700 | I4: =(IF(H4>0,"AJUSTE POR MAYOR VALOR PAGADO",IF(H4<0,"AJUSTE POR MENOR VALOR PAGADO","CRUCE DE ENTIDADES"))) -> AJUSTE POR MAYOR VALOR PAGADO | K4: =SUMIFS(Hoja1!I:I,Hoja1!B:B,"PENSION",Hoja1!D:D,Ajuste!B4) -> 0
A5: PENSIÓN | B5: 1077085712 | C5: PUENTES FLOREZ CLAUDIA LILIANA | D5: COLPENSIONES | E5: COLPENSIONES | F5: =1021700-1560 -> 1020140 | G5: 1015400 | H5: =+G5-F5 -> -4740 | I5: =(IF(H5>0,"AJUSTE POR MAYOR VALOR PAGADO",IF(H5<0,"AJUSTE POR MENOR VALOR PAGADO","CRUCE DE ENTIDADES"))) -> AJUSTE POR MENOR VALOR PAGADO | K5: =SUMIFS(Hoja1!I:I,Hoja1!B:B,"PENSION",Hoja1!D:D,Ajuste!B5) -> 0
A6: PENSIÓN | B6: 1098639080 | C6: MARIN FERREIRA NINI JOHANNA | D6: PORVENIR | E6: PORVENIR | F6: =1457100+2500 -> 1459600 | G6: 1467700 | H6: =+G6-F6 -> 8100 | I6: =(IF(H6>0,"AJUSTE POR MAYOR VALOR PAGADO",IF(H6<0,"AJUSTE POR MENOR VALOR PAGADO","CRUCE DE ENTIDADES"))) -> AJUSTE POR MAYOR VALOR PAGADO | K6: =SUMIFS(Hoja1!I:I,Hoja1!B:B,"PENSION",Hoja1!D:D,Ajuste!B6) -> 0
A7: PENSIÓN | B7: 4147388 | C7: SAENZ AMADO JAIRO ARMANDO | D7: COLPENSIONES | E7: COLPENSIONES | F7: =1309100-5686 -> 1303414 | G7: 1290500 | H7: =+G7-F7 -> -12914 | I7: =(IF(H7>0,"AJUSTE POR MAYOR VALOR PAGADO",IF(H7<0,"AJUSTE POR MENOR VALOR PAGADO","CRUCE DE ENTIDADES"))) -> AJUSTE POR MENOR VALOR PAGADO | K7: =SUMIFS(Hoja1!I:I,Hoja1!B:B,"PENSION",Hoja1!D:D,Ajuste!B7) -> 0
A8: PENSIÓN | B8: 7225978 | C8: NUÑEZ ROJAS JOSE DAVID | D8: COLPENSIONES | E8: COLPENSIONES | F8: =589800-2400 -> 587400 | G8: 580200 | H8: =+G8-F8 -> -7200 | I8: =(IF(H8>0,"AJUSTE POR MAYOR VALOR PAGADO",IF(H8<0,"AJUSTE POR MENOR VALOR PAGADO","CRUCE DE ENTIDADES"))) -> AJUSTE POR MENOR VALOR PAGADO | K8: =SUMIFS(Hoja1!I:I,Hoja1!B:B,"PENSION",Hoja1!D:D,Ajuste!B8) -> 0
A9: PENSIÓN | B9: 79836141 | C9: PEREZ MARIN ERVIN CELEDONIO | D9: PORVENIR | E9: PORVENIR | F9: 2736300 | G9: 2733500 | H9: =+G9-F9 -> -2800 | I9: =(IF(H9>0,"AJUSTE POR MAYOR VALOR PAGADO",IF(H9<0,"AJUSTE POR MENOR VALOR PAGADO","CRUCE DE ENTIDADES"))) -> AJUSTE POR MENOR VALOR PAGADO | K9: =SUMIFS(Hoja1!I:I,Hoja1!B:B,"PENSION",Hoja1!D:D,Ajuste!B9) -> 0
A10: PENSIÓN | B10: 93371464 | C10: TORRES BETANCOURT ARISTOBULO | D10: COLPENSIONES | E10: COLPENSIONES | F10: =1302800+127564 -> 1430364 | G10: 1736900 | H10: =+G10-F10 -> 306536 | I10: =(IF(H10>0,"AJUSTE POR MAYOR VALOR PAGADO",IF(H10<0,"AJUSTE POR MENOR VALOR PAGADO","CRUCE DE ENTIDADES"))) -> AJUSTE POR MAYOR VALOR PAGADO | K10: =SUMIFS(Hoja1!I:I,Hoja1!B:B,"PENSION",Hoja1!D:D,Ajuste!B10) -> 0
A11: PENSIÓN | B11: 93373335 | C11: MORA CUBILLOS JESUS ELKY | D11: COLPENSIONES | E11: COLPENSIONES | F11: =1433300-3745 -> 1429555 | G11: 1421500 | H11: =+G11-F11 -> -8055 | I11: =(IF(H11>0,"AJUSTE POR MAYOR VALOR PAGADO",IF(H11<0,"AJUSTE POR MENOR VALOR PAGADO","CRUCE DE ENTIDADES"))) -> AJUSTE POR MENOR VALOR PAGADO | K11: =SUMIFS(Hoja1!I:I,Hoja1!B:B,"PENSION",Hoja1!D:D,Ajuste!B11) -> 0
A12: PENSIÓN | B12: 11338086 | C12: SARMIENTO CASTILLO GERMAN | D12: COLPENSIONES | E12: COLPENSIONES | F12: =239900-59967 -> 179933 | G12: 0 | H12: =+G12-F12 -> -179933 | I12: =(IF(H12>0,"AJUSTE POR MAYOR VALOR PAGADO",IF(H12<0,"AJUSTE POR MENOR VALOR PAGADO","CRUCE DE ENTIDADES"))) -> AJUSTE POR MENOR VALOR PAGADO | K12: =SUMIFS(Hoja1!I:I,Hoja1!B:B,"PENSION",Hoja1!D:D,Ajuste!B12) -> 0
A13: PENSIÓN | B13: 1082866503 | C13: SOSA GONZALEZ JOSE DANIEL | D13: PROTECCION | E13: PROTECCION | F13: 358900 | G13: 357200 | H13: =+G13-F13 -> -1700 | I13: =(IF(H13>0,"AJUSTE POR MAYOR VALOR PAGADO",IF(H13<0,"AJUSTE POR MENOR VALOR PAGADO","CRUCE DE ENTIDADES"))) -> AJUSTE POR MENOR VALOR PAGADO | K13: =SUMIFS(Hoja1!I:I,Hoja1!B:B,"PENSION",Hoja1!D:D,Ajuste!B13) -> 0
A14: PENSIÓN | B14: 1032403143 | C14: DIAZ LEGUIZAMON YESID ALEJANDRO | D14: PORVENIR | E14: PORVENIR | F14: =46700+3200 -> 49900 | G14: 59400 | H14: =+G14-F14 -> 9500 | I14: =(IF(H14>0,"AJUSTE POR MAYOR VALOR PAGADO",IF(H14<0,"AJUSTE POR MENOR VALOR PAGADO","CRUCE DE ENTIDADES"))) -> AJUSTE POR MAYOR VALOR PAGADO | K14: =SUMIFS(Hoja1!I:I,Hoja1!B:B,"PENSION",Hoja1!D:D,Ajuste!B14) -> 0
A15: PENSIÓN | B15: 17957880 | C15: FORERO CALDERON EDIER | D15: PORVENIR | E15: COLPENSIONES | F15: 78200 | G15: 78200 | H15: =+G15-F15 -> 0 | I15: =(IF(H15>0,"AJUSTE POR MAYOR VALOR PAGADO",IF(H15<0,"AJUSTE POR MENOR VALOR PAGADO","CRUCE DE ENTIDADES"))) -> CRUCE DE ENTIDADES | K15: =SUMIFS(Hoja1!I:I,Hoja1!B:B,"PENSION",Hoja1!D:D,Ajuste!B15) -> 0
A16: SALUD | B16: 1036964545 | C16: MORALES VANEGAS MARIA FERNANDA | D16: SANITAS | E16: SANITAS | F16: 145000 | G16: 145700 | H16: =+G16-F16 -> 700 | I16: =(IF(H16>0,"AJUSTE POR MAYOR VALOR PAGADO",IF(H16<0,"AJUSTE POR MENOR VALOR PAGADO","CRUCE DE ENTIDADES"))) -> AJUSTE POR MAYOR VALOR PAGADO | K16: =SUMIFS(Hoja1!I:I,Hoja1!B:B,"salud",Hoja1!D:D,Ajuste!B16) -> 0
A17: SALUD | B17: 1043605841 | C17: POLO CABALLERO ESTEFER JOSE | D17: FAMISANAR | E17: FAMISANAR | F17: 75600 | G17: 76300 | H17: =+G17-F17 -> 700 | I17: =(IF(H17>0,"AJUSTE POR MAYOR VALOR PAGADO",IF(H17<0,"AJUSTE POR MENOR VALOR PAGADO","CRUCE DE ENTIDADES"))) -> AJUSTE POR MAYOR VALOR PAGADO | K17: =SUMIFS(Hoja1!I:I,Hoja1!B:B,"salud",Hoja1!D:D,Ajuste!B17) -> 0
A18: SALUD | B18: 1077085712 | C18: PUENTES FLOREZ CLAUDIA LILIANA | D18: FAMISANAR | E18: FAMISANAR | F18: =255500-1600 -> 253900 | G18: 254000 | H18: =+G18-F18 -> 100 | I18: =(IF(H18>0,"AJUSTE POR MAYOR VALOR PAGADO",IF(H18<0,"AJUSTE POR MENOR VALOR PAGADO","CRUCE DE ENTIDADES"))) -> AJUSTE POR MAYOR VALOR PAGADO | K18: =SUMIFS(Hoja1!I:I,Hoja1!B:B,"salud",Hoja1!D:D,Ajuste!B18) -> -1600
A19: SALUD | B19: 4147388 | C19: SAENZ AMADO JAIRO ARMANDO | D19: COMPENSAR | E19: COMPENSAR | F19: =308100-4500 -> 303600 | G19: 303700 | H19: =+G19-F19 -> 100 | I19: =(IF(H19>0,"AJUSTE POR MAYOR VALOR PAGADO",IF(H19<0,"AJUSTE POR MENOR VALOR PAGADO","CRUCE DE ENTIDADES"))) -> AJUSTE POR MAYOR VALOR PAGADO | K19: =SUMIFS(Hoja1!I:I,Hoja1!B:B,"salud",Hoja1!D:D,Ajuste!B19) -> -4500
A20: SALUD | B20: 4165737 | C20: CARDENAS VARGAS HECTOR HERNAN | D20: EPS FAMILIAR DE COLOMBIA SAS | E20: SALUD TOTAL | F20: 117900 | G20: 117900 | H20: =+G20-F20 -> 0 | I20: =(IF(H20>0,"AJUSTE POR MAYOR VALOR PAGADO",IF(H20<0,"AJUSTE POR MENOR VALOR PAGADO","CRUCE DE ENTIDADES"))) -> CRUCE DE ENTIDADES | K20: =SUMIFS(Hoja1!I:I,Hoja1!B:B,"salud",Hoja1!D:D,Ajuste!B20) -> 0
A21: SALUD | B21: 79836141 | C21: PEREZ MARIN ERVIN CELEDONIO | D21: SANITAS | E21: SANITAS | F21: 2011700 | G21: 2009600 | H21: =+G21-F21 -> -2100 | I21: =(IF(H21>0,"AJUSTE POR MAYOR VALOR PAGADO",IF(H21<0,"AJUSTE POR MENOR VALOR PAGADO","CRUCE DE ENTIDADES"))) -> AJUSTE POR MENOR VALOR PAGADO | K21: =SUMIFS(Hoja1!I:I,Hoja1!B:B,"salud",Hoja1!D:D,Ajuste!B21) -> 0
A22: SALUD | B22: 93373335 | C22: MORA CUBILLOS JESUS ELKY | D22: SANITAS | E22: SANITAS | F22: =337200-2800 -> 334400 | G22: 334500 | H22: =+G22-F22 -> 100 | I22: =(IF(H22>0,"AJUSTE POR MAYOR VALOR PAGADO",IF(H22<0,"AJUSTE POR MENOR VALOR PAGADO","CRUCE DE ENTIDADES"))) -> AJUSTE POR MAYOR VALOR PAGADO | K22: =SUMIFS(Hoja1!I:I,Hoja1!B:B,"salud",Hoja1!D:D,Ajuste!B22) -> -2800
A23: SALUD | B23: 1047371050 | C23: SALAS GUERRA RONAL RAFAEL | D23: MUTUAL SER | E23: MUTUAL SER | F23: 133000 | G23: 148200 | H23: =+G23-F23 -> 15200 | I23: =(IF(H23>0,"AJUSTE POR MAYOR VALOR PAGADO",IF(H23<0,"AJUSTE POR MENOR VALOR PAGADO","CRUCE DE ENTIDADES"))) -> AJUSTE POR MAYOR VALOR PAGADO | K23: =SUMIFS(Hoja1!I:I,Hoja1!B:B,"salud",Hoja1!D:D,Ajuste!B23) -> 0
A24: ARL | B24: 1019021939 | C24: RAMIREZ RIVADENEIRA EDUARDO ENRIQUE | D24: COLMENA | E24: COLMENA | F24: 810900 | G24: 892000 | H24: =+G24-F24 -> 81100 | I24: =(IF(H24>0,"AJUSTE POR MAYOR VALOR PAGADO",IF(H24<0,"AJUSTE POR MENOR VALOR PAGADO","CRUCE DE ENTIDADES"))) -> AJUSTE POR MAYOR VALOR PAGADO
A25: ARL | B25: 1036964545 | C25: MORALES VANEGAS MARIA FERNANDA | D25: COLMENA | E25: COLMENA | F25: 16700 | G25: 16800 | H25: =+G25-F25 -> 100 | I25: =(IF(H25>0,"AJUSTE POR MAYOR VALOR PAGADO",IF(H25<0,"AJUSTE POR MENOR VALOR PAGADO","CRUCE DE ENTIDADES"))) -> AJUSTE POR MAYOR VALOR PAGADO
A26: ARL | B26: 7225978 | C26: NUÑEZ ROJAS JOSE DAVID | D26: COLMENA | E26: COLMENA | F26: 256600 | G26: 252400 | H26: =+G26-F26 -> -4200 | I26: =(IF(H26>0,"AJUSTE POR MAYOR VALOR PAGADO",IF(H26<0,"AJUSTE POR MENOR VALOR PAGADO","CRUCE DE ENTIDADES"))) -> AJUSTE POR MENOR VALOR PAGADO
A27: ARL | B27: 93371464 | C27: TORRES BETANCOURT ARISTOBULO | D27: COLMENA | E27: COLMENA | F27: 533300 | G27: 711100 | H27: =+G27-F27 -> 177800 | I27: =(IF(H27>0,"AJUSTE POR MAYOR VALOR PAGADO",IF(H27<0,"AJUSTE POR MENOR VALOR PAGADO","CRUCE DE ENTIDADES"))) -> AJUSTE POR MAYOR VALOR PAGADO
A28: ARL | B28: 11338086 | C28: SARMIENTO CASTILLO GERMAN | D28: COLMENA | E28: COLMENA | F28: 186500 | G28: 186400 | H28: =+G28-F28 -> -100 | I28: =(IF(H28>0,"AJUSTE POR MAYOR VALOR PAGADO",IF(H28<0,"AJUSTE POR MENOR VALOR PAGADO","CRUCE DE ENTIDADES"))) -> AJUSTE POR MENOR VALOR PAGADO
A29: ARL | B29: 1082866503 | C29: SOSA GONZALES JOSE DANIEL | D29: COLMENA | E29: COLMENA | F29: 156200 | G29: 155400 | H29: =+G29-F29 -> -800 | I29: =(IF(H29>0,"AJUSTE POR MAYOR VALOR PAGADO",IF(H29<0,"AJUSTE POR MENOR VALOR PAGADO","CRUCE DE ENTIDADES"))) -> AJUSTE POR MENOR VALOR PAGADO
A30: ARL | B30: 1032403143 | C30: DIAZ LEGUIZAMON YESID ALEJANDRO | D30: COLMENA | E30: COLMENA | F30: 20400 | G30: 15500 | H30: =+G30-F30 -> -4900 | I30: =(IF(H30>0,"AJUSTE POR MAYOR VALOR PAGADO",IF(H30<0,"AJUSTE POR MENOR VALOR PAGADO","CRUCE DE ENTIDADES"))) -> AJUSTE POR MENOR VALOR PAGADO
A31: CCF | B31: 1019021939 | C31: RAMIREZ RIVADENEIRA EDUARDO ENRIQUE | D31: COMPENSAR | E31: COMPENSAR | F31: 419500 | G31: 466100 | H31: =+G31-F31 -> 46600 | I31: =(IF(H31>0,"AJUSTE POR MAYOR VALOR PAGADO",IF(H31<0,"AJUSTE POR MENOR VALOR PAGADO","CRUCE DE ENTIDADES"))) -> AJUSTE POR MAYOR VALOR PAGADO
A32: CCF | B32: 1036964545 | C32: MORALES VANEGAS MARIA FERNANDA | D32: COMPENSAR | E32: COMPENSAR | F32: 145000 | G32: 146500 | H32: =+G32-F32 -> 1500 | I32: =(IF(H32>0,"AJUSTE POR MAYOR VALOR PAGADO",IF(H32<0,"AJUSTE POR MENOR VALOR PAGADO","CRUCE DE ENTIDADES"))) -> AJUSTE POR MAYOR VALOR PAGADO
A33: CCF | B33: 93371464 | C33: TORRES BETANCOURT ARISTOBULO | D33: COMPENSAR | E33: COMPENSAR | F33: 204400 | G33: 306500 | H33: =+G33-F33 -> 102100 | I33: =(IF(H33>0,"AJUSTE POR MAYOR VALOR PAGADO",IF(H33<0,"AJUSTE POR MENOR VALOR PAGADO","CRUCE DE ENTIDADES"))) -> AJUSTE POR MAYOR VALOR PAGADO

Sheet Hoja1
A1: CONCEPTO | B1: NOMBRE CONCEPTO | C1: VALOR_SALARIAL | D1: Cédula identificación | E1: CODIGO_DEL_EMPLEADO | F1: NOMBRE | G1: PRIMER APELLIDO | H1: SEGUNDO APELLIDO
A2: C396 | B2: SALUD | C2: -46600 | D2: 1019021939 | E2: 00117E07 | F2: EDUARDO ENRIQUE | G2: RAMIREZ | H2: RIVADENEIRA | I2: =+C2*-1 -> 46600
A3: C396 | B3: SALUD | C3: 4500 | D3: 4147388 | E3: 00541E07 | F3: JAIRO ARMANDO | G3: SAENZ | H3: AMADO | I3: =+C3*-1 -> -4500
A4: C396 | B4: SALUD | C4: -102200 | D4: 93371464 | E4: 00554E07 | F4: ARISTOBULO | G4: TORRES | H4: BETANCOURT | I4: =+C4*-1 -> 102200
A5: C396 | B5: SALUD | C5: 2800 | D5: 93373335 | E5: 00555E07 | F5: JESUS ELKY | G5: MORA | H5: CUBILLOS | I5: =+C5*-1 -> -2800
A6: C396 | B6: SALUD | C6: 1600 | D6: 1077085712 | E6: 00690E07 | F6: CLAUDIA LILIANA | G6: PUENTES | H6: FLOREZ | I6: =+C6*-1 -> -1600
A7: C396 | B7: SALUD | C7: -2500 | D7: 1098639080 | E7: 00772E07 | F7: NINI JOHANNA | G7: MARIN | H7: FERREIRA | I7: =+C7*-1 -> 2500
A8: C396 | B8: SALUD | C8: 2400 | D8: 7225978 | E8: 02269E07 | F8: JOSE DAVID | G8: NUÑEZ | H8: ROJAS | I8: =+C8*-1 -> -2400
A9: C396 | B9: SALUD | C9: 2800 | D9: 1032403143 | E9: 02739E07 | F9: YESID ALEJANDRO | G9: DIAZ | H9: LEGUIZAMON | I9: =+C9*-1 -> -2800
A10: C396 | B10: SALUD | C10: -6000 | D10: 1032403143 | E10: 02739E07 | F10: YESID ALEJANDRO | G10: DIAZ | H10: LEGUIZAMON | I10: =+C10*-1 -> 6000
A11: C397 | B11: PENSIÓN | C11: -46601 | D11: 1019021939 | E11: 00117E07 | F11: EDUARDO ENRIQUE | G11: RAMIREZ | H11: RIVADENEIRA | I11: =+C11*-1 -> 46601
A12: C397 | B12: PENSIÓN | C12: 4386 | D12: 4147388 | E12: 00541E07 | F12: JAIRO ARMANDO | G12: SAENZ | H12: AMADO | I12: =+C12*-1 -> -4386
A13: C397 | B13: PENSIÓN | C13: -102164 | D13: 93371464 | E13: 00554E07 | F13: ARISTOBULO | G13: TORRES | H13: BETANCOURT | I13: =+C13*-1 -> 102164
... A24: C398 | B24: PENSIÓN | C24: 1000 | D24: 93373335 | E24: 00555E07 | F24: JESUS ELKY | G24: MORA | H24: CUBILLOS | I24: =+C24*-1 -> -1000
I25: =+C25*-1 -> 0
I26: =+C26*-1 -> 0
I27: =+C27*-1 -> 0
I28: =+C28*-1 -> 0
I29: =+C29*-1 -> 0
I30: =+C30*-1 -> 0
I31: =+C31*-1 -> 0
I32: =+C32*-1 -> 0
I33: =+C33*-1 -> 0
I34: =+C34*-1 -> 0
I35: =+C35*-1 -> 0
I36: =+C36*-1 -> 0
... I45: =+C45*-1 -> 0
I46: =+C46*-1 -> 0 | J46: =+VLOOKUP(D46,Ajuste!$B$1:$K$15,12,0) -> #N/A
I47: =+C47*-1 -> 0 | J47: =+VLOOKUP(D47,Ajuste!$B$1:$K$15,12,0) -> #N/A
I48: =+C48*-1 -> 0 | J48: =+VLOOKUP(D48,Ajuste!$B$1:$K$15,12,0) -> #N/A
I49: =+C49*-1 -> 0 | J49: =+VLOOKUP(D49,Ajuste!$B$1:$K$15,12,0) -> #N/A
I50: =+C50*-1 -> 0 | J50: =+VLOOKUP(D50,Ajuste!$B$1:$K$15,12,0) -> #N/A
I51: =+C51*-1 -> 0 | J51: =+VLOOKUP(D51,Ajuste!$B$1:$K$15,12,0) -> #N/A
I52: =+C52*-1 -> 0 | J52: =+VLOOKUP(D52,Ajuste!$B$1:$K$15,12,0) -> #N/A
I53: =+C53*-1 -> 0 | J53: =+VLOOKUP(D53,Ajuste!$B$1:$K$15,12,0) -> #N/A
I54: =+C54*-1 -> 0 | J54: =+VLOOKUP(D54,Ajuste!$B$1:$K$15,12,0) -> #N/A
I55: =+C55*-1 -> 0 | J55: =+VLOOKUP(D55,Ajuste!$B$1:$K$15,12,0) -> #N/A
I56: =+C56*-1 -> 0 | J56: =+VLOOKUP(D56,Ajuste!$B$1:$K$15,12,0) -> #N/A
I57: =+C57*-1 -> 0 | J57: =+VLOOKUP(D57,Ajuste!$B$1:$K$15,12,0) -> #N/A
... I101: =+C101*-1 -> 0 | J101: =+VLOOKUP(D101,Ajuste!$B$1:$K$15,12,0) -> #N/A
I103: 370500
I104: =+I11+I12+I13+I14+I15+I16+I17+I18+I19+I20+I21+I22+I23+I24 -> 118107
I105: =+I103-I104 -> 252393

Sheet Hoja2
A1: CONCEPTO | B1: NOMBRE CONCEPTO | C1: VALOR_SALARIAL | D1: Cédula identificación | E1: CODIGO_DEL_EMPLEADO | F1: NOMBRE | G1: PRIMER APELLIDO | H1: SEGUNDO APELLIDO
A2: C396 | B2: APORTE SALUD | C2: -1850 | D2: 74324181 | E2: 00550E07 | F2: RODRIGO ALBERTO | G2: GARZON | H2: OSORIO | I2: =+C2*-1 -> 1850
A3: C397 | B3: APORTE PENSION | C3: -1824 | D3: 74324181 | E3: 00550E07 | F3: RODRIGO ALBERTO | G3: GARZON | H3: OSORIO
A4: C396 | B4: APORTE SALUD | C4: -38700 | D4: 73144545 | E4: 00695E07 | F4: JAIRO RAMON | G4: VANEGAS | H4: PATERNINA | I4: =+C4*-1 -> 38700
A5: C397 | B5: APORTE PENSION | C5: -38682 | D5: 73144545 | E5: 00695E07 | F5: JAIRO RAMON | G5: VANEGAS | H5: PATERNINA
A6: C396 | B6: APORTE SALUD | C6: -1800 | D6: 77190624 | E6: 01841E07 | F6: JOSE FERNANDO | G6: CAMARGO | H6: MAESTRE | I6: =+C6*-1 -> 1800
A7: C397 | B7: APORTE PENSION | C7: -1871 | D7: 77190624 | E7: 01841E07 | F7: JOSE FERNANDO | G7: CAMARGO | H7: MAESTRE
A8: C396 | B8: APORTE SALUD | C8: -6700 | D8: 1032470870 | E8: 01986E07 | F8: LUISA FERNANDA | G8: GIRALDO | H8: RESTREPO | I8: =+C8*-1 -> 6700
A9: C397 | B9: APORTE PENSION | C9: -6695 | D9: 1032470870 | E9: 01986E07 | F9: LUISA FERNANDA | G9: GIRALDO | H9: RESTREPO
A10: C396 | B10: APORTE SALUD | C10: -1800 | D10: 46377021 | E10: 02063E07 | F10: SANDRA | G10: GUANUMEN | H10: MOLINA | I10: =+C10*-1 -> 1800
A11: C397 | B11: APORTE PENSION | C11: -1800 | D11: 46377021 | E11: 02063E07 | F11: SANDRA | G11: GUANUMEN | H11: MOLINA
A12: C396 | B12: APORTE SALUD | C12: -2500 | D12: 1065900773 | E12: 02183E07 | F12: WILMER YESID | G12: BALLESTEROS | H12: QUINTERO | I12: =+C12*-1 -> 2500
A13: C397 | B13: APORTE PENSION | C13: -2448 | D13: 1065900773 | E13: 02183E07 | F13: WILMER YESID | G13: BALLESTEROS | H13: QUINTERO
A14: C398 | B14: FONDO SOLIDARIDAD | C14: -6800 | D14: 49794465 | E14: 02284E07 | F14: YULEMA PATRICIA | G14: CHINCHILLA | H14: BUELVAS
C16: =SUM(C2:C15) -> -113470
C17: =+C16*-1 -> 113470
